Workbook
Name SegmentaciónDeDatos_Clase: #N/A
Name SegmentaciónDeDatos_Marca1: #N/A

Sheet Datos HTML
F1: {=VLOOKUP(_xlfn.SINGLE(C:C),'[1]Price List'!$C:$H,{4,5,6},0)} -> #N/A | K1: =SUBTOTAL(9,K3:K1048576) -> 139929 | O1: =SUBTOTAL(9,O3:O1165) -> 40555 | P1: =SUBTOTAL(9,P3:P1165) -> 30146 | Q1: =SUBTOTAL(9,Q3:Q1165) -> 26943 | R1: =SUBTOTAL(9,R3:R1165) -> 26624 | S1: =SUBTOTAL(9,S3:S1165) -> 25404 | T1: =SUBTOTAL(9,T3:T1165) -> 25104 | U1: =SUBTOTAL(9,U3:U1165) -> 25155 | V1: =SUBTOTAL(9,V3:V1165) -> 25596 | ... Z1: =SUBTOTAL(9,Z3:Z1165) -> 49167 | AA1: =SUBTOTAL(9,AA3:AA1048576) -> 11828974 | AB1: =SUBTOTAL(9,AB3:AB1048576) -> 9226992.9 | AC1: =SUBTOTAL(9,AC3:AC1048576) -> 8294344.6 | AD1: =SUBTOTAL(9,AD3:AD1048576) -> 7422632 | AE1: =SUBTOTAL(9,AE3:AE1048576) -> 7355363.7 | AF1: =SUBTOTAL(9,AF3:AF1048576) -> 7105609.6 | AG1: =SUBTOTAL(9,AG3:AG1048576) -> 6920620.6 | AH1: =SUBTOTAL(9,AH3:AH1048576) -> 7596590.9 | ... AL1: =SUBTOTAL(9,AL3:AL1048576) -> 15197205
A2: Marca | B2: SKU Retail | C2: ITEM | D2: UPC | E2: Descripción | F2: Categoría | G2: Sub Categoría | H2: Clase | I2: Retail | J2: Type | K2: Roll Out | L2: Cost | M2: Status ACA | N2: Status Retail | O2: FCST Jan | P2: FCST Feb | Q2: FCST Mar | R2: FCST Apr | S2: FCST May | T2: FCST Jun | U2: FCST Jul | V2: FCST Aug | W2: FCST Sep | X2: FCST Oct | Y2: FCST Nov | Z2: FCST Dec | AA2: Jan | AB2: Feb | AC2: Mar | AD2: Apr | AE2: May | AF2: Jun | AG2: Jul | AH2: Aug | AI2: Sep | AJ2: Oct | AK2: Nov | AL2: Dec
A3: Speck | B3: 228994 | C3: 150986-D143 | D3: 840168546589 | E3: Speck Presidio2 Grip iPhone 17 Pro Max Black | F3: Cases iPhone | G3: iPhone 17 | H3: iPhone 17 Pro Max | I3: Coppel | J3: Firme | K3: 1500 | L3: 447.83 | M3: Descontinuado | N3: Discontinued | O3: {=IFERROR(VLOOKUP(_xlfn.SINGLE(B:B),'[1]Pivot SI'!$D:$AN,{6,7,8,9,10,11,12},0),0)} -> 0 | P3: 0 | Q3: 0 | R3: 260 | S3: 0 | T3: 0 | U3: 0 | V3: 0 | W3: 0 | X3: 0 | Y3: 0 | Z3: 0 | AA3: =O3*$L:$L -> 0 | AB3: =P3*$L:$L -> 0 | AC3: =Q3*$L:$L -> 0 | AD3: =R3*$L:$L -> 116435.8 | AE3: =S3*$L:$L -> 0 | AF3: =T3*$L:$L -> 0 | AG3: =U3*$L:$L -> 0 | AH3: =V3*$L:$L -> 0 | ... AL3: =Z3*$L:$L -> 0
A4: Speck | B4: 228977 | C4: 150983-3199 | D4: 840168546541 | E4: Speck Presidio Perfect-Clear Grip + Cl Clear/Clear/Silver Iphone 17 Pro Max | F4: Cases iPhone | G4: iPhone 17 | H4: iPhone 17 Pro Max | I4: Coppel | J4: Firme | K4: 1500 | L4: 447.83 | M4: Descontinuado | N4: Discontinued | O4: {=IFERROR(VLOOKUP(_xlfn.SINGLE(B:B),'[1]Pivot SI'!$D:$AN,{6,7,8,9,10,11,12},0),0)} -> 0 | P4: 0 | Q4: 0 | R4: 260 | S4: 0 | T4: 0 | U4: 0 | V4: 0 | W4: 0 | X4: 0 | Y4: 0 | Z4: 0 | AA4: =O4*$L:$L -> 0 | AB4: =P4*$L:$L -> 0 | AC4: =Q4*$L:$L -> 0 | AD4: =R4*$L:$L -> 116435.8 | AE4: =S4*$L:$L -> 0 | AF4: =T4*$L:$L -> 0 | AG4: =U4*$L:$L -> 0 | AH4: =V4*$L:$L -> 0 | ... AL4: =Z4*$L:$L -> 0
A5: Speck | B5: 228969 | C5: 150697-5085 | D5: 840168540655 | E5: Speck iPhone 16 Gemshell Grip +Ms Clear/Clear | F5: Cases iPhone | G5: iPhone | H5: iPhone 16 | I5: Coppel | J5: Firme | K5: 450 | L5: 223.69 | M5: Descontinuado | O5: {=IFERROR(VLOOKUP(_xlfn.SINGLE(B:B),'[1]Pivot SI'!$D:$AN,{6,7,8,9,10,11,12},0),0)} -> 0 | P5: 0 | Q5: 0 | R5: 650 | S5: 0 | T5: 0 | U5: 0 | V5: 0 | W5: 0 | X5: 0 | Y5: 0 | Z5: 0 | AA5: =O5*$L:$L -> 0 | AB5: =P5*$L:$L -> 0 | AC5: =Q5*$L:$L -> 0 | AD5: =R5*$L:$L -> 145398.5 | AE5: =S5*$L:$L -> 0 | AF5: =T5*$L:$L -> 0 | AG5: =U5*$L:$L -> 0 | AH5: =V5*$L:$L -> 0 | ... AL5: =Z5*$L:$L -> 0
A6: Speck | B6: 229044 | C6: 150443-3199 | D6: 840168532865 | E6: Speck Presidio® Perfect-Clear Grip Magsafe® Clicklock™ Clear/Clear/Chrome iPhone 15 | F6: Cases iPhone | G6: iPhone | H6: iPhone 16e / 15 / 14 / 13 | I6: Coppel | J6: Firme | K6: 450 | L6: 223.69 | M6: Descontinuado | O6: {=IFERROR(VLOOKUP(_xlfn.SINGLE(B:B),'[1]Pivot SI'!$D:$AN,{6,7,8,9,10,11,12},0),0)} -> 0 | P6: 0 | Q6: 0 | R6: 300 | S6: 0 | T6: 0 | U6: 0 | V6: 0 | W6: 0 | X6: 0 | Y6: 0 | Z6: 0 | AA6: =O6*$L:$L -> 0 | AB6: =P6*$L:$L -> 0 | AC6: =Q6*$L:$L -> 0 | AD6: =R6*$L:$L -> 67107 | AE6: =S6*$L:$L -> 0 | AF6: =T6*$L:$L -> 0 | AG6: =U6*$L:$L -> 0 | AH6: =V6*$L:$L -> 0 | ... AL6: =Z6*$L:$L -> 0
A7: Nomad | B7: 856504014339 | C7: NM014339858 | D7: 856504014339 | E7: Nomad Modern Leather Case - iPhone 17 Pro | Black | Nomad Leather | F7: Cases iPhone | G7: iPhone 17 | H7: iPhone 17 Pro | I7: iShop | J7: Firme | K7: 320 | L7: 521.08 | M7: Descontinuado | N7: Active | O7: 59 | P7: 82 | Q7: 24 | R7: 10 | S7: 71 | T7: 14 | U7: 50 | V7: 50 | W7: 0 | X7: 0 | Y7: 0 | Z7: 0 | AA7: =O7*$L:$L -> 30743.72 | AB7: =P7*$L:$L -> 42728.56 | AC7: =Q7*$L:$L -> 12505.92 | AD7: =R7*$L:$L -> 5210.8 | AE7: =S7*$L:$L -> 36996.68 | AF7: =T7*$L:$L -> 7295.12 | AG7: =U7*$L:$L -> 26054 | AH7: =V7*$L:$L -> 26054 | ... AL7: =Z7*$L:$L -> 0 | AN7: =C7&I7 -> NM014339858iShop | AO7: {=IFERROR(VLOOKUP(_xlfn.SINGLE(AN:AN),'[1]Pivot SI'!$R:$Y,{2,3,4,5,6,7,8},0),0)} -> 59 | AP7: 82 | AQ7: 24 | AR7: 10 | AS7: 71 | AT7: 14 | AU7: 50
A8: Nomad | B8: 856504014322 | C8: NM014322858 | D8: 856504014322 | E8: Nomad Modern Leather Case - iPhone 17 Pro | Brown | Nomad Leather | F8: Cases iPhone | G8: iPhone 17 | H8: iPhone 17 Pro | I8: iShop | J8: Firme | K8: 320 | L8: 521.08 | M8: Descontinuado | N8: Active | O8: 40 | P8: 3 | Q8: 8 | R8: 17 | S8: 56 | T8: 22 | U8: 27 | V8: 18 | W8: 0 | X8: 0 | Y8: 0 | Z8: 0 | AA8: =O8*$L:$L -> 20843.2 | AB8: =P8*$L:$L -> 1563.24 | AC8: =Q8*$L:$L -> 4168.64 | AD8: =R8*$L:$L -> 8858.36 | AE8: =S8*$L:$L -> 29180.48 | AF8: =T8*$L:$L -> 11463.76 | AG8: =U8*$L:$L -> 14069.16 | AH8: =V8*$L:$L -> 9379.44 | ... AL8: =Z8*$L:$L -> 0 | AN8: =C8&I8 -> NM014322858iShop | AO8: {=IFERROR(VLOOKUP(_xlfn.SINGLE(AN:AN),'[1]Pivot SI'!$R:$Y,{2,3,4,5,6,7,8},0),0)} -> 40 | AP8: 3 | AQ8: 8 | AR8: 17 | AS8: 56 | AT8: 22 | AU8: 27
A9: Nomad | B9: 856504014285 | C9: NM014285858 | D9: 856504014285 | E9: Nomad Modern Leather Case - iPhone 17 Pro Max | Black | Nomad Leather | F9: Cases iPhone | G9: iPhone 17 | H9: iPhone 17 Pro Max | I9: iShop | J9: Firme | K9: 320 | L9: 521.08 | M9: Descontinuado | N9: Active | O9: 152 | P9: 1 | Q9: 218 | R9: 59 | S9: 117 | T9: 49 | U9: 96 | V9: 80 | W9: 0 | X9: 0 | Y9: 0 | Z9: 0 | AA9: =O9*$L:$L -> 79204.16 | AB9: =P9*$L:$L -> 521.08 | AC9: =Q9*$L:$L -> 113595.44 | AD9: =R9*$L:$L -> 30743.72 | AE9: =S9*$L:$L -> 60966.36 | AF9: =T9*$L:$L -> 25532.92 | AG9: =U9*$L:$L -> 50023.68 | AH9: =V9*$L:$L -> 41686.4 | ... AL9: =Z9*$L:$L -> 0 | AN9: =C9&I9 -> NM014285858iShop | AO9: {=IFERROR(VLOOKUP(_xlfn.SINGLE(AN:AN),'[1]Pivot SI'!$R:$Y,{2,3,4,5,6,7,8},0),0)} -> 152 | AP9: 1 | AQ9: 218 | AR9: 59 | AS9: 117 | AT9: 49 | AU9: 96
A10: Nomad | B10: 856504014278 | C10: NM014278858 | D10: 856504014278 | E10: Nomad Modern Leather Case - iPhone 17 Pro Max | Brown | Nomad Leather | F10: Cases iPhone | G10: iPhone 17 | H10: iPhone 17 Pro Max | I10: iShop | J10: Firme | K10: 320 | L10: 521.08 | M10: Descontinuado | N10: Active | O10: 101 | P10: 155 | Q10: 185 | R10: 56 | S10: 100 | T10: 66 | U10: 74 | V10: 80 | W10: 0 | X10: 0 | Y10: 0 | Z10: 0 | AA10: =O10*$L:$L -> 52629.08 | AB10: =P10*$L:$L -> 80767.4 | AC10: =Q10*$L:$L -> 96399.8 | AD10: =R10*$L:$L -> 29180.48 | AE10: =S10*$L:$L -> 52108 | AF10: =T10*$L:$L -> 34391.28 | AG10: =U10*$L:$L -> 38559.92 | AH10: =V10*$L:$L -> 41686.4 | ... AL10: =Z10*$L:$L -> 0 | AN10: =C10&I10 -> NM014278858iShop | AO10: {=IFERROR(VLOOKUP(_xlfn.SINGLE(AN:AN),'[1]Pivot SI'!$R:$Y,{2,3,4,5,6,7,8},0),0)} -> 101 | AP10: 155 | AQ10: 185 | AR10: 56 | AS10: 100 | AT10: 66 | AU10: 74
A11: Speck | B11: 840168546428 | C11: 150976-D143 | D11: 840168546428 | E11: Speck Presidio2 Grip + MS iPhone 17 Pro Black | F11: Cases iPhone | G11: iPhone 17 | H11: iPhone 17 Pro | I11: iShop | J11: Firme | K11: 320 | L11: 387.54 | M11: Descontinuado | N11: Active | O11: 4 | P11: 0 | Q11: 2 | R11: 12 | S11: 0 | T11: 0 | U11: 55 | V11: 4 | W11: 130 | X11: 0 | Y11: 0 | Z11: 0 | AA11: =O11*$L:$L -> 1550.16 | AB11: =P11*$L:$L -> 0 | AC11: =Q11*$L:$L -> 775.08 | AD11: =R11*$L:$L -> 4650.48 | AE11: =S11*$L:$L -> 0 | AF11: =T11*$L:$L -> 0 | AG11: =U11*$L:$L -> 21314.7 | AH11: =V11*$L:$L -> 1550.16 | ... AL11: =Z11*$L:$L -> 0 | AN11: =C11&I11 -> 150976-D143iShop | AO11: {=IFERROR(VLOOKUP(_xlfn.SINGLE(AN:AN),'[1]Pivot SI'!$R:$Y,{2,3,4,5,6,7,8},0),0)} -> 0
A12: Speck | B12: 840168546411 | C12: 150975-D143 | D12: 840168546411 | E12: Speck Presidio2 + MS iPhone 17 Pro Black/Slate Grey/White | F12: Cases iPhone | G12: iPhone 17 | H12: iPhone 17 Pro | I12: iShop | J12: Firme | K12: 320 | L12: 387.54 | M12: Descontinuado | N12: Active | O12: 8 | P12: 0 | Q12: 0 | R12: 0 | S12: 26 | T12: 0 | U12: 36 | V12: 0 | W12: 0 | X12: 0 | Y12: 0 | Z12: 0 | AA12: =O12*$L:$L -> 3100.32 | AB12: =P12*$L:$L -> 0 | AC12: =Q12*$L:$L -> 0 | AD12: =R12*$L:$L -> 0 | AE12: =S12*$L:$L -> 10076.04 | AF12: =T12*$L:$L -> 0 | AG12: =U12*$L:$L -> 13951.44 | AH12: =V12*$L:$L -> 0 | ... AL12: =Z12*$L:$L -> 0 | AN12: =C12&I12 -> 150975-D143iShop | AO12: {=IFERROR(VLOOKUP(_xlfn.SINGLE(AN:AN),'[1]Pivot SI'!$R:$Y,{2,3,4,5,6,7,8},0),0)} -> 0
A13: Speck | B13: 840168547302 | C13: 151020-3261 | D13: 840168547302 | E13: Speck Presidio2 + MS iPhone 17 Pro Deep Sea/Silver Metallic/Spell Blue | F13: Cases iPhone | G13: iPhone 17 | H13: iPhone 17 Pro | I13: iShop | J13: Firme | K13: 320 | L13: 387.54 | M13: Descontinuado | N13: Active | O13: 0 | P13: 28 | Q13: 0 | R13: 8 | S13: 19 | T13: 0 | U13: 37 | V13: 17 | W13: 20 | X13: 0 | Y13: 0 | Z13: 0 | AA13: =O13*$L:$L -> 0 | AB13: =P13*$L:$L -> 10851.12 | AC13: =Q13*$L:$L -> 0 | AD13: =R13*$L:$L -> 3100.32 | AE13: =S13*$L:$L -> 7363.26 | AF13: =T13*$L:$L -> 0 | AG13: =U13*$L:$L -> 14338.98 | AH13: =V13*$L:$L -> 6588.18 | ... AL13: =Z13*$L:$L -> 0 | AN13: =C13&I13 -> 151020-3261iShop | AO13: {=IFERROR(VLOOKUP(_xlfn.SINGLE(AN:AN),'[1]Pivot SI'!$R:$Y,{2,3,4,5,6,7,8},0),0)} -> 0
A14: Speck | B14: 840168546381 | C14: 150972-3240 | D14: 840168546381 | E14: Speck Presidio Perfect-Clear iPhone 17 Pro Clear | F14: Cases iPhone | G14: iPhone 17 | H14: iPhone 17 Pro | I14: iShop | J14: Firme | K14: 320 | L14: 387.54 | M14: Descontinuado | N14: Active | O14: 27 | P14: 62 | Q14: 28 | R14: 0 | S14: 36 | T14: 52 | U14: 58 | V14: 25 | W14: 0 | X14: 0 | Y14: 0 | Z14: 0 | AA14: =O14*$L:$L -> 10463.58 | AB14: =P14*$L:$L -> 24027.48 | AC14: =Q14*$L:$L -> 10851.12 | AD14: =R14*$L:$L -> 0 | AE14: =S14*$L:$L -> 13951.44 | AF14: =T14*$L:$L -> 20152.08 | AG14: =U14*$L:$L -> 22477.32 | AH14: =V14*$L:$L -> 9688.5 | ... AL14: =Z14*$L:$L -> 0 | AN14: =C14&I14 -> 150972-3240iShop | AO14: {=IFERROR(VLOOKUP(_xlfn.SINGLE(AN:AN),'[1]Pivot SI'!$R:$Y,{2,3,4,5,6,7,8},0),0)} -> 0
A15: Speck | B15: 840168546558 | C15: 150984-D143 | D15: 840168546558 | E15: Speck Presidio2 + MS iPhone 17 Pro Max Black/Slate Grey/White | F15: Cases iPhone | G15: iPhone 17 | H15: iPhone 17 Pro Max | I15: iShop | J15: Firme | K15: 320 | L15: 387.54 | M15: Descontinuado | N15: Active | O15: 0 | P15: 133 | Q15: 44 | R15: 29 | S15: 64 | T15: 0 | U15: 16 | V15: 0 | W15: 0 | X15: 0 | Y15: 0 | Z15: 0 | AA15: =O15*$L:$L -> 0 | AB15: =P15*$L:$L -> 51542.82 | AC15: =Q15*$L:$L -> 17051.76 | AD15: =R15*$L:$L -> 11238.66 | AE15: =S15*$L:$L -> 24802.56 | AF15: =T15*$L:$L -> 0 | AG15: =U15*$L:$L -> 6200.64 | AH15: =V15*$L:$L -> 0 | ... AL15: =Z15*$L:$L -> 0 | AN15: =C15&I15 -> 150984-D143iShop | AO15: {=IFERROR(VLOOKUP(_xlfn.SINGLE(AN:AN),'[1]Pivot SI'!$R:$Y,{2,3,4,5,6,7,8},0),0)} -> 0
A16: Speck | B16: 840168547401 | C16: 151025-3261 | D16: 840168547401 | E16: Speck Presidio2 + MS iPhone 17 Pro Max Deep Sea/Silver Metallic/Spell Blue | F16: Cases iPhone | G16: iPhone 17 | H16: iPhone 17 Pro Max | I16: iShop | J16: Firme | K16: 320 | L16: 387.54 | M16: Descontinuado | N16: Active | O16: 0 | P16: 198 | Q16: 24 | R16: 2 | S16: 40 | T16: 0 | U16: 1 | V16: 0 | W16: 0 | X16: 0 | Y16: 0 | Z16: 0 | AA16: =O16*$L:$L -> 0 | AB16: =P16*$L:$L -> 76732.92 | AC16: =Q16*$L:$L -> 9300.96 | AD16: =R16*$L:$L -> 775.08 | AE16: =S16*$L:$L -> 15501.6 | AF16: =T16*$L:$L -> 0 | AG16: =U16*$L:$L -> 387.54 | AH16: =V16*$L:$L -> 0 | ... AL16: =Z16*$L:$L -> 0 | AN16: =C16&I16 -> 151025-3261iShop | AO16: {=IFERROR(VLOOKUP(_xlfn.SINGLE(AN:AN),'[1]Pivot SI'!$R:$Y,{2,3,4,5,6,7,8},0),0)} -> 0
A17: Speck | B17: 840168546527 | C17: 150981-3240 | D17: 840168546527 | E17: Speck Presidio Perfect-Clear iPhone 17 Pro Max Clear | F17: Cases iPhone | G17: iPhone 17 | H17: iPhone 17 Pro Max | I17: iShop | J17: Firme | K17: 320 | L17: 387.54 | M17: Descontinuado | N17: Active | O17: 44 | P17: 319 | Q17: 272 | R17: 105 | S17: 121 | T17: 89 | U17: 2 | V17: 70 | W17: 0 | X17: 0 | Y17: 0 | Z17: 0 | AA17: =O17*$L:$L -> 17051.76 | AB17: =P17*$L:$L -> 123625.26 | AC17: =Q17*$L:$L -> 105410.88 | AD17: =R17*$L:$L -> 40691.7 | AE17: =S17*$L:$L -> 46892.34 | AF17: =T17*$L:$L -> 34491.06 | AG17: =U17*$L:$L -> 775.08 | AH17: =V17*$L:$L -> 27127.8 | ... AL17: =Z17*$L:$L -> 0 | AN17: =C17&I17 -> 150981-3240iShop | AO17: {=IFERROR(VLOOKUP(_xlfn.SINGLE(AN:AN),'[1]Pivot SI'!$R:$Y,{2,3,4,5,6,7,8},0),0)} -> 0
A18: Speck | B18: 840168546589 | C18: 150986-D143 | D18: 840168546589 | E18: Speck Presidio2 Grip iPhone 17 Pro Max Black | F18: Cases iPhone | G18: iPhone 17 | H18: iPhone 17 Pro Max | I18: iShop | J18: Firme | K18: 320 | L18: 387.54 | M18: Descontinuado | N18: Active | O18: 0 | P18: 78 | Q18: 46 | R18: 18 | S18: 47 | T18: 2 | U18: 0 | V18: 0 | W18: 0 | X18: 0 | Y18: 0 | Z18: 0 | AA18: =O18*$L:$L -> 0 | AB18: =P18*$L:$L -> 30228.12 | AC18: =Q18*$L:$L -> 17826.84 | AD18: =R18*$L:$L -> 6975.72 | AE18: =S18*$L:$L -> 18214.38 | AF18: =T18*$L:$L -> 775.08 | AG18: =U18*$L:$L -> 0 | AH18: =V18*$L:$L -> 0 | ... AL18: =Z18*$L:$L -> 0 | AN18: =C18&I18 -> 150986-D143iShop | AO18: {=IFERROR(VLOOKUP(_xlfn.SINGLE(AN:AN),'[1]Pivot SI'!$R:$Y,{2,3,4,5,6,7,8},0),0)} -> 0
A19: Tech21 | B19: 840459607258 | C19: T21-11323 | D19: 840459607258 | E19: Tech21 EvoClear iPhone 17 Pro Clear | F19: Cases iPhone | G19: iPhone 17 | H19: iPhone 17 Pro | I19: iShop | J19: Firme | K19: 320 | L19: 387.5 | M19: Descontinuado | N19: Active | O19: 47 | P19: 49 | Q19: 16 | R19: 46 | S19: 99 | T19: 24 | U19: 48 | V19: 20 | W19: 0 | X19: 0 | Y19: 0 | Z19: 0 | AA19: =O19*$L:$L -> 18212.5 | AB19: =P19*$L:$L -> 18987.5 | AC19: =Q19*$L:$L -> 6200 | AD19: =R19*$L:$L -> 17825 | AE19: =S19*$L:$L -> 38362.5 | AF19: =T19*$L:$L -> 9300 | AG19: =U19*$L:$L -> 18600 | AH19: =V19*$L:$L -> 7750 | ... AL19: =Z19*$L:$L -> 0 | AN19: =C19&I19 -> T21-11323iShop | AO19: {=IFERROR(VLOOKUP(_xlfn.SINGLE(AN:AN),'[1]Pivot SI'!$R:$Y,{2,3,4,5,6,7,8},0),0)} -> 0
A20: Tech21 | B20: 840459607371 | C20: T21-11334 | D20: 840459607371 | E20: Tech21 EvoClear iPhone 17 Pro Max Clear | F20: Cases iPhone | G20: iPhone 17 | H20: iPhone 17 Pro Max | I20: iShop | J20: Firme | K20: 320 | L20: 387.5 | M20: Descontinuado | N20: Active | O20: 0 | P20: 236 | Q20: 215 | R20: 73 | S20: 92 | T20: 46 | U20: 25 | V20: 17 | W20: 0 | X20: 0 | Y20: 0 | Z20: 0 | AA20: =O20*$L:$L -> 0 | AB20: =P20*$L:$L -> 91450 | AC20: =Q20*$L:$L -> 83312.5 | AD20: =R20*$L:$L -> 28287.5 | AE20: =S20*$L:$L -> 35650 | AF20: =T20*$L:$L -> 17825 | AG20: =U20*$L:$L -> 9687.5 | AH20: =V20*$L:$L -> 6587.5 | ... AL20: =Z20*$L:$L -> 0 | AN20: =C20&I20 -> T21-11334iShop | AO20: {=IFERROR(VLOOKUP(_xlfn.SINGLE(AN:AN),'[1]Pivot SI'!$R:$Y,{2,3,4,5,6,7,8},0),0)} -> 0
A21: Speck | C21: 151119-5085 | E21: Speck Presidio Perfect Clear Fold + MagSafe Clear iPhone 18 FOLD | F21: Cases iPhone | G21: iPhone 18 | H21: iPhone 18 Fold | I21: iShop | J21: Firme | K21: 200 | L21: 503.92241 | M21: New | N21: New | O21: 0 | V21: 0 | W21: 250 | X21: 30 | Y21: 30 | Z21: 30 | AA21: =O21*$L:$L -> 0 | AB21: =P21*$L:$L -> 0 | AC21: =Q21*$L:$L -> 0 | AD21: =R21*$L:$L -> 0 | AE21: =S21*$L:$L -> 0 | AF21: =T21*$L:$L -> 0 | AG21: =U21*$L:$L -> 0 | AH21: =V21*$L:$L -> 0 | ... AL21: =Z21*$L:$L -> 15117.672 | AN21: =C21&I21 -> 151119-5085iShop | AO21: {=IFERROR(VLOOKUP(_xlfn.SINGLE(AN:AN),'[1]Pivot SI'!$R:$Y,{2,3,4,5,6,7,8},0),0)} -> 0
A22: Speck | C22: 151098-3240 | E22: Speck Presidio Perfect Clear + C-MagSafe/CC Clear iPhone 18 Pro | F22: Cases iPhone | G22: iPhone 18 | H22: iPhone 18 Pro | I22: iShop | J22: Firme | K22: 320 | L22: 387.54 | M22: New | N22: New | O22: 0 | V22: 0 | W22: 280 | X22: 180 | Y22: 120 | Z22: 180 | AA22: =O22*$L:$L -> 0 | AB22: =P22*$L:$L -> 0 | AC22: =Q22*$L:$L -> 0 | AD22: =R22*$L:$L -> 0 | AE22: =S22*$L:$L -> 0 | AF22: =T22*$L:$L -> 0 | AG22: =U22*$L:$L -> 0 | AH22: =V22*$L:$L -> 0 | ... AL22: =Z22*$L:$L -> 69757.2 | AN22: =C22&I22 -> 151098-3240iShop | AO22: {=IFERROR(VLOOKUP(_xlfn.SINGLE(AN:AN),'[1]Pivot SI'!$R:$Y,{2,3,4,5,6,7,8},0),0)} -> 0
A23: Speck | C23: 151096-D143 | E23: Speck Presidio2 Grip + MagSafe/CC Black iPhone 18 Pro | F23: Cases iPhone | G23: iPhone 18 | H23: iPhone 18 Pro | I23: iShop | J23: Firme | K23: 320 | L23: 387.5431 | M23: New | N23: New | O23: 0 | V23: 0 | W23: 120 | X23: 30 | Y23: 45 | Z23: 30 | AA23: =O23*$L:$L -> 0 | AB23: =P23*$L:$L -> 0 | AC23: =Q23*$L:$L -> 0 | AD23: =R23*$L:$L -> 0 | AE23: =S23*$L:$L -> 0 | AF23: =T23*$L:$L -> 0 | AG23: =U23*$L:$L -> 0 | AH23: =V23*$L:$L -> 0 | ... AL23: =Z23*$L:$L -> 11626.293 | AN23: =C23&I23 -> 151096-D143iShop | AO23: {=IFERROR(VLOOKUP(_xlfn.SINGLE(AN:AN),'[1]Pivot SI'!$R:$Y,{2,3,4,5,6,7,8},0),0)} -> 0
A24: Speck | C24: 151096-3261 | E24: Speck Presidio2 Grip + MagSafe/CC Deep Sea iPhone 18 Pro | F24: Cases iPhone | G24: iPhone 18 | H24: iPhone 18 Pro | I24: iShop | J24: Firme | K24: 320 | L24: 387.5431 | M24: New | N24: New | O24: 0 | V24: 0 | W24: 200 | X24: 35 | Y24: 35 | Z24: 35 | AA24: =O24*$L:$L -> 0 | AB24: =P24*$L:$L -> 0 | AC24: =Q24*$L:$L -> 0 | AD24: =R24*$L:$L -> 0 | AE24: =S24*$L:$L -> 0 | AF24: =T24*$L:$L -> 0 | AG24: =U24*$L:$L -> 0 | AH24: =V24*$L:$L -> 0 | ... AL24: =Z24*$L:$L -> 13564.009 | AN24: =C24&I24 -> 151096-3261iShop | AO24: {=IFERROR(VLOOKUP(_xlfn.SINGLE(AN:AN),'[1]Pivot SI'!$R:$Y,{2,3,4,5,6,7,8},0),0)} -> 0
A25: Speck | C25: 151104-9984 | E25: Speck Presidio Lux Grip + C-MagSafe/CC Obsidian iPhone 18 Pro | F25: Cases iPhone | G25: iPhone 18 | H25: iPhone 18 Pro | I25: iShop | J25: Firme | K25: 320 | L25: 387.5431 | M25: New | N25: New | O25: 0 | V25: 0 | W25: 220 | X25: 20 | Y25: 20 | Z25: 20 | AA25: =O25*$L:$L -> 0 | AB25: =P25*$L:$L -> 0 | AC25: =Q25*$L:$L -> 0 | AD25: =R25*$L:$L -> 0 | AE25: =S25*$L:$L -> 0 | AF25: =T25*$L:$L -> 0 | AG25: =U25*$L:$L -> 0 | AH25: =V25*$L:$L -> 0 | ... AL25: =Z25*$L:$L -> 7750.8621 | AN25: =C25&I25 -> 151104-9984iShop | AO25: {=IFERROR(VLOOKUP(_xlfn.SINGLE(AN:AN),'[1]Pivot SI'!$R:$Y,{2,3,4,5,6,7,8},0),0)} -> 0
A26: Speck | C26: 151110-3240 | E26: Speck Presidio Perfect Clear + C-MagSafe/CC Clear iPhone 18 Pro Max | F26: Cases iPhone | G26: iPhone 18 | H26: iPhone 18 Pro Max | I26: iShop | J26: Firme | K26: 320 | L26: 387.54 | M26: New | N26: New | O26: 0 | V26: 0 | W26: 280 | X26: 220 | Y26: 280 | Z26: 200 | AA26: =O26*$L:$L -> 0 | AB26: =P26*$L:$L -> 0 | AC26: =Q26*$L:$L -> 0 | AD26: =R26*$L:$L -> 0 | AE26: =S26*$L:$L -> 0 | AF26: =T26*$L:$L -> 0 | AG26: =U26*$L:$L -> 0 | AH26: =V26*$L:$L -> 0 | ... AL26: =Z26*$L:$L -> 77508 | AN26: =C26&I26 -> 151110-3240iShop | AO26: {=IFERROR(VLOOKUP(_xlfn.SINGLE(AN:AN),'[1]Pivot SI'!$R:$Y,{2,3,4,5,6,7,8},0),0)} -> 0
A27: Speck | C27: 151108-D143 | E27: Speck Presidio2 Grip + MagSafe/CC Black iPhone 18 Pro Max | F27: Cases iPhone | G27: iPhone 18 | H27: iPhone 18 Pro Max | I27: iShop | J27: Firme | K27: 320 | L27: 387.5431 | M27: New | N27: New | O27: 0 | V27: 0 | W27: 280 | X27: 100 | Y27: 65 | Z27: 65 | AA27: =O27*$L:$L -> 0 | AB27: =P27*$L:$L -> 0 | AC27: =Q27*$L:$L -> 0 | AD27: =R27*$L:$L -> 0 | AE27: =S27*$L:$L -> 0 | AF27: =T27*$L:$L -> 0 | AG27: =U27*$L:$L -> 0 | AH27: =V27*$L:$L -> 0 | ... AL27: =Z27*$L:$L -> 25190.302 | AN27: =C27&I27 -> 151108-D143iShop | AO27: {=IFERROR(VLOOKUP(_xlfn.SINGLE(AN:AN),'[1]Pivot SI'!$R:$Y,{2,3,4,5,6,7,8},0),0)} -> 0
A28: Speck | C28: 151108-3261 | E28: Speck Presidio2 Grip + MagSafe/CC Deep Sea iPhone 18 Pro Max | F28: Cases iPhone | G28: iPhone 18 | H28: iPhone 18 Pro Max | I28: iShop | J28: Firme | K28: 320 | L28: 387.5431 | M28: New | N28: New | O28: 0 | V28: 0 | W28: 220 | X28: 120 | Y28: 150 | Z28: 80 | AA28: =O28*$L:$L -> 0 | AB28: =P28*$L:$L -> 0 | AC28: =Q28*$L:$L -> 0 | AD28: =R28*$L:$L -> 0 | AE28: =S28*$L:$L -> 0 | AF28: =T28*$L:$L -> 0 | AG28: =U28*$L:$L -> 0 | AH28: =V28*$L:$L -> 0 | ... AL28: =Z28*$L:$L -> 31003.448 | AN28: =C28&I28 -> 151108-3261iShop | AO28: {=IFERROR(VLOOKUP(_xlfn.SINGLE(AN:AN),'[1]Pivot SI'!$R:$Y,{2,3,4,5,6,7,8},0),0)} -> 0
A29: Speck | C29: 151116-9984 | E29: Speck Presidio Lux Grip + C-MagSafe/CC Obsidian iPhone 18 Pro Max | F29: Cases iPhone | G29: iPhone 18 | H29: iPhone 18 Pro Max | I29: iShop | J29: Firme | K29: 320 | L29: 387.5431 | M29: New | N29: New | O29: 0 | V29: 0 | W29: 250 | X29: 30 | Y29: 30 | Z29: 30 | AA29: =O29*$L:$L -> 0 | AB29: =P29*$L:$L -> 0 | AC29: =Q29*$L:$L -> 0 | AD29: =R29*$L:$L -> 0 | AE29: =S29*$L:$L -> 0 | AF29: =T29*$L:$L -> 0 | AG29: =U29*$L:$L -> 0 | AH29: =V29*$L:$L -> 0 | ... AL29: =Z29*$L:$L -> 11626.293 | AN29: =C29&I29 -> 151116-9984iShop | AO29: {=IFERROR(VLOOKUP(_xlfn.SINGLE(AN:AN),'[1]Pivot SI'!$R:$Y,{2,3,4,5,6,7,8},0),0)} -> 0
A30: Tech21 | C30: T21-11730 | E30: Tech21 EvoClear w/MagSafe Clear iPhone 18 FOLD | F30: Cases iPhone | G30: iPhone 18 | H30: iPhone 18 Fold | I30: iShop | J30: Firme | K30: 200 | L30: 559.91379 | M30: New | N30: New | O30: 0 | V30: 0 | W30: 250 | X30: 50 | Y30: 50 | Z30: 50 | AA30: =O30*$L:$L -> 0 | AB30: =P30*$L:$L -> 0 | AC30: =Q30*$L:$L -> 0 | AD30: =R30*$L:$L -> 0 | AE30: =S30*$L:$L -> 0 | AF30: =T30*$L:$L -> 0 | AG30: =U30*$L:$L -> 0 | AH30: =V30*$L:$L -> 0 | ... AL30: =Z30*$L:$L -> 27995.69 | AN30: =C30&I30 -> T21-11730iShop | AO30: {=IFERROR(VLOOKUP(_xlfn.SINGLE(AN:AN),'[1]Pivot SI'!$R:$Y,{2,3,4,5,6,7,8},0),0)} -> 0
A31: Tech21 | C31: T21-11655 | E31: Tech21 EvoClear w/C-MagSafe/CC Clear iPhone 18 Pro | F31: Cases iPhone | G31: iPhone 18 | H31: iPhone 18 Pro | I31: iShop | J31: Firme | K31: 320 | L31: 387.5 | M31: New | N31: New | O31: 0 | V31: 0 | W31: 300 | X31: 100 | Y31: 120 | Z31: 80 | AA31: =O31*$L:$L -> 0 | AB31: =P31*$L:$L -> 0 | AC31: =Q31*$L:$L -> 0 | AD31: =R31*$L:$L -> 0 | AE31: =S31*$L:$L -> 0 | AF31: =T31*$L:$L -> 0 | AG31: =U31*$L:$L -> 0 | AH31: =V31*$L:$L -> 0 | ... AL31: =Z31*$L:$L -> 31000 | AN31: =C31&I31 -> T21-11655iShop | AO31: {=IFERROR(VLOOKUP(_xlfn.SINGLE(AN:AN),'[1]Pivot SI'!$R:$Y,{2,3,4,5,6,7,8},0),0)} -> 0
A32: Tech21 | C32: T21-11740 | E32: Tech21 Apple AP-1041 EvoClear w/C-MagSafe/CC - Mandala Pattern | F32: Cases iPhone | G32: iPhone 18 | H32: iPhone 18 Pro | I32: iShop | J32: Firme | K32: 320 | L32: 430.60345 | M32: New | N32: New | O32: 0 | V32: 0 | W32: 360 | X32: 45 | Y32: 80 | Z32: 80 | AA32: =O32*$L:$L -> 0 | AB32: =P32*$L:$L -> 0 | AC32: =Q32*$L:$L -> 0 | AD32: =R32*$L:$L -> 0 | AE32: =S32*$L:$L -> 0 | AF32: =T32*$L:$L -> 0 | AG32: =U32*$L:$L -> 0 | AH32: =V32*$L:$L -> 0 | ... AL32: =Z32*$L:$L -> 34448.276 | AN32: =C32&I32 -> T21-11740iShop | AO32: {=IFERROR(VLOOKUP(_xlfn.SINGLE(AN:AN),'[1]Pivot SI'!$R:$Y,{2,3,4,5,6,7,8},0),0)} -> 0
... A46: Nomad | C46: NM009162858 | E46: Nomad Modern Leather Case - iPhone 18 Pro Max | Brown | Nomad Leather | F46: Cases iPhone | G46: iPhone 18 | H46: iPhone 18 Pro Max | I46: iShop | J46: Firme | K46: 320 | L46: 473.7069 | M46: New | N46: New | O46: 0 | V46: 0 | W46: 280 | X46: 180 | Y46: 210 | Z46: 150 | AA46: =O46*$L:$L -> 0 | AB46: =P46*$L:$L -> 0 | AC46: =Q46*$L:$L -> 0 | AD46: =R46*$L:$L -> 0 | AE46: =S46*$L:$L -> 0 | AF46: =T46*$L:$L -> 0 | AG46: =U46*$L:$L -> 0 | AH46: =V46*$L:$L -> 0 | ... AL46: =Z46*$L:$L -> 71056.034 | AN46: =C46&I46 -> NM009162858iShop | AO46: {=IFERROR(VLOOKUP(_xlfn.SINGLE(AN:AN),'[1]Pivot SI'!$R:$Y,{2,3,4,5,6,7,8},0),0)} -> 0
A47: Nomad | B47: 856504011291 | C47: NM011291858 | D47: 856504011291 | E47: Nomad Modern Leather Case - Airpods Pro 3 | Black | Horween | F47: Cases Airpods | G47: Airpods | H47: Airpods Pro 3 | I47: iShop | J47: Firme | K47: 220 | L47: 344.4 | M47: Activo | N47: Active | O47: 221 | P47: 137 | Q47: 177 | R47: 62 | S47: 168 | T47: 76 | U47: 56 | V47: 80 | W47: 80 | X47: 30 | Y47: 30 | Z47: 30 | AA47: =O47*$L:$L -> 76112.4 | AB47: =P47*$L:$L -> 47182.8 | AC47: =Q47*$L:$L -> 60958.8 | AD47: =R47*$L:$L -> 21352.8 | AE47: =S47*$L:$L -> 57859.2 | AF47: =T47*$L:$L -> 26174.4 | AG47: =U47*$L:$L -> 19286.4 | AH47: =V47*$L:$L -> 27552 | ... AL47: =Z47*$L:$L -> 10332 | AN47: =C47&I47 -> NM011291858iShop | AO47: {=IFERROR(VLOOKUP(_xlfn.SINGLE(AN:AN),'[1]Pivot SI'!$R:$Y,{2,3,4,5,6,7,8},0),0)} -> 221 | AP47: 137 | AQ47: 177 | AR47: 62 | AS47: 168 | AT47: 76 | AU47: 56
A48: Nomad | B48: 856504011284 | C48: NM011284858 | D48: 856504011284 | E48: Nomad Modern Leather Case - Airpods Pro 3 | Rustic Brown | Horween | F48: Cases Airpods | G48: Airpods | H48: Airpods Pro 3 | I48: iShop | J48: Firme | K48: 220 | L48: 344.4 | M48: Activo | N48: Active | O48: 214 | P48: 97 | Q48: 121 | R48: 51 | S48: 107 | T48: 77 | U48: 29 | V48: 80 | W48: 80 | X48: 84 | Y48: 30 | Z48: 30 | AA48: =O48*$L:$L -> 73701.6 | AB48: =P48*$L:$L -> 33406.8 | AC48: =Q48*$L:$L -> 41672.4 | AD48: =R48*$L:$L -> 17564.4 | AE48: =S48*$L:$L -> 36850.8 | AF48: =T48*$L:$L -> 26518.8 | AG48: =U48*$L:$L -> 9987.6 | AH48: =V48*$L:$L -> 27552 | ... AL48: =Z48*$L:$L -> 10332 | AN48: =C48&I48 -> NM011284858iShop | AO48: {=IFERROR(VLOOKUP(_xlfn.SINGLE(AN:AN),'[1]Pivot SI'!$R:$Y,{2,3,4,5,6,7,8},0),0)} -> 214 | AP48: 97 | AQ48: 121 | AR48: 51 | AS48: 107 | AT48: 77 | AU48: 29
A49: Nomad | B49: 856500018522 | C49: NM1Am10000 | D49: 856500018522 | E49: Nomad Sport Strap - 45/44mm/42mm | M/L | Black | FKM | V2 | F49: Straps | G49: Apple Watch | H49: 49/45/44/42 mm | I49: iShop | J49: Firme | K49: 200 | L49: 473.71 | M49: Activo | N49: Active | O49: 100 | P49: 126 | Q49: 192 | R49: 118 | S49: 260 | T49: 91 | U49: 90 | V49: 144 | W49: 120 | X49: 291 | Y49: 250 | Z49: 200 | AA49: =O49*$L:$L -> 47371 | AB49: =P49*$L:$L -> 59687.46 | AC49: =Q49*$L:$L -> 90952.32 | AD49: =R49*$L:$L -> 55897.78 | AE49: =S49*$L:$L -> 123164.6 | AF49: =T49*$L:$L -> 43107.61 | AG49: =U49*$L:$L -> 42633.9 | AH49: =V49*$L:$L -> 68214.24 | ... AL49: =Z49*$L:$L -> 94742 | AN49: =C49&I49 -> NM1Am10000iShop | AO49: {=IFERROR(VLOOKUP(_xlfn.SINGLE(AN:AN),'[1]Pivot SI'!$R:$Y,{2,3,4,5,6,7,8},0),0)} -> 100 | AP49: 126 | AQ49: 192 | AR49: 118 | AS49: 260 | AT49: 91 | AU49: 90
A50: Nomad | B50: 855848007366 | C50: NM00736685 | D50: 855848007366 | E50: Nomad Sport Band - 45mm | Ultra Orange | F50: Straps | G50: Apple Watch | H50: 49/45/44/42 mm | I50: iShop | J50: Firme | K50: 200 | L50: 473.71 | M50: Activo | N50: Active | O50: 1 | P50: 162 | Q50: 239 | R50: 106 | S50: 174 | T50: 66 | U50: 72 | V50: 150 | W50: 120 | X50: 80 | Y50: 362 | Z50: 110 | AA50: =O50*$L:$L -> 473.71 | AB50: =P50*$L:$L -> 76741.02 | AC50: =Q50*$L:$L -> 113216.69 | AD50: =R50*$L:$L -> 50213.26 | AE50: =S50*$L:$L -> 82425.54 | AF50: =T50*$L:$L -> 31264.86 | AG50: =U50*$L:$L -> 34107.12 | AH50: =V50*$L:$L -> 71056.5 | ... AL50: =Z50*$L:$L -> 52108.1 | AN50: =C50&I50 -> NM00736685iShop | AO50: {=IFERROR(VLOOKUP(_xlfn.SINGLE(AN:AN),'[1]Pivot SI'!$R:$Y,{2,3,4,5,6,7,8},0),0)} -> 1 | AP50: 162 | AQ50: 239 | AR50: 106 | AS50: 174 | AT50: 66 | AU50: 72
A51: Nomad | B51: 856504014919 | C51: NM014919858 | D51: 856504014919 | E51: Nomad Sport Band - 49/45/44mm/42mm | M/L | Naval | F51: Straps | G51: Apple Watch | H51: 49/45/44/42 mm | I51: iShop | J51: Firme | K51: 200 | L51: 473.71 | M51: Activo2 | N51: Active | O51: 1 | P51: 0 | Q51: 152 | R51: 84 | S51: 24 | T51: 67 | U51: 91 | V51: 80 | W51: 80 | X51: 90 | Y51: 110 | Z51: 80 | AA51: =O51*$L:$L -> 473.71 | AB51: =P51*$L:$L -> 0 | AC51: =Q51*$L:$L -> 72003.92 | AD51: =R51*$L:$L -> 39791.64 | AE51: =S51*$L:$L -> 11369.04 | AF51: =T51*$L:$L -> 31738.57 | AG51: =U51*$L:$L -> 43107.61 | AH51: =V51*$L:$L -> 37896.8 | ... AL51: =Z51*$L:$L -> 37896.8 | AN51: =C51&I51 -> NM014919858iShop | AO51: {=IFERROR(VLOOKUP(_xlfn.SINGLE(AN:AN),'[1]Pivot SI'!$R:$Y,{2,3,4,5,6,7,8},0),0)} -> 1 | AP51: 0 | AQ51: 152 | AR51: 84 | AS51: 24 | AT51: 67 | AU51: 91
A52: Nomad | B52: 856504014803 | C52: NM014803858 | D52: 856504014803 | E52: Nomad Rocky Point Band - 46mm/49mm | Storm | Black Hardware | F52: Straps | G52: Apple Watch | H52: 49/45/44/42 mm | I52: iShop | J52: Firme | K52: 180 | L52: 775.43 | M52: Activo2 | N52: Active | O52: 0 | P52: 171 | Q52: 154 | R52: 92 | S52: 171 | T52: 6 | U52: 78 | V52: 37 | AA52: =O52*$L:$L -> 0 | AB52: =P52*$L:$L -> 132598.53 | AC52: =Q52*$L:$L -> 119416.22 | AD52: =R52*$L:$L -> 71339.56 | AE52: =S52*$L:$L -> 132598.53 | AF52: =T52*$L:$L -> 4652.58 | AG52: =U52*$L:$L -> 60483.54 | AH52: =V52*$L:$L -> 28690.91 | ... AL52: =Z52*$L:$L -> 0 | AN52: =C52&I52 -> NM014803858iShop | AO52: {=IFERROR(VLOOKUP(_xlfn.SINGLE(AN:AN),'[1]Pivot SI'!$R:$Y,{2,3,4,5,6,7,8},0),0)} -> 0 | AP52: 171 | AQ52: 154 | AR52: 92 | AS52: 171 | AT52: 6 | AU52: 78
A53: Nomad | B53: 856504014827 | C53: NM014827858 | D53: 856504014827 | E53: Nomad Rocky Point Band - 46mm/49mm | Atlantic | Black Hardware | F53: Straps | G53: Apple Watch | H53: 49/45/44/42 mm | I53: iShop | J53: Firme | K53: 180 | L53: 775.43 | M53: Activo | N53: Active | O53: 0 | P53: 154 | Q53: 77 | R53: 0 | S53: 82 | T53: 35 | U53: 49 | V53: 18 | W53: 0 | X53: 95 | Y53: 40 | Z53: 65 | AA53: =O53*$L:$L -> 0 | AB53: =P53*$L:$L -> 119416.22 | AC53: =Q53*$L:$L -> 59708.11 | AD53: =R53*$L:$L -> 0 | AE53: =S53*$L:$L -> 63585.26 | AF53: =T53*$L:$L -> 27140.05 | AG53: =U53*$L:$L -> 37996.07 | AH53: =V53*$L:$L -> 13957.74 | ... AL53: =Z53*$L:$L -> 50402.95 | AN53: =C53&I53 -> NM014827858iShop | AO53: {=IFERROR(VLOOKUP(_xlfn.SINGLE(AN:AN),'[1]Pivot SI'!$R:$Y,{2,3,4,5,6,7,8},0),0)} -> 0 | AP53: 154 | AQ53: 77 | AR53: 0 | AS53: 82 | AT53: 35 | AU53: 49
A54: Speck | B54: 840168528202 | C54: 150226-7265 | D54: 840168528202 | E54: Speck Balance Folio Case for iPad 10th Gen - Plumberry/Crushed Purple/Crepe Pink | F54: Cases iPad | G54: iPad | H54: iPad 10th /11th - 10.9"/11" (2022-2025) | I54: iShop | J54: Firme | K54: 270 | L54: 430.6 | M54: Activo | N54: Active | O54: 69 | P54: 112 | Q54: 284 | R54: 105 | S54: 254 | T54: 17 | U54: 0 | V54: 268 | W54: 120 | X54: 90 | Y54: 320 | Z54: 110 | AA54: =O54*$L:$L -> 29711.4 | AB54: =P54*$L:$L -> 48227.2 | AC54: =Q54*$L:$L -> 122290.4 | AD54: =R54*$L:$L -> 45213 | AE54: =S54*$L:$L -> 109372.4 | AF54: =T54*$L:$L -> 7320.2 | AG54: =U54*$L:$L -> 0 | AH54: =V54*$L:$L -> 115400.8 | ... AL54: =Z54*$L:$L -> 47366 | AN54: =C54&I54 -> 150226-7265iShop | AO54: {=IFERROR(VLOOKUP(_xlfn.SINGLE(AN:AN),'[1]Pivot SI'!$R:$Y,{2,3,4,5,6,7,8},0),0)} -> 69 | AP54: 112 | AQ54: 284 | AR54: 105 | AS54: 254 | AT54: 17 | AU54: 0
A55: Speck | B55: 840168528172 | C55: 150226-9969 | D55: 840168528172 | E55: Speck Balance Folio Case for iPad 10th Gen - Almond Milk /Mocha/Charcoal | F55: Cases iPad | G55: iPad | H55: iPad 10th /11th - 10.9"/11" (2022-2025) | I55: iShop | J55: Firme | K55: 270 | L55: 430.6 | M55: Activo | N55: Active | O55: 89 | P55: 116 | Q55: 191 | R55: 76 | S55: 67 | T55: 85 | U55: 73 | V55: 175 | W55: 123 | X55: 80 | Y55: 280 | Z55: 70 | AA55: =O55*$L:$L -> 38323.4 | AB55: =P55*$L:$L -> 49949.6 | AC55: =Q55*$L:$L -> 82244.6 | AD55: =R55*$L:$L -> 32725.6 | AE55: =S55*$L:$L -> 28850.2 | AF55: =T55*$L:$L -> 36601 | AG55: =U55*$L:$L -> 31433.8 | AH55: =V55*$L:$L -> 75355 | ... AL55: =Z55*$L:$L -> 30142 | AN55: =C55&I55 -> 150226-9969iShop | AO55: {=IFERROR(VLOOKUP(_xlfn.SINGLE(AN:AN),'[1]Pivot SI'!$R:$Y,{2,3,4,5,6,7,8},0),0)} -> 89 | AP55: 116 | AQ55: 191 | AR55: 76 | AS55: 67 | AT55: 85 | AU55: 73
A56: Speck | B56: 840168528165 | C56: 150226-D143 | D56: 840168528165 | E56: Speck Balance Folio Case for iPad 10th Gen - Black/Black/White | F56: Cases iPad | G56: iPad | H56: iPad 10th /11th - 10.9"/11" (2022-2025) | I56: iShop | J56: Firme | K56: 270 | L56: 473.71 | M56: Activo | N56: Active | O56: 133 | P56: 154 | Q56: 130 | R56: 74 | S56: 148 | T56: 69 | U56: 49 | V56: 244 | W56: 134 | X56: 80 | Y56: 300 | Z56: 70 | AA56: =O56*$L:$L -> 63003.43 | AB56: =P56*$L:$L -> 72951.34 | AC56: =Q56*$L:$L -> 61582.3 | AD56: =R56*$L:$L -> 35054.54 | AE56: =S56*$L:$L -> 70109.08 | AF56: =T56*$L:$L -> 32685.99 | AG56: =U56*$L:$L -> 23211.79 | AH56: =V56*$L:$L -> 115585.24 | ... AL56: =Z56*$L:$L -> 33159.7 | AN56: =C56&I56 -> 150226-D143iShop | AO56: {=IFERROR(VLOOKUP(_xlfn.SINGLE(AN:AN),'[1]Pivot SI'!$R:$Y,{2,3,4,5,6,7,8},0),0)} -> 133 | AP56: 154 | AQ56: 130 | AR56: 74 | AS56: 148 | AT56: 69 | AU56: 49
A57: Speck | B57: 840168546688 | C57: 150989-3267 | D57: 840168546688 | E57: Speck Balance Folio iPad 11" (2022-2025) Ceramic Grey/Autumn Sky/Black | F57: Cases iPad | G57: iPad | H57: iPad 10th /11th - 10.9"/11" (2022-2025) | I57: iShop | J57: Firme | K57: 270 | L57: 430.6 | M57: Activo | N57: Active | O57: 0 | P57: 0 | Q57: 227 | R57: 73 | S57: 156 | T57: 41 | U57: 0 | V57: 120 | W57: 80 | X57: 70 | Y57: 80 | Z57: 80 | AA57: =O57*$L:$L -> 0 | AB57: =P57*$L:$L -> 0 | AC57: =Q57*$L:$L -> 97746.2 | AD57: =R57*$L:$L -> 31433.8 | AE57: =S57*$L:$L -> 67173.6 | AF57: =T57*$L:$L -> 17654.6 | AG57: =U57*$L:$L -> 0 | AH57: =V57*$L:$L -> 51672 | ... AL57: =Z57*$L:$L -> 34448 | AN57: =C57&I57 -> 150989-3267iShop | AO57: {=IFERROR(VLOOKUP(_xlfn.SINGLE(AN:AN),'[1]Pivot SI'!$R:$Y,{2,3,4,5,6,7,8},0),0)} -> 0
A58: Speck | B58: 840168507573 | C58: 142573-1050 | D58: 840168507573 | E58: Speck Balance Folio with Microban for iPad mini 6 - Black | F58: Cases iPad | G58: iPad | H58: iPad mini 6 | I58: iShop | J58: Firme | K58: 270 | L58: 344.4 | M58: Descontinuado | N58: Active | O58: 0 | P58: 166 | Q58: 121 | R58: 0 | S58: 231 | T58: 108 | U58: 88 | V58: 60 | W58: 40 | X58: 0 | Y58: 0 | Z58: 0 | AA58: =O58*$L:$L -> 0 | AB58: =P58*$L:$L -> 57170.4 | AC58: =Q58*$L:$L -> 41672.4 | AD58: =R58*$L:$L -> 0 | AE58: =S58*$L:$L -> 79556.4 | AF58: =T58*$L:$L -> 37195.2 | AG58: =U58*$L:$L -> 30307.2 | AH58: =V58*$L:$L -> 20664 | ... AL58: =Z58*$L:$L -> 0 | AN58: =C58&I58 -> 142573-1050iShop | AO58: {=IFERROR(VLOOKUP(_xlfn.SINGLE(AN:AN),'[1]Pivot SI'!$R:$Y,{2,3,4,5,6,7,8},0),0)} -> 0 | AP58: 166 | AQ58: 121 | AR58: 0 | AS58: 231 | AT58: 108 | AU58: 88
A59: Speck | B59: 840168501823 | C59: 140999-1050 | D59: 840168501823 | E59: Speck Presidio Pro Folio Case for iPad Pro 11" 2/M1/M2 /Air 10.9" 4/5 - Black | F59: Cases iPad | G59: iPad | H59: iPad Pro 11" 2/3 | I59: iShop | J59: Firme | K59: 270 | L59: 516.81 | M59: Activo | N59: Active | O59: 93 | P59: 66 | Q59: 134 | R59: 30 | S59: 64 | T59: 31 | U59: 42 | V59: 147 | W59: 35 | X59: 60 | Y59: 98 | Z59: 52 | AA59: =O59*$L:$L -> 48063.33 | AB59: =P59*$L:$L -> 34109.46 | AC59: =Q59*$L:$L -> 69252.54 | AD59: =R59*$L:$L -> 15504.3 | AE59: =S59*$L:$L -> 33075.84 | AF59: =T59*$L:$L -> 16021.11 | AG59: =U59*$L:$L -> 21706.02 | AH59: =V59*$L:$L -> 75971.07 | ... AL59: =Z59*$L:$L -> 26874.12 | AN59: =C59&I59 -> 140999-1050iShop | AO59: {=IFERROR(VLOOKUP(_xlfn.SINGLE(AN:AN),'[1]Pivot SI'!$R:$Y,{2,3,4,5,6,7,8},0),0)} -> 93 | AP59: 66 | AQ59: 134 | AR59: 30 | AS59: 64 | AT59: 31 | AU59: 42
A60: Speck | B60: 840168501106 | C60: 140548-1050 | D60: 840168501106 | E60: Speck Balance Folio Case with Microban for iPad Pro 11" M1/Air 10.9" - Black | F60: Cases iPad | G60: iPad | H60: iPad Pro 11" 2/3/4/Air 4/5 | I60: iShop | J60: Firme | K60: 270 | L60: 430.6 | M60: Activo | N60: Active | O60: 55 | P60: 0 | Q60: 0 | R60: 0 | S60: 104 | T60: 40 | U60: 49 | V60: 164 | W60: 50 | X60: 70 | Y60: 110 | Z60: 60 | AA60: =O60*$L:$L -> 23683 | AB60: =P60*$L:$L -> 0 | AC60: =Q60*$L:$L -> 0 | AD60: =R60*$L:$L -> 0 | AE60: =S60*$L:$L -> 44782.4 | AF60: =T60*$L:$L -> 17224 | AG60: =U60*$L:$L -> 21099.4 | AH60: =V60*$L:$L -> 70618.4 | ... AL60: =Z60*$L:$L -> 25836 | AN60: =C60&I60 -> 140548-1050iShop | AO60: {=IFERROR(VLOOKUP(_xlfn.SINGLE(AN:AN),'[1]Pivot SI'!$R:$Y,{2,3,4,5,6,7,8},0),0)} -> 55 | AP60: 0 | AQ60: 0 | AR60: 0 | AS60: 104 | AT60: 40 | AU60: 49
A61: Speck | B61: 840168501335 | C61: 140548-7265 | D61: 840168501335 | E61: Speck Balance Folio for iPad Air 10.9"/Pro 11" - Plumberry Purple/Crushed Purple/C | F61: Cases iPad | G61: iPad | H61: iPad Pro 11" 2/3/4/Air 4/5 | I61: iShop | J61: Firme | K61: 0 | L61: 430.6 | M61: Descontinuado | N61: Discontinued | O61: 104 | P61: 73 | Q61: 76 | R61: 9 | S61: 0 | T61: 0 | U61: 0 | V61: 0 | W61: 0 | X61: 0 | Y61: 0 | Z61: 0 | AA61: =O61*$L:$L -> 44782.4 | AB61: =P61*$L:$L -> 31433.8 | AC61: =Q61*$L:$L -> 32725.6 | AD61: =R61*$L:$L -> 3875.4 | AE61: =S61*$L:$L -> 0 | AF61: =T61*$L:$L -> 0 | AG61: =U61*$L:$L -> 0 | AH61: =V61*$L:$L -> 0 | ... AL61: =Z61*$L:$L -> 0 | AN61: =C61&I61 -> 140548-7265iShop | AO61: {=IFERROR(VLOOKUP(_xlfn.SINGLE(AN:AN),'[1]Pivot SI'!$R:$Y,{2,3,4,5,6,7,8},0),0)} -> 104 | AP61: 73 | AQ61: 76 | AR61: 9 | AS61: 0 | AT61: 0 | AU61: 0
A62: Speck | B62: 840168536160 | C62: 150525-D143 | D62: 840168536160 | E62: Speck BALANCE FOLIO APPLE 11" IPAD PRO CASES - Black | F62: Cases iPad | G62: iPad | H62: iPad Pro 11" M3/M4 | I62: iShop | J62: Firme | K62: 170 | L62: 430.6 | M62: Activo | N62: Active | O62: 10 | P62: 45 | Q62: 39 | R62: 7 | S62: 34 | T62: 23 | U62: 16 | V62: 45 | W62: 15 | X62: 25 | Y62: 35 | Z62: 15 | AA62: =O62*$L:$L -> 4306 | AB62: =P62*$L:$L -> 19377 | AC62: =Q62*$L:$L -> 16793.4 | AD62: =R62*$L:$L -> 3014.2 | AE62: =S62*$L:$L -> 14640.4 | AF62: =T62*$L:$L -> 9903.8 | AG62: =U62*$L:$L -> 6889.6 | AH62: =V62*$L:$L -> 19377 | ... AL62: =Z62*$L:$L -> 6459 | AN62: =C62&I62 -> 150525-D143iShop | AO62: {=IFERROR(VLOOKUP(_xlfn.SINGLE(AN:AN),'[1]Pivot SI'!$R:$Y,{2,3,4,5,6,7,8},0),0)} -> 10 | AP62: 45 | AQ62: 39 | AR62: 7 | AS62: 34 | AT62: 23 | AU62: 16
A63: Speck | B63: 840168536320 | C63: 150527-D143 | D63: 840168536320 | E63: Speck BALANCE FOLIO APPLE 13" IPAD PRO CASES - Black | F63: Cases iPad | G63: iPad | H63: iPad Pro 13" M4 | I63: iShop | J63: Firme | K63: 170 | L63: 516.81 | M63: Activo | N63: Active | O63: 22 | P63: 31 | Q63: 0 | R63: 0 | S63: 0 | T63: 37 | U63: 12 | V63: 39 | W63: 28 | X63: 25 | Y63: 25 | Z63: 18 | AA63: =O63*$L:$L -> 11369.82 | AB63: =P63*$L:$L -> 16021.11 | AC63: =Q63*$L:$L -> 0 | AD63: =R63*$L:$L -> 0 | AE63: =S63*$L:$L -> 0 | AF63: =T63*$L:$L -> 19121.97 | AG63: =U63*$L:$L -> 6201.72 | AH63: =V63*$L:$L -> 20155.59 | ... AL63: =Z63*$L:$L -> 9302.58 | AN63: =C63&I63 -> 150527-D143iShop | AO63: {=IFERROR(VLOOKUP(_xlfn.SINGLE(AN:AN),'[1]Pivot SI'!$R:$Y,{2,3,4,5,6,7,8},0),0)} -> 22 | AP63: 31 | AQ63: 0 | AR63: 0 | AS63: 0 | AT63: 37 | AU63: 12
A64: Speck | B64: 848709095855 | C64: 138616-1212 | D64: 848709095855 | E64: Speck Smartshell Case for Macbook Air 13" Retina 2020 - Clear | F64: Cases Macbook | G64: Macbook | H64: MacBook Air 13" M1 Cases | I64: iShop | J64: Firme | K64: 0 | L64: 430.6 | M64: Descontinuado | N64: Discontinued | O64: 0 | P64: 0 | Q64: 0 | R64: 0 | S64: 0 | T64: 0 | U64: 0 | V64: 0 | W64: 0 | X64: 0 | Y64: 0 | Z64: 0 | AA64: =O64*$L:$L -> 0 | AB64: =P64*$L:$L -> 0 | AC64: =Q64*$L:$L -> 0 | AD64: =R64*$L:$L -> 0 | AE64: =S64*$L:$L -> 0 | AF64: =T64*$L:$L -> 0 | AG64: =U64*$L:$L -> 0 | AH64: =V64*$L:$L -> 0 | ... AL64: =Z64*$L:$L -> 0 | AN64: =C64&I64 -> 138616-1212iShop | AO64: {=IFERROR(VLOOKUP(_xlfn.SINGLE(AN:AN),'[1]Pivot SI'!$R:$Y,{2,3,4,5,6,7,8},0),0)} -> 0 | AP64: 0 | AQ64: 0 | AR64: 0 | AS64: 0 | AT64: 0 | AU64: 0
A65: Speck | B65: 848709097941 | C65: 138970-9352 | D65: 848709097941 | E65: Speck Smartshell Case for Macbook Air 13" Retina M1 2020 - Swell Blue | F65: Cases Macbook | G65: Macbook | H65: MacBook Air 13" M1 Cases | I65: iShop | J65: Firme | K65: 0 | L65: 697.76 | M65: Descontinuado | N65: Discontinued | O65: 0 | P65: 0 | Q65: 0 | R65: 0 | S65: 0 | T65: 0 | U65: 0 | V65: 0 | W65: 0 | X65: 0 | Y65: 0 | Z65: 0 | AA65: =O65*$L:$L -> 0 | AB65: =P65*$L:$L -> 0 | AC65: =Q65*$L:$L -> 0 | AD65: =R65*$L:$L -> 0 | AE65: =S65*$L:$L -> 0 | AF65: =T65*$L:$L -> 0 | AG65: =U65*$L:$L -> 0 | AH65: =V65*$L:$L -> 0 | ... AL65: =Z65*$L:$L -> 0 | AN65: =C65&I65 -> 138970-9352iShop | AO65: {=IFERROR(VLOOKUP(_xlfn.SINGLE(AN:AN),'[1]Pivot SI'!$R:$Y,{2,3,4,5,6,7,8},0),0)} -> 0 | AP65: 0 | AQ65: 0 | AR65: 0 | AS65: 0 | AT65: 0 | AU65: 0
A66: Speck | B66: 848709095848 | C66: 138616-0581 | D66: 848709095848 | E66: Speck Smartshell Onyx Black MacBook Air 13 Retina Display 2020 | F66: Cases Macbook | G66: Macbook | H66: MacBook Air 13" M2 Cases | I66: iShop | J66: Firme | K66: 0 | L66: 697.76 | M66: Descontinuado | N66: Discontinued | O66: 0 | P66: 0 | Q66: 0 | R66: 0 | S66: 0 | T66: 0 | U66: 0 | V66: 0 | W66: 0 | X66: 0 | Y66: 0 | Z66: 0 | AA66: =O66*$L:$L -> 0 | AB66: =P66*$L:$L -> 0 | AC66: =Q66*$L:$L -> 0 | AD66: =R66*$L:$L -> 0 | AE66: =S66*$L:$L -> 0 | AF66: =T66*$L:$L -> 0 | AG66: =U66*$L:$L -> 0 | AH66: =V66*$L:$L -> 0 | ... AL66: =Z66*$L:$L -> 0 | AN66: =C66&I66 -> 138616-0581iShop | AO66: {=IFERROR(VLOOKUP(_xlfn.SINGLE(AN:AN),'[1]Pivot SI'!$R:$Y,{2,3,4,5,6,7,8},0),0)} -> 0 | AP66: 0 | AQ66: 0 | AR66: 0 | AS66: 0 | AT66: 0 | AU66: 0
A67: Speck | B67: 848709071354 | C67: 126087-6010 | D67: 848709071354 | E67: Speck Smartshell - Purple MacBook Air 13 Rd | F67: Cases Macbook | G67: Macbook | H67: MacBook Air 13" M2 Cases | I67: iShop | J67: Firme | K67: 0 | L67: 568.45 | M67: Descontinuado | N67: Discontinued | O67: 0 | P67: 0 | Q67: 0 | R67: 0 | S67: 0 | T67: 0 | U67: 0 | V67: 0 | W67: 0 | X67: 0 | Y67: 0 | Z67: 0 | AA67: =O67*$L:$L -> 0 | AB67: =P67*$L:$L -> 0 | AC67: =Q67*$L:$L -> 0 | AD67: =R67*$L:$L -> 0 | AE67: =S67*$L:$L -> 0 | AF67: =T67*$L:$L -> 0 | AG67: =U67*$L:$L -> 0 | AH67: =V67*$L:$L -> 0 | ... AL67: =Z67*$L:$L -> 0 | AN67: =C67&I67 -> 126087-6010iShop | AO67: {=IFERROR(VLOOKUP(_xlfn.SINGLE(AN:AN),'[1]Pivot SI'!$R:$Y,{2,3,4,5,6,7,8},0),0)} -> 0 | AP67: 0 | AQ67: 0 | AR67: 0 | AS67: 0 | AT67: 0 | AU67: 0
A68: Speck | B68: 848709071378 | C68: 126087-B189 | D68: 848709071378 | E68: Speck Smartshell - Blue MacBook Air 13 Rd | F68: Cases Macbook | G68: Macbook | H68: MacBook Air 13" M2 Cases | I68: iShop | J68: Firme | K68: 0 | L68: 568.45 | M68: Descontinuado | N68: Discontinued | O68: 0 | P68: 0 | Q68: 0 | R68: 0 | S68: 0 | T68: 0 | U68: 0 | V68: 0 | W68: 0 | X68: 0 | Y68: 0 | Z68: 0 | AA68: =O68*$L:$L -> 0 | AB68: =P68*$L:$L -> 0 | AC68: =Q68*$L:$L -> 0 | AD68: =R68*$L:$L -> 0 | AE68: =S68*$L:$L -> 0 | AF68: =T68*$L:$L -> 0 | AG68: =U68*$L:$L -> 0 | AH68: =V68*$L:$L -> 0 | ... AL68: =Z68*$L:$L -> 0 | AN68: =C68&I68 -> 126087-B189iShop | AO68: {=IFERROR(VLOOKUP(_xlfn.SINGLE(AN:AN),'[1]Pivot SI'!$R:$Y,{2,3,4,5,6,7,8},0),0)} -> 0 | AP68: 0 | AQ68: 0 | AR68: 0 | AS68: 0 | AT68: 0 | AU68: 0
A69: Speck | B69: 848709071484 | C69: 126087-6011 | D69: 848709071484 | E69: Speck Smartshell - Rose Pink MacBook Air 13 Rd | F69: Cases Macbook | G69: Macbook | H69: MacBook Air 13" M2 Cases | I69: iShop | J69: Firme | K69: 0 | L69: 568.45 | M69: Descontinuado | N69: Discontinued | O69: 0 | P69: 0 | Q69: 0 | R69: 0 | S69: 0 | T69: 0 | U69: 0 | V69: 0 | W69: 0 | X69: 0 | Y69: 0 | Z69: 0 | AA69: =O69*$L:$L -> 0 | AB69: =P69*$L:$L -> 0 | AC69: =Q69*$L:$L -> 0 | AD69: =R69*$L:$L -> 0 | AE69: =S69*$L:$L -> 0 | AF69: =T69*$L:$L -> 0 | AG69: =U69*$L:$L -> 0 | AH69: =V69*$L:$L -> 0 | ... AL69: =Z69*$L:$L -> 0 | AN69: =C69&I69 -> 126087-6011iShop | AO69: {=IFERROR(VLOOKUP(_xlfn.SINGLE(AN:AN),'[1]Pivot SI'!$R:$Y,{2,3,4,5,6,7,8},0),0)} -> 0 | AP69: 0 | AQ69: 0 | AR69: 0 | AS69: 0 | AT69: 0 | AU69: 0
A70: Speck | B70: 840168538683 | C70: 150585-1568 | D70: 840168538683 | E70: Speck Tagimals 4-Pack - Mulicolor | F70: Cases AirTag | G70: AirTag | H70: AirTag | I70: iShop | J70: Firme | K70: 170 | L70: 232.37 | M70: Activo | N70: Active | O70: 36 | P70: 49 | Q70: 122 | R70: 32 | S70: 85 | T70: 2 | U70: 1 | V70: 80 | W70: 36 | X70: 84 | Y70: 100 | Z70: 51 | AA70: =O70*$L:$L -> 8365.32 | AB70: =P70*$L:$L -> 11386.13 | AC70: =Q70*$L:$L -> 28349.14 | AD70: =R70*$L:$L -> 7435.84 | AE70: =S70*$L:$L -> 19751.45 | AF70: =T70*$L:$L -> 464.74 | AG70: =U70*$L:$L -> 232.37 | AH70: =V70*$L:$L -> 18589.6 | ... AL70: =Z70*$L:$L -> 11850.87 | AN70: =C70&I70 -> 150585-1568iShop | AO70: {=IFERROR(VLOOKUP(_xlfn.SINGLE(AN:AN),'[1]Pivot SI'!$R:$Y,{2,3,4,5,6,7,8},0),0)} -> 36 | AP70: 49 | AQ70: 122 | AR70: 32 | AS70: 85 | AT70: 2 | AU70: 1
A71: Speck | B71: 840168532148 | C71: 150423-1041 | D71: 840168532148 | E71: Speck Wallet for MagSafe® Black iPhone 15 Wallet | F71: Others | G71: Click Lock | H71: Wallet | I71: iShop | J71: Firme | K71: 160 | L71: 232.37 | M71: Activo | N71: Active | O71: 30 | P71: 6 | Q71: 29 | R71: 0 | S71: 64 | T71: 0 | U71: 30 | V71: 27 | W71: 38 | X71: 10 | Y71: 40 | Z71: 38 | AA71: =O71*$L:$L -> 6971.1 | AB71: =P71*$L:$L -> 1394.22 | AC71: =Q71*$L:$L -> 6738.73 | AD71: =R71*$L:$L -> 0 | AE71: =S71*$L:$L -> 14871.68 | AF71: =T71*$L:$L -> 0 | AG71: =U71*$L:$L -> 6971.1 | AH71: =V71*$L:$L -> 6273.99 | ... AL71: =Z71*$L:$L -> 8830.06 | AN71: =C71&I71 -> 150423-1041iShop | AO71: {=IFERROR(VLOOKUP(_xlfn.SINGLE(AN:AN),'[1]Pivot SI'!$R:$Y,{2,3,4,5,6,7,8},0),0)} -> 30 | AP71: 6 | AQ71: 29 | AR71: 0 | AS71: 64 | AT71: 0 | AU71: 30
A72: Speck | B72: 848709087164 | C72: 127573-9166 | D72: 848709087164 | E72: Speck Transfer Pro Pocket Universal Sleeve 13"/14" - Sweater Grey/Coastal Blue | F72: Cases Sleeves | G72: Sleeves | H72: 13" Sleeves | I72: iShop | J72: Firme | K72: 70 | L72: 430.6 | M72: Activo | N72: Active | O72: 0 | P72: 0 | Q72: 31 | R72: 9 | S72: 0 | T72: 8 | U72: 9 | V72: 21 | W72: 12 | X72: 33 | Y72: 12 | Z72: 12 | AA72: =O72*$L:$L -> 0 | AB72: =P72*$L:$L -> 0 | AC72: =Q72*$L:$L -> 13348.6 | AD72: =R72*$L:$L -> 3875.4 | AE72: =S72*$L:$L -> 0 | AF72: =T72*$L:$L -> 3444.8 | AG72: =U72*$L:$L -> 3875.4 | AH72: =V72*$L:$L -> 9042.6 | ... AL72: =Z72*$L:$L -> 5167.2 | AN72: =C72&I72 -> 127573-9166iShop | AO72: {=IFERROR(VLOOKUP(_xlfn.SINGLE(AN:AN),'[1]Pivot SI'!$R:$Y,{2,3,4,5,6,7,8},0),0)} -> 0 | AP72: 0 | AQ72: 31 | AR72: 9 | AS72: 0 | AT72: 8 | AU72: 9
A73: Tech21 | B73: 840459607753 | C73: T21-11364 | D73: 840459607753 | E73: Tech21 EvoSparkle iPhone 17 Pro Focus | F73: Cases iPhone | G73: iPhone 17 | H73: iPhone 17 Pro | I73: iShop | J73: Firme | K73: 320 | L73: 387.5 | M73: Descontinuado | N73: Active | O73: 6 | P73: 0 | Q73: 16 | R73: 2 | S73: 2 | T73: 10 | U73: 0 | V73: 0 | W73: 0 | X73: 0 | Y73: 0 | Z73: 0 | AA73: =O73*$L:$L -> 2325 | AB73: =P73*$L:$L -> 0 | AC73: =Q73*$L:$L -> 6200 | AD73: =R73*$L:$L -> 775 | AE73: =S73*$L:$L -> 775 | AF73: =T73*$L:$L -> 3875 | AG73: =U73*$L:$L -> 0 | AH73: =V73*$L:$L -> 0 | ... AL73: =Z73*$L:$L -> 0 | AN73: =C73&I73 -> T21-11364iShop | AO73: {=IFERROR(VLOOKUP(_xlfn.SINGLE(AN:AN),'[1]Pivot SI'!$R:$Y,{2,3,4,5,6,7,8},0),0)} -> 0
A74: Tech21 | B74: 840459607869 | C74: T21-11373 | D74: 840459607869 | E74: Tech21 EvoSparkle iPhone 17 Pro Lunar | F74: Cases iPhone | G74: iPhone 17 | H74: iPhone 17 Pro | I74: iShop | J74: Firme | K74: 320 | L74: 387.5 | M74: Descontinuado | N74: Active | O74: 0 | P74: 22 | Q74: 0 | R74: 0 | S74: 0 | T74: 0 | U74: 19 | V74: 0 | W74: 0 | X74: 0 | Y74: 0 | Z74: 0 | AA74: =O74*$L:$L -> 0 | AB74: =P74*$L:$L -> 8525 | AC74: =Q74*$L:$L -> 0 | AD74: =R74*$L:$L -> 0 | AE74: =S74*$L:$L -> 0 | AF74: =T74*$L:$L -> 0 | AG74: =U74*$L:$L -> 7362.5 | AH74: =V74*$L:$L -> 0 | ... AL74: =Z74*$L:$L -> 0 | AN74: =C74&I74 -> T21-11373iShop | AO74: {=IFERROR(VLOOKUP(_xlfn.SINGLE(AN:AN),'[1]Pivot SI'!$R:$Y,{2,3,4,5,6,7,8},0),0)} -> 0
A75: Tech21 | B75: 840459607265 | C75: T21-11324 | D75: 840459607265 | E75: Tech21 EvoCrystal iPhone 17 Pro Black | F75: Cases iPhone | G75: iPhone 17 | H75: iPhone 17 Pro | I75: iShop | J75: Firme | K75: 320 | L75: 387.5 | M75: Descontinuado | N75: Active | O75: 14 | P75: 10 | Q75: 0 | R75: 18 | S75: 9 | T75: 0 | U75: 36 | V75: 0 | W75: 0 | X75: 0 | Y75: 0 | Z75: 0 | AA75: =O75*$L:$L -> 5425 | AB75: =P75*$L:$L -> 3875 | AC75: =Q75*$L:$L -> 0 | AD75: =R75*$L:$L -> 6975 | AE75: =S75*$L:$L -> 3487.5 | AF75: =T75*$L:$L -> 0 | AG75: =U75*$L:$L -> 13950 | AH75: =V75*$L:$L -> 0 | ... AL75: =Z75*$L:$L -> 0 | AN75: =C75&I75 -> T21-11324iShop | AO75: {=IFERROR(VLOOKUP(_xlfn.SINGLE(AN:AN),'[1]Pivot SI'!$R:$Y,{2,3,4,5,6,7,8},0),0)} -> 0
A76: Tech21 | B76: 840459607777 | C76: T21-11366 | D76: 840459607777 | E76: Tech21 EvoSparkle iPhone 17 Pro Max Focus | F76: Cases iPhone | G76: iPhone 17 | H76: iPhone 17 Pro Max | I76: iShop | J76: Firme | K76: 320 | L76: 387.5 | M76: Descontinuado | N76: Active | O76: 14 | P76: 130 | Q76: 29 | R76: 35 | S76: 43 | T76: 0 | U76: 36 | V76: 0 | W76: 0 | X76: 0 | Y76: 0 | Z76: 0 | AA76: =O76*$L:$L -> 5425 | AB76: =P76*$L:$L -> 50375 | AC76: =Q76*$L:$L -> 11237.5 | AD76: =R76*$L:$L -> 13562.5 | AE76: =S76*$L:$L -> 16662.5 | AF76: =T76*$L:$L -> 0 | AG76: =U76*$L:$L -> 13950 | AH76: =V76*$L:$L -> 0 | ... AL76: =Z76*$L:$L -> 0 | AN76: =C76&I76 -> T21-11366iShop | AO76: {=IFERROR(VLOOKUP(_xlfn.SINGLE(AN:AN),'[1]Pivot SI'!$R:$Y,{2,3,4,5,6,7,8},0),0)} -> 0
A77: Tech21 | B77: 840459607890 | C77: T21-11376 | D77: 840459607890 | E77: Tech21 EvoSparkle iPhone 17 Pro Max Lunar | F77: Cases iPhone | G77: iPhone 17 | H77: iPhone 17 Pro Max | I77: iShop | J77: Firme | K77: 320 | L77: 387.5 | M77: Descontinuado | N77: Active | O77: 0 | P77: 133 | Q77: 7 | R77: 14 | S77: 7 | T77: 0 | U77: 17 | V77: 0 | W77: 0 | X77: 0 | Y77: 0 | Z77: 0 | AA77: =O77*$L:$L -> 0 | AB77: =P77*$L:$L -> 51537.5 | AC77: =Q77*$L:$L -> 2712.5 | AD77: =R77*$L:$L -> 5425 | AE77: =S77*$L:$L -> 2712.5 | AF77: =T77*$L:$L -> 0 | AG77: =U77*$L:$L -> 6587.5 | AH77: =V77*$L:$L -> 0 | ... AL77: =Z77*$L:$L -> 0 | AN77: =C77&I77 -> T21-11376iShop | AO77: {=IFERROR(VLOOKUP(_xlfn.SINGLE(AN:AN),'[1]Pivot SI'!$R:$Y,{2,3,4,5,6,7,8},0),0)} -> 0
A78: Tech21 | B78: 840459607388 | C78: T21-11335 | D78: 840459607388 | E78: Tech21 EvoCrystal iPhone 17 Pro Max Black | F78: Cases iPhone | G78: iPhone 17 | H78: iPhone 17 Pro Max | I78: iShop | J78: Firme | K78: 320 | L78: 387.5 | M78: Descontinuado | N78: Active | O78: 0 | P78: 220 | Q78: 33 | R78: 41 | S78: 19 | T78: 0 | U78: 24 | V78: 0 | W78: 0 | X78: 0 | Y78: 0 | Z78: 0 | AA78: =O78*$L:$L -> 0 | AB78: =P78*$L:$L -> 85250 | AC78: =Q78*$L:$L -> 12787.5 | AD78: =R78*$L:$L -> 15887.5 | AE78: =S78*$L:$L -> 7362.5 | AF78: =T78*$L:$L -> 0 | AG78: =U78*$L:$L -> 9300 | AH78: =V78*$L:$L -> 0 | ... AL78: =Z78*$L:$L -> 0 | AN78: =C78&I78 -> T21-11335iShop | AO78: {=IFERROR(VLOOKUP(_xlfn.SINGLE(AN:AN),'[1]Pivot SI'!$R:$Y,{2,3,4,5,6,7,8},0),0)} -> 0
A79: Tech21 | B79: 840459607333 | C79: T21-11331 | D79: 840459607333 | E79: Tech21 EvoPro w/MagSafe Clear/Black iPhone 17 Pro | F79: Cases iPhone | G79: iPhone 17 | H79: iPhone 17 Pro | I79: iShop | J79: Firme | K79: 320 | L79: 516.81 | M79: Descontinuado | N79: Active | O79: 0 | P79: 0 | Q79: 145 | R79: 24 | S79: 22 | T79: 0 | U79: 0 | V79: 0 | W79: 190 | X79: 0 | Y79: 0 | Z79: 0 | AA79: =O79*$L:$L -> 0 | AB79: =P79*$L:$L -> 0 | AC79: =Q79*$L:$L -> 74937.45 | AD79: =R79*$L:$L -> 12403.44 | AE79: =S79*$L:$L -> 11369.82 | AF79: =T79*$L:$L -> 0 | AG79: =U79*$L:$L -> 0 | AH79: =V79*$L:$L -> 0 | ... AL79: =Z79*$L:$L -> 0 | AN79: =C79&I79 -> T21-11331iShop | AO79: {=IFERROR(VLOOKUP(_xlfn.SINGLE(AN:AN),'[1]Pivot SI'!$R:$Y,{2,3,4,5,6,7,8},0),0)} -> 0
A80: Tech21 | B80: 840459607456 | C80: T21-11342 | D80: 840459607456 | E80: Tech21 EvoPro w/MagSafe Clear/Black iPhone 17 Pro Max | F80: Cases iPhone | G80: iPhone 17 | H80: iPhone 17 Pro Max | I80: iShop | J80: Firme | K80: 320 | L80: 516.81 | M80: Descontinuado | N80: Active | O80: 0 | P80: 0 | Q80: 211 | R80: 50 | S80: 45 | T80: 20 | U80: 48 | V80: 30 | X80: 0 | Y80: 0 | Z80: 100 | AA80: =O80*$L:$L -> 0 | AB80: =P80*$L:$L -> 0 | AC80: =Q80*$L:$L -> 109046.91 | AD80: =R80*$L:$L -> 25840.5 | AE80: =S80*$L:$L -> 23256.45 | AF80: =T80*$L:$L -> 10336.2 | AG80: =U80*$L:$L -> 24806.88 | AH80: =V80*$L:$L -> 15504.3 | ... AL80: =Z80*$L:$L -> 51681 | AN80: =C80&I80 -> T21-11342iShop | AO80: {=IFERROR(VLOOKUP(_xlfn.SINGLE(AN:AN),'[1]Pivot SI'!$R:$Y,{2,3,4,5,6,7,8},0),0)} -> 0
A81: Speck | B81: 840168536245 | C81: 150526-D143 | D81: 840168536245 | E81: Speck BALANCE FOLIO APPLE 13" IPAD AIR CASES - Black | F81: Cases iPad | G81: iPad | H81: iPad Air 13" M2 | I81: iShop | J81: Firme | K81: 60 | L81: 516.81 | M81: Activo2 | N81: Blocked | O81: 0 | P81: 0 | Q81: 0 | R81: 0 | S81: 0 | T81: 0 | U81: 0 | V81: 0 | W81: 0 | X81: 0 | Y81: 0 | Z81: 0 | AA81: =O81*$L:$L -> 0 | AB81: =P81*$L:$L -> 0 | AC81: =Q81*$L:$L -> 0 | AD81: =R81*$L:$L -> 0 | AE81: =S81*$L:$L -> 0 | AF81: =T81*$L:$L -> 0 | AG81: =U81*$L:$L -> 0 | AH81: =V81*$L:$L -> 0 | ... AL81: =Z81*$L:$L -> 0 | AN81: =C81&I81 -> 150526-D143iShop | AO81: {=IFERROR(VLOOKUP(_xlfn.SINGLE(AN:AN),'[1]Pivot SI'!$R:$Y,{2,3,4,5,6,7,8},0),0)} -> 0 | AP81: 0 | AQ81: 0 | AR81: 0 | AS81: 0 | AT81: 0 | AU81: 0
A82: Speck | B82: 840168546671 | C82: 150989-3266 | D82: 840168546671 | E82: Speck Balance Folio iPad 11" (2022-2025) Sable/Blue Granite/Black | F82: Cases iPad | G82: iPad | H82: iPad 10th /11th - 10.9"/11" (2022-2025) | I82: iShop | J82: Firme | K82: 270 | L82: 430.6 | M82: Activo | N82: Discontinued | O82: 0 | P82: 167 | Q82: 0 | R82: 0 | S82: 0 | T82: 0 | U82: 0 | V82: 0 | W82: 0 | X82: 0 | Y82: 0 | Z82: 0 | AA82: =O82*$L:$L -> 0 | AB82: =P82*$L:$L -> 71910.2 | AC82: =Q82*$L:$L -> 0 | AD82: =R82*$L:$L -> 0 | AE82: =S82*$L:$L -> 0 | AF82: =T82*$L:$L -> 0 | AG82: =U82*$L:$L -> 0 | AH82: =V82*$L:$L -> 0 | ... AL82: =Z82*$L:$L -> 0 | AN82: =C82&I82 -> 150989-3266iShop | AO82: {=IFERROR(VLOOKUP(_xlfn.SINGLE(AN:AN),'[1]Pivot SI'!$R:$Y,{2,3,4,5,6,7,8},0),0)} -> 0
A83: Speck | B83: 840168532735 | C83: 150439-3205 | D83: 840168532735 | E83: Speck Presidio®2 Grip Magsafe® Clicklock™ Black / Slate Grey iPhone 15 | F83: Cases iPhone | G83: iPhone 15 | H83: iPhone 16e / 15 / 14 / 13 | I83: iShop | J83: Firme | K83: 110 | L83: 387.54 | M83: Activo2 | N83: Active | O83: 0 | P83: 0 | Q83: 0 | R83: 66 | S83: 0 | T83: 63 | U83: 83 | V83: 40 | W83: 20 | X83: 80 | Y83: 50 | Z83: 20 | AA83: =O83*$L:$L -> 0 | AB83: =P83*$L:$L -> 0 | AC83: =Q83*$L:$L -> 0 | AD83: =R83*$L:$L -> 25577.64 | AE83: =S83*$L:$L -> 0 | AF83: =T83*$L:$L -> 24415.02 | AG83: =U83*$L:$L -> 32165.82 | AH83: =V83*$L:$L -> 15501.6 | ... AL83: =Z83*$L:$L -> 7750.8 | AN83: =C83&I83 -> 150439-3205iShop | AO83: {=IFERROR(VLOOKUP(_xlfn.SINGLE(AN:AN),'[1]Pivot SI'!$R:$Y,{2,3,4,5,6,7,8},0),0)} -> 0 | AP83: 0 | AQ83: 0 | AR83: 66 | AS83: 0 | AT83: 63 | AU83: 83
A84: Speck | B84: 840168532865 | C84: 150443-3199 | D84: 840168532865 | E84: Speck Presidio® Perfect-Clear Grip Magsafe® Clicklock™ Clear/Clear/Chrome iPhone 15 | F84: Cases iPhone | G84: iPhone | H84: iPhone 16e / 15 / 14 / 13 | I84: iShop | J84: Firme | K84: 110 | L84: 387.54 | M84: Activo2 | N84: Discontinued | O84: 0 | P84: 0 | Q84: 0 | R84: 127 | S84: 74 | T84: 0 | U84: 0 | V84: 0 | W84: 0 | X84: 0 | Y84: 0 | Z84: 0 | AA84: =O84*$L:$L -> 0 | AB84: =P84*$L:$L -> 0 | AC84: =Q84*$L:$L -> 0 | AD84: =R84*$L:$L -> 49217.58 | AE84: =S84*$L:$L -> 28677.96 | AF84: =T84*$L:$L -> 0 | AG84: =U84*$L:$L -> 0 | AH84: =V84*$L:$L -> 0 | ... AL84: =Z84*$L:$L -> 0 | AN84: =C84&I84 -> 150443-3199iShop | AO84: {=IFERROR(VLOOKUP(_xlfn.SINGLE(AN:AN),'[1]Pivot SI'!$R:$Y,{2,3,4,5,6,7,8},0),0)} -> 0 | AP84: 0 | AQ84: 0 | AR84: 127 | AS84: 74 | AT84: 0 | AU84: 0
A85: Speck | B85: 840168528127 | C85: 150225-9992 | D85: 840168528127 | E85: Speck Smartshell Macbook Air M2/M3 Clear/Clear/Sweatergrey | F85: Cases Macbook | G85: Macbook | H85: MacBook Air 13" M4/M3/M2 | I85: iShop | J85: Firme | K85: 190 | L85: 430.6 | M85: Activo | N85: Active | O85: 0 | P85: 208 | Q85: 328 | R85: 96 | S85: 239 | T85: 94 | U85: 97 | V85: 201 | W85: 110 | X85: 50 | Y85: 201 | Z85: 120 | AA85: =O85*$L:$L -> 0 | AB85: =P85*$L:$L -> 89564.8 | AC85: =Q85*$L:$L -> 141236.8 | AD85: =R85*$L:$L -> 41337.6 | AE85: =S85*$L:$L -> 102913.4 | AF85: =T85*$L:$L -> 40476.4 | AG85: =U85*$L:$L -> 41768.2 | AH85: =V85*$L:$L -> 86550.6 | ... AL85: =Z85*$L:$L -> 51672 | AN85: =C85&I85 -> 150225-9992iShop | AO85: {=IFERROR(VLOOKUP(_xlfn.SINGLE(AN:AN),'[1]Pivot SI'!$R:$Y,{2,3,4,5,6,7,8},0),0)} -> 0 | AP85: 208 | AQ85: 328 | AR85: 96 | AS85: 239 | AT85: 94 | AU85: 97
A86: Speck | B86: 840168528134 | C86: 150225-3085 | D86: 840168528134 | E86: Speck Smartshell Case for Macbook Air 13" M2 2022 - Obsidian | F86: Cases Macbook | G86: Macbook | H86: MacBook Air 13" M4/M3/M2 | I86: iShop | J86: Firme | K86: 190 | L86: 430.6 | M86: Activo | N86: Active | O86: 0 | P86: 171 | Q86: 154 | R86: 52 | S86: 92 | T86: 63 | U86: 59 | V86: 200 | W86: 90 | X86: 55 | Y86: 200 | Z86: 90 | AA86: =O86*$L:$L -> 0 | AB86: =P86*$L:$L -> 73632.6 | AC86: =Q86*$L:$L -> 66312.4 | AD86: =R86*$L:$L -> 22391.2 | AE86: =S86*$L:$L -> 39615.2 | AF86: =T86*$L:$L -> 27127.8 | AG86: =U86*$L:$L -> 25405.4 | AH86: =V86*$L:$L -> 86120 | ... AL86: =Z86*$L:$L -> 38754 | AN86: =C86&I86 -> 150225-3085iShop | AO86: {=IFERROR(VLOOKUP(_xlfn.SINGLE(AN:AN),'[1]Pivot SI'!$R:$Y,{2,3,4,5,6,7,8},0),0)} -> 0 | AP86: 171 | AQ86: 154 | AR86: 52 | AS86: 92 | AT86: 63 | AU86: 59
A87: Speck | B87: 840168528141 | C87: 150225-3086 | D87: 840168528141 | E87: Speck Smartshell Macbook Air M2/M3 Cozy Pink/Cozy Pink/Swtrgrey | F87: Cases Macbook | G87: Macbook | H87: MacBook Air 13" M4/M3/M2 | I87: iShop | J87: Firme | K87: 190 | L87: 538.36 | M87: Activo | N87: Active | O87: 0 | P87: 52 | Q87: 55 | R87: 0 | S87: 81 | T87: 14 | U87: 18 | V87: 55 | W87: 42 | X87: 30 | Y87: 55 | Z87: 40 | AA87: =O87*$L:$L -> 0 | AB87: =P87*$L:$L -> 27994.72 | AC87: =Q87*$L:$L -> 29609.8 | AD87: =R87*$L:$L -> 0 | AE87: =S87*$L:$L -> 43607.16 | AF87: =T87*$L:$L -> 7537.04 | AG87: =U87*$L:$L -> 9690.48 | AH87: =V87*$L:$L -> 29609.8 | ... AL87: =Z87*$L:$L -> 21534.4 | AN87: =C87&I87 -> 150225-3086iShop | AO87: {=IFERROR(VLOOKUP(_xlfn.SINGLE(AN:AN),'[1]Pivot SI'!$R:$Y,{2,3,4,5,6,7,8},0),0)} -> 0 | AP87: 52 | AQ87: 55 | AR87: 0 | AS87: 81 | AT87: 14 | AU87: 18
A88: Tech21 | B88: 840459608569 | C88: T21-11443 | D88: 840459608569 | E88: Tech21 Apple MacBook Air 13 EvoShell - Clear | F88: Cases Macbook | G88: Macbook | H88: MacBook Air 13" M4/M3/M2 | I88: iShop | J88: Firme | K88: 190 | L88: 581.47 | M88: Activo | N88: Active | O88: 0 | P88: 0 | Q88: 302 | R88: 80 | S88: 0 | T88: 163 | U88: 120 | V88: 200 | W88: 70 | X88: 120 | Y88: 200 | Z88: 40 | AA88: =O88*$L:$L -> 0 | AB88: =P88*$L:$L -> 0 | AC88: =Q88*$L:$L -> 175603.94 | AD88: =R88*$L:$L -> 46517.6 | AE88: =S88*$L:$L -> 0 | AF88: =T88*$L:$L -> 94779.61 | AG88: =U88*$L:$L -> 69776.4 | AH88: =V88*$L:$L -> 116294 | ... AL88: =Z88*$L:$L -> 23258.8 | AN88: =C88&I88 -> T21-11443iShop | AO88: {=IFERROR(VLOOKUP(_xlfn.SINGLE(AN:AN),'[1]Pivot SI'!$R:$Y,{2,3,4,5,6,7,8},0),0)} -> 0
A89: Speck | B89: 840168538638 | C89: 150584-9992 | D89: 840168538638 | E89: Speck Smartshell for Mackbook Air 15" - Clear/Sweater Grey | F89: Cases Macbook | G89: Macbook | H89: MacBook Air 15" M2/M3 | I89: iShop | J89: Firme | K89: 160 | L89: 538.36 | M89: Activo2 | N89: Active | O89: 0 | P89: 64 | Q89: 79 | R89: 0 | S89: 87 | T89: 16 | U89: 45 | V89: 50 | W89: 20 | X89: 80 | Y89: 80 | Z89: 100 | AA89: =O89*$L:$L -> 0 | AB89: =P89*$L:$L -> 34455.04 | AC89: =Q89*$L:$L -> 42530.44 | AD89: =R89*$L:$L -> 0 | AE89: =S89*$L:$L -> 46837.32 | AF89: =T89*$L:$L -> 8613.76 | AG89: =U89*$L:$L -> 24226.2 | AH89: =V89*$L:$L -> 26918 | ... AL89: =Z89*$L:$L -> 53836 | AN89: =C89&I89 -> 150584-9992iShop | AO89: {=IFERROR(VLOOKUP(_xlfn.SINGLE(AN:AN),'[1]Pivot SI'!$R:$Y,{2,3,4,5,6,7,8},0),0)} -> 0 | AP89: 64 | AQ89: 79 | AR89: 0 | AS89: 87 | AT89: 16 | AU89: 45
A90: Speck | B90: 848709087171 | C90: 127573-9166 | D90: 848709087171 | E90: Speck Transfer Pro Pocket Universal Sleeve 13"/14" - Sweater Grey/Coastal Blue | F90: Cases Sleeves | G90: Sleeves | H90: 13" Sleeves | I90: iShop | J90: Firme | K90: 70 | L90: 430.6 | M90: Activo | N90: Discontinued | O90: 0 | P90: 0 | Q90: 0 | R90: 0 | S90: 0 | T90: 0 | U90: 0 | V90: 0 | W90: 0 | X90: 0 | Y90: 0 | Z90: 0 | AA90: =O90*$L:$L -> 0 | AB90: =P90*$L:$L -> 0 | AC90: =Q90*$L:$L -> 0 | AD90: =R90*$L:$L -> 0 | AE90: =S90*$L:$L -> 0 | AF90: =T90*$L:$L -> 0 | AG90: =U90*$L:$L -> 0 | AH90: =V90*$L:$L -> 0 | ... AL90: =Z90*$L:$L -> 0 | AN90: =C90&I90 -> 127573-9166iShop | AO90: {=IFERROR(VLOOKUP(_xlfn.SINGLE(AN:AN),'[1]Pivot SI'!$R:$Y,{2,3,4,5,6,7,8},0),0)} -> 0 | AP90: 0 | AQ90: 31 | AR90: 9 | AS90: 0 | AT90: 8 | AU90: 9
A91: Speck | B91: 848709073143 | C91: 127573-8336 | D91: 848709073143 | E91: Speck Transfer Pro Pocket Universal Sleeve 13"/14" - City Grey/Rose Gold Pink | F91: Sleeves | G91: Sleeves | H91: 13" Sleeves | I91: iShop | J91: Firme | K91: 70 | L91: 430.6 | M91: Descontinuado | N91: Discontinued | O91: 0 | P91: 0 | Q91: 0 | R91: 0 | S91: 0 | T91: 0 | U91: 0 | V91: 0 | W91: 0 | X91: 0 | Y91: 0 | Z91: 0 | AA91: =O91*$L:$L -> 0 | AB91: =P91*$L:$L -> 0 | AC91: =Q91*$L:$L -> 0 | AD91: =R91*$L:$L -> 0 | AE91: =S91*$L:$L -> 0 | AF91: =T91*$L:$L -> 0 | AG91: =U91*$L:$L -> 0 | AH91: =V91*$L:$L -> 0 | ... AL91: =Z91*$L:$L -> 0 | AN91: =C91&I91 -> 127573-8336iShop | AO91: {=IFERROR(VLOOKUP(_xlfn.SINGLE(AN:AN),'[1]Pivot SI'!$R:$Y,{2,3,4,5,6,7,8},0),0)} -> 0 | AP91: 0 | AQ91: 0 | AR91: 0 | AS91: 0 | AT91: 0 | AU91: 0
A92: Nomad | B92: 856504014810 | C92: NM014810858 | D92: 856504014810 | E92: Nomad Rocky Point Band - 45mm | Sol | Black Hardware | F92: Straps | G92: Apple Watch | H92: 49/45/44/42 mm | I92: iShop | J92: Firme | K92: 0 | L92: 775.43 | M92: Descontinuado | N92: Discontinued | O92: 0 | V92: 0 | W92: 0 | X92: 0 | Y92: 0 | Z92: 0 | AA92: =O92*$L:$L -> 0 | AB92: =P92*$L:$L -> 0 | AC92: =Q92*$L:$L -> 0 | AD92: =R92*$L:$L -> 0 | AE92: =S92*$L:$L -> 0 | AF92: =T92*$L:$L -> 0 | AG92: =U92*$L:$L -> 0 | AH92: =V92*$L:$L -> 0 | ... AL92: =Z92*$L:$L -> 0 | AN92: =C92&I92 -> NM014810858iShop | AO92: {=IFERROR(VLOOKUP(_xlfn.SINGLE(AN:AN),'[1]Pivot SI'!$R:$Y,{2,3,4,5,6,7,8},0),0)} -> 0
A93: Nomad | B93: 856504011697 | C93: NM011697858 | D93: 856504011697 | E93: Nomad Rocky Point Band - 46mm/49mm | Carbon Black | Black Hardware | F93: Straps | G93: Apple Watch | H93: 49/45/44/42 mm | I93: iShop | J93: Firme | K93: 0 | L93: 775.43 | M93: Activo | N93: Active | O93: 0 | V93: 0 | W93: 69 | X93: 140 | Y93: 180 | Z93: 127 | AA93: =O93*$L:$L -> 0 | AB93: =P93*$L:$L -> 0 | AC93: =Q93*$L:$L -> 0 | AD93: =R93*$L:$L -> 0 | AE93: =S93*$L:$L -> 0 | AF93: =T93*$L:$L -> 0 | AG93: =U93*$L:$L -> 0 | AH93: =V93*$L:$L -> 0 | ... AL93: =Z93*$L:$L -> 98479.61 | AN93: =C93&I93 -> NM011697858iShop | AO93: {=IFERROR(VLOOKUP(_xlfn.SINGLE(AN:AN),'[1]Pivot SI'!$R:$Y,{2,3,4,5,6,7,8},0),0)} -> 0
A94: Tech21 | B94: 840459609283 | C94: T21-11515 | D94: 840459609283 | E94: Tech21 FlexFolio - Apple iPad Air 10.9-11-inch (2020-2025) / iPad Pro 11-inch (2018-2021) Case - Clear | F94: Cases iPad | G94: iPad | H94: iPad Pro 11" 2/3/4/Air 4/5 | I94: iShop | J94: Firme | K94: 270 | L94: 603.02 | M94: Activo | N94: Active | O94: 0 | P94: 0 | Q94: 225 | R94: 101 | S94: 9 | T94: 104 | U94: 108 | V94: 120 | W94: 80 | X94: 80 | Y94: 90 | Z94: 120 | AA94: =O94*$L:$L -> 0 | AB94: =P94*$L:$L -> 0 | AC94: =Q94*$L:$L -> 135679.5 | AD94: =R94*$L:$L -> 60905.02 | AE94: =S94*$L:$L -> 5427.18 | AF94: =T94*$L:$L -> 62714.08 | AG94: =U94*$L:$L -> 65126.16 | AH94: =V94*$L:$L -> 72362.4 | ... AL94: =Z94*$L:$L -> 72362.4 | AN94: =C94&I94 -> T21-11515iShop | AO94: {=IFERROR(VLOOKUP(_xlfn.SINGLE(AN:AN),'[1]Pivot SI'!$R:$Y,{2,3,4,5,6,7,8},0),0)} -> 0
A95: Tech21 | B95: 840459609290 | C95: T21-11516 | D95: 840459609290 | E95: Tech21 FlexFolio - Apple iPad Air 10.9-11-inch (2020-2025) / iPad Pro 11-inch (2018-2021) Case - Tint | F95: Cases iPad | G95: iPad | H95: iPad Pro 11" 2/3/4/Air 4/5 | I95: iShop | J95: Firme | K95: 270 | L95: 603.02 | M95: Activo | N95: Active | O95: 0 | P95: 0 | Q95: 224 | R95: 38 | S95: 65 | T95: 36 | U95: 0 | V95: 30 | W95: 27 | X95: 27 | Y95: 55 | Z95: 100 | AA95: =O95*$L:$L -> 0 | AB95: =P95*$L:$L -> 0 | AC95: =Q95*$L:$L -> 135076.48 | AD95: =R95*$L:$L -> 22914.76 | AE95: =S95*$L:$L -> 39196.3 | AF95: =T95*$L:$L -> 21708.72 | AG95: =U95*$L:$L -> 0 | AH95: =V95*$L:$L -> 18090.6 | ... AL95: =Z95*$L:$L -> 60302 | AN95: =C95&I95 -> T21-11516iShop | AO95: {=IFERROR(VLOOKUP(_xlfn.SINGLE(AN:AN),'[1]Pivot SI'!$R:$Y,{2,3,4,5,6,7,8},0),0)} -> 0
A96: Speck | B96: 840168538645 | C96: 150584-3085 | D96: 840168538645 | E96: Speck Smartshell for Mackbook Air 15" - Obsidian/Sweater Grey | F96: Cases Macbook | G96: Macbook | H96: MacBook Air 15" M2/M3 | I96: iShop | J96: Firme | K96: 160 | L96: 538.36 | M96: Activo | N96: Active | O96: 1 | P96: 23 | Q96: 38 | R96: 0 | S96: 29 | T96: 36 | U96: 21 | V96: 34 | W96: 15 | X96: 32 | Y96: 56 | Z96: 47 | AA96: =O96*$L:$L -> 538.36 | AB96: =P96*$L:$L -> 12382.28 | AC96: =Q96*$L:$L -> 20457.68 | AD96: =R96*$L:$L -> 0 | AE96: =S96*$L:$L -> 15612.44 | AF96: =T96*$L:$L -> 19380.96 | AG96: =U96*$L:$L -> 11305.56 | AH96: =V96*$L:$L -> 18304.24 | ... AL96: =Z96*$L:$L -> 25302.92 | AN96: =C96&I96 -> 150584-3085iShop | AO96: {=IFERROR(VLOOKUP(_xlfn.SINGLE(AN:AN),'[1]Pivot SI'!$R:$Y,{2,3,4,5,6,7,8},0),0)} -> 1 | AP96: 23 | AQ96: 38 | AR96: 0 | AS96: 29 | AT96: 36 | AU96: 21
A97: Speck | B97: 840168546732 | C97: 150992-5085 | D97: 840168546732 | E97: Speck Gemshell Grip + MS iPhone 17 Clear | F97: Cases iPhone | G97: iPhone 17 | H97: iPhone 17 | I97: iShop | J97: Firme | K97: 200 | L97: 309.96 | M97: Descontinuado | N97: Active | O97: 3 | P97: 0 | Q97: 0 | R97: 6 | S97: 10 | T97: 0 | U97: 5 | V97: 13 | W97: 13 | X97: 13 | Y97: 13 | Z97: 13 | AA97: =O97*$L:$L -> 929.88 | AB97: =P97*$L:$L -> 0 | AC97: =Q97*$L:$L -> 0 | AD97: =R97*$L:$L -> 1859.76 | AE97: =S97*$L:$L -> 3099.6 | AF97: =T97*$L:$L -> 0 | AG97: =U97*$L:$L -> 1549.8 | AH97: =V97*$L:$L -> 4029.48 | ... AL97: =Z97*$L:$L -> 4029.48 | AN97: =C97&I97 -> 150992-5085iShop | AO97: {=IFERROR(VLOOKUP(_xlfn.SINGLE(AN:AN),'[1]Pivot SI'!$R:$Y,{2,3,4,5,6,7,8},0),0)} -> 0
A98: Speck | B98: 840168546107 | C98: 150954-3240 | D98: 840168546107 | E98: Speck Presidio Perfect-Clear + MS iPhone 17 Clear | F98: Cases iPhone | G98: iPhone 17 | H98: iPhone 17 | I98: iShop | J98: Firme | K98: 200 | L98: 387.54 | M98: Descontinuado | N98: Active | O98: 0 | P98: 54 | Q98: 53 | R98: 59 | S98: 0 | T98: 0 | U98: 0 | V98: 0 | W98: 0 | X98: 0 | Y98: 0 | Z98: 0 | AA98: =O98*$L:$L -> 0 | AB98: =P98*$L:$L -> 20927.16 | AC98: =Q98*$L:$L -> 20539.62 | AD98: =R98*$L:$L -> 22864.86 | AE98: =S98*$L:$L -> 0 | AF98: =T98*$L:$L -> 0 | AG98: =U98*$L:$L -> 0 | AH98: =V98*$L:$L -> 0 | ... AL98: =Z98*$L:$L -> 0 | AN98: =C98&I98 -> 150954-3240iShop | AO98: {=IFERROR(VLOOKUP(_xlfn.SINGLE(AN:AN),'[1]Pivot SI'!$R:$Y,{2,3,4,5,6,7,8},0),0)} -> 0
A99: Speck | B99: 840168546145 | C99: 150958-D143 | D99: 840168546145 | E99: Speck Presidio2 Grip + MS iPhone 17 Black | F99: Cases iPhone | G99: iPhone 17 | H99: iPhone 17 | I99: iShop | J99: Firme | K99: 200 | L99: 387.54 | M99: Descontinuado | N99: Active | O99: 0 | P99: 10 | Q99: 0 | R99: 20 | S99: 18 | T99: 0 | U99: 0 | V99: 0 | W99: 0 | X99: 0 | Y99: 0 | Z99: 0 | AA99: =O99*$L:$L -> 0 | AB99: =P99*$L:$L -> 3875.4 | AC99: =Q99*$L:$L -> 0 | AD99: =R99*$L:$L -> 7750.8 | AE99: =S99*$L:$L -> 6975.72 | AF99: =T99*$L:$L -> 0 | AG99: =U99*$L:$L -> 0 | AH99: =V99*$L:$L -> 0 | ... AL99: =Z99*$L:$L -> 0 | AN99: =C99&I99 -> 150958-D143iShop | AO99: {=IFERROR(VLOOKUP(_xlfn.SINGLE(AN:AN),'[1]Pivot SI'!$R:$Y,{2,3,4,5,6,7,8},0),0)} -> 0
A100: Speck | B100: 840168546138 | C100: 150957-D143 | D100: 840168546138 | E100: Speck Presidio2 + MS iPhone 17 Black/Slate Grey/White | F100: Cases iPhone | G100: iPhone 17 | H100: iPhone 17 | I100: iShop | J100: Firme | K100: 200 | L100: 387.54 | M100: Descontinuado | N100: Active | O100: 0 | P100: 18 | Q100: 7 | R100: 0 | S100: 22 | T100: 22 | U100: 34 | V100: 11 | W100: 11 | X100: 11 | Y100: 11 | Z100: 11 | AA100: =O100*$L:$L -> 0 | AB100: =P100*$L:$L -> 6975.72 | AC100: =Q100*$L:$L -> 2712.78 | AD100: =R100*$L:$L -> 0 | AE100: =S100*$L:$L -> 8525.88 | AF100: =T100*$L:$L -> 8525.88 | AG100: =U100*$L:$L -> 13176.36 | AH100: =V100*$L:$L -> 4262.94 | ... AL100: =Z100*$L:$L -> 4262.94 | AN100: =C100&I100 -> 150957-D143iShop | AO100: {=IFERROR(VLOOKUP(_xlfn.SINGLE(AN:AN),'[1]Pivot SI'!$R:$Y,{2,3,4,5,6,7,8},0),0)} -> 0
A101: Speck | B101: 840168547135 | C101: 151008-3261 | D101: 840168547135 | E101: Speck Presidio2 + MS iPhone 17 Deep Sea/Silver Metallic/Spell Blue | F101: Cases iPhone | G101: iPhone 17 | H101: iPhone 17 | I101: iShop | J101: Firme | K101: 200 | L101: 387.54 | M101: Descontinuado | N101: Active | O101: 18 | P101: 6 | Q101: 0 | R101: 8 | S101: 4 | T101: 0 | U101: 28 | V101: 0 | W101: 0 | X101: 0 | Y101: 0 | Z101: 0 | AA101: =O101*$L:$L -> 6975.72 | AB101: =P101*$L:$L -> 2325.24 | AC101: =Q101*$L:$L -> 0 | AD101: =R101*$L:$L -> 3100.32 | AE101: =S101*$L:$L -> 1550.16 | AF101: =T101*$L:$L -> 0 | AG101: =U101*$L:$L -> 10851.12 | AH101: =V101*$L:$L -> 0 | ... AL101: =Z101*$L:$L -> 0 | AN101: =C101&I101 -> 151008-3261iShop | AO101: {=IFERROR(VLOOKUP(_xlfn.SINGLE(AN:AN),'[1]Pivot SI'!$R:$Y,{2,3,4,5,6,7,8},0),0)} -> 0
A102: Tech21 | B102: 5056586735251 | C102: T21-10857 | D102: 5056586735251 | E102: Tech21 EvoCrystal w/MagSafe for iPhone 16 - Black | F102: Cases iPhone | G102: iPhone 16 | H102: iPhone 16 | I102: iShop | J102: Firme | K102: 110 | L102: 430.6 | M102: Descontinuado | N102: Active | O102: 64 | P102: 38 | Q102: 77 | R102: 0 | S102: 0 | T102: 0 | U102: 0 | V102: 0 | W102: 0 | X102: 0 | Y102: 0 | Z102: 0 | AA102: =O102*$L:$L -> 27558.4 | AB102: =P102*$L:$L -> 16362.8 | AC102: =Q102*$L:$L -> 33156.2 | AD102: =R102*$L:$L -> 0 | AE102: =S102*$L:$L -> 0 | AF102: =T102*$L:$L -> 0 | AG102: =U102*$L:$L -> 0 | AH102: =V102*$L:$L -> 0 | ... AL102: =Z102*$L:$L -> 0 | AN102: =C102&I102 -> T21-10857iShop | AO102: {=IFERROR(VLOOKUP(_xlfn.SINGLE(AN:AN),'[1]Pivot SI'!$R:$Y,{2,3,4,5,6,7,8},0),0)} -> 0
A103: Tech21 | B103: 840459607036 | C103: T21-11303 | D103: 840459607036 | E103: Tech21 EvoClear iPhone 17 Clear | F103: Cases iPhone | G103: iPhone 17 | H103: iPhone 17 | I103: iShop | J103: Firme | K103: 200 | L103: 387.5 | M103: Descontinuado | N103: Active | O103: 0 | P103: 102 | Q103: 37 | R103: 62 | S103: 13 | T103: 0 | U103: 0 | V103: 0 | W103: 0 | X103: 0 | Y103: 0 | Z103: 0 | AA103: =O103*$L:$L -> 0 | AB103: =P103*$L:$L -> 39525 | AC103: =Q103*$L:$L -> 14337.5 | AD103: =R103*$L:$L -> 24025 | AE103: =S103*$L:$L -> 5037.5 | AF103: =T103*$L:$L -> 0 | AG103: =U103*$L:$L -> 0 | AH103: =V103*$L:$L -> 0 | ... AL103: =Z103*$L:$L -> 0 | AN103: =C103&I103 -> T21-11303iShop | AO103: {=IFERROR(VLOOKUP(_xlfn.SINGLE(AN:AN),'[1]Pivot SI'!$R:$Y,{2,3,4,5,6,7,8},0),0)} -> 0
A104: Tech21 | B104: 840459607715 | C104: T21-11360 | D104: 840459607715 | E104: Tech21 EvoSparkle iPhone 17 Focus | F104: Cases iPhone | G104: iPhone 17 | H104: iPhone 17 | I104: iShop | J104: Firme | K104: 200 | L104: 387.5 | M104: Descontinuado | N104: Active | O104: 40 | P104: 0 | Q104: 2 | R104: 0 | S104: 0 | T104: 0 | U104: 0 | V104: 0 | W104: 0 | X104: 0 | Y104: 0 | Z104: 0 | AA104: =O104*$L:$L -> 15500 | AB104: =P104*$L:$L -> 0 | AC104: =Q104*$L:$L -> 775 | AD104: =R104*$L:$L -> 0 | AE104: =S104*$L:$L -> 0 | AF104: =T104*$L:$L -> 0 | AG104: =U104*$L:$L -> 0 | AH104: =V104*$L:$L -> 0 | ... AL104: =Z104*$L:$L -> 0 | AN104: =C104&I104 -> T21-11360iShop | AO104: {=IFERROR(VLOOKUP(_xlfn.SINGLE(AN:AN),'[1]Pivot SI'!$R:$Y,{2,3,4,5,6,7,8},0),0)} -> 0
A105: Tech21 | B105: 840459607845 | C105: T21-11371 | D105: 840459607845 | E105: Tech21 EvoSparkle iPhone 17 Lunar | F105: Cases iPhone | G105: iPhone 17 | H105: iPhone 17 | I105: iShop | J105: Firme | K105: 200 | L105: 387.5 | M105: Descontinuado | N105: Active | O105: 2 | P105: 0 | Q105: 6 | R105: 6 | S105: 21 | T105: 0 | U105: 47 | V105: 0 | W105: 0 | X105: 0 | Y105: 0 | Z105: 0 | AA105: =O105*$L:$L -> 775 | AB105: =P105*$L:$L -> 0 | AC105: =Q105*$L:$L -> 2325 | AD105: =R105*$L:$L -> 2325 | AE105: =S105*$L:$L -> 8137.5 | AF105: =T105*$L:$L -> 0 | AG105: =U105*$L:$L -> 18212.5 | AH105: =V105*$L:$L -> 0 | ... AL105: =Z105*$L:$L -> 0 | AN105: =C105&I105 -> T21-11371iShop | AO105: {=IFERROR(VLOOKUP(_xlfn.SINGLE(AN:AN),'[1]Pivot SI'!$R:$Y,{2,3,4,5,6,7,8},0),0)} -> 0
A106: Tech21 | B106: 840459607043 | C106: T21-11304 | D106: 840459607043 | E106: Tech21 EvoCrystal iPhone 17 Black | F106: Cases iPhone | G106: iPhone 17 | H106: iPhone 17 | I106: iShop | J106: Firme | K106: 200 | L106: 387.5 | M106: Descontinuado | N106: Active | O106: 45 | P106: 43 | Q106: 23 | R106: 20 | S106: 27 | T106: 0 | U106: 35 | V106: 35 | W106: 35 | X106: 35 | Y106: 35 | Z106: 35 | AA106: =O106*$L:$L -> 17437.5 | AB106: =P106*$L:$L -> 16662.5 | AC106: =Q106*$L:$L -> 8912.5 | AD106: =R106*$L:$L -> 7750 | AE106: =S106*$L:$L -> 10462.5 | AF106: =T106*$L:$L -> 0 | AG106: =U106*$L:$L -> 13562.5 | AH106: =V106*$L:$L -> 13562.5 | ... AL106: =Z106*$L:$L -> 13562.5 | AN106: =C106&I106 -> T21-11304iShop | AO106: {=IFERROR(VLOOKUP(_xlfn.SINGLE(AN:AN),'[1]Pivot SI'!$R:$Y,{2,3,4,5,6,7,8},0),0)} -> 0
A107: Tech21 | B107: 5056586746745 | C107: T21-11240 | D107: 840459603182 | E107: Tech21 EvoLite for AirPods 4 - Clear | F107: Cases Airpods | G107: Airpods | H107: Airpods 4 | I107: iShop | J107: Firme | K107: 180 | L107: 174.18 | M107: Activo2 | N107: Active | O107: 0 | P107: 0 | Q107: 0 | R107: 81 | S107: 39 | T107: 8 | U107: 24 | V107: 13 | W107: 30 | X107: 30 | Y107: 30 | Z107: 30 | AA107: =O107*$L:$L -> 0 | AB107: =P107*$L:$L -> 0 | AC107: =Q107*$L:$L -> 0 | AD107: =R107*$L:$L -> 14108.58 | AE107: =S107*$L:$L -> 6793.02 | AF107: =T107*$L:$L -> 1393.44 | AG107: =U107*$L:$L -> 4180.32 | AH107: =V107*$L:$L -> 2264.34 | ... AL107: =Z107*$L:$L -> 5225.4 | AN107: =C107&I107 -> T21-11240iShop | AO107: {=IFERROR(VLOOKUP(_xlfn.SINGLE(AN:AN),'[1]Pivot SI'!$R:$Y,{2,3,4,5,6,7,8},0),0)} -> 0
A108: Speck | B108: 2021942878173 | C108: 150661-3225 | D108: 2021942878173 | E108: Speck Speaker Gemtones Infinity Speaker Max -DARK GREY/CHROME/TAN | F108: Audio | G108: Speakers | H108: Infinity | I108: iShop | J108: Firme | K108: 0 | L108: 0.01 | M108: Descontinuado | N108: Discontinued | O108: 0 | P108: 0 | Q108: 0 | R108: 0 | S108: 0 | T108: 0 | U108: 0 | V108: 0 | W108: 0 | X108: 0 | Y108: 0 | Z108: 0 | AA108: =O108*$L:$L -> 0 | AB108: =P108*$L:$L -> 0 | AC108: =Q108*$L:$L -> 0 | AD108: =R108*$L:$L -> 0 | AE108: =S108*$L:$L -> 0 | AF108: =T108*$L:$L -> 0 | AG108: =U108*$L:$L -> 0 | AH108: =V108*$L:$L -> 0 | ... AL108: =Z108*$L:$L -> 0 | AN108: =C108&I108 -> 150661-3225iShop | AO108: {=IFERROR(VLOOKUP(_xlfn.SINGLE(AN:AN),'[1]Pivot SI'!$R:$Y,{2,3,4,5,6,7,8},0),0)} -> 0
A109: Speck | B109: 2021942878104 | C109: 150659-3225 | D109: 2021942878104 | E109: Speck Speaker Gemtones Infinity Speaker Mini -DARK GREY/CHROME/TAN | F109: Audio | G109: Speakers | H109: Infinity | I109: iShop | J109: Firme | K109: 0 | L109: 0.01 | M109: Descontinuado | N109: Discontinued | O109: 0 | P109: 0 | Q109: 0 | R109: 0 | S109: 0 | T109: 0 | U109: 0 | V109: 0 | W109: 0 | X109: 0 | Y109: 0 | Z109: 0 | AA109: =O109*$L:$L -> 0 | AB109: =P109*$L:$L -> 0 | AC109: =Q109*$L:$L -> 0 | AD109: =R109*$L:$L -> 0 | AE109: =S109*$L:$L -> 0 | AF109: =T109*$L:$L -> 0 | AG109: =U109*$L:$L -> 0 | AH109: =V109*$L:$L -> 0 | ... AL109: =Z109*$L:$L -> 0 | AN109: =C109&I109 -> 150659-3225iShop | AO109: {=IFERROR(VLOOKUP(_xlfn.SINGLE(AN:AN),'[1]Pivot SI'!$R:$Y,{2,3,4,5,6,7,8},0),0)} -> 0
A110: Nomad | B110: 856500013602 | C110: NM013602858 | D110: 856500013602 | E110: Nomad Rocky Point Band - 45mm | Sol | F110: Straps | G110: Apple Watch | H110: 49/45/44 mm | I110: iShop | J110: Firme | K110: 0 | L110: 775.43 | M110: Descontinuado | N110: Discontinued | O110: 0 | P110: 0 | Q110: 0 | R110: 0 | S110: 0 | T110: 0 | U110: 0 | V110: 0 | W110: 0 | X110: 0 | Y110: 0 | Z110: 0 | AA110: =O110*$L:$L -> 0 | AB110: =P110*$L:$L -> 0 | AC110: =Q110*$L:$L -> 0 | AD110: =R110*$L:$L -> 0 | AE110: =S110*$L:$L -> 0 | AF110: =T110*$L:$L -> 0 | AG110: =U110*$L:$L -> 0 | AH110: =V110*$L:$L -> 0 | ... AL110: =Z110*$L:$L -> 0 | AN110: =C110&I110 -> NM013602858iShop | AO110: {=IFERROR(VLOOKUP(_xlfn.SINGLE(AN:AN),'[1]Pivot SI'!$R:$Y,{2,3,4,5,6,7,8},0),0)} -> 0 | AP110: 0 | AQ110: 0 | AR110: 0 | AS110: 0 | AT110: 0 | AU110: 0
A111: Nomad | B111: 856500016962 | C111: NM01696285 | D111: 856500016962 | E111: Nomad Modern Leather Case - iPhone 16 Pro Brown | F111: Cases iPhone | G111: iPhone 16 | H111: iPhone 16 Pro / iPhone 17 | I111: iShop | J111: Firme | K111: 0 | L111: 473.66 | M111: Descontinuado | N111: Discontinued | O111: 0 | P111: 0 | Q111: 0 | R111: 0 | S111: 0 | T111: 0 | U111: 0 | V111: 0 | W111: 0 | X111: 0 | Y111: 0 | Z111: 0 | AA111: =O111*$L:$L -> 0 | AB111: =P111*$L:$L -> 0 | AC111: =Q111*$L:$L -> 0 | AD111: =R111*$L:$L -> 0 | AE111: =S111*$L:$L -> 0 | AF111: =T111*$L:$L -> 0 | AG111: =U111*$L:$L -> 0 | AH111: =V111*$L:$L -> 0 | ... AL111: =Z111*$L:$L -> 0 | AN111: =C111&I111 -> NM01696285iShop | AO111: {=IFERROR(VLOOKUP(_xlfn.SINGLE(AN:AN),'[1]Pivot SI'!$R:$Y,{2,3,4,5,6,7,8},0),0)} -> 0 | AP111: 0 | AQ111: 0 | AR111: 0 | AS111: 0 | AT111: 0 | AU111: 0
A112: Nomad | B112: 856500016979 | C112: NM01697985 | D112: 856500016979 | E112: Nomad Modern Leather Case - iPhone 16 Pro Black | F112: Cases iPhone | G112: iPhone 16 | H112: iPhone 16 Pro / iPhone 17 | I112: iShop | J112: Firme | K112: 0 | L112: 473.66 | M112: Descontinuado | N112: Discontinued | O112: 0 | P112: 0 | Q112: 0 | R112: 0 | S112: 0 | T112: 0 | U112: 0 | V112: 0 | W112: 0 | X112: 0 | Y112: 0 | Z112: 0 | AA112: =O112*$L:$L -> 0 | AB112: =P112*$L:$L -> 0 | AC112: =Q112*$L:$L -> 0 | AD112: =R112*$L:$L -> 0 | AE112: =S112*$L:$L -> 0 | AF112: =T112*$L:$L -> 0 | AG112: =U112*$L:$L -> 0 | AH112: =V112*$L:$L -> 0 | ... AL112: =Z112*$L:$L -> 0 | AN112: =C112&I112 -> NM01697985iShop | AO112: {=IFERROR(VLOOKUP(_xlfn.SINGLE(AN:AN),'[1]Pivot SI'!$R:$Y,{2,3,4,5,6,7,8},0),0)} -> 0 | AP112: 0 | AQ112: 0 | AR112: 0 | AS112: 0 | AT112: 0 | AU112: 0
A113: Nomad | B113: 856500016924 | C113: NM01692485 | D113: 856500016924 | E113: Nomad Modern Leather Case - iPhone 16 Pro Max | Brown | Nomad Leather | F113: Cases iPhone | G113: iPhone 16 | H113: iPhone 16 Pro Max | I113: iShop | J113: Firme | K113: 0 | L113: 473.66 | M113: Descontinuado | N113: Discontinued | O113: 0 | P113: 0 | Q113: 0 | R113: 0 | S113: 0 | T113: 0 | U113: 0 | V113: 0 | W113: 0 | X113: 0 | Y113: 0 | Z113: 0 | AA113: =O113*$L:$L -> 0 | AB113: =P113*$L:$L -> 0 | AC113: =Q113*$L:$L -> 0 | AD113: =R113*$L:$L -> 0 | AE113: =S113*$L:$L -> 0 | AF113: =T113*$L:$L -> 0 | AG113: =U113*$L:$L -> 0 | AH113: =V113*$L:$L -> 0 | ... AL113: =Z113*$L:$L -> 0 | AN113: =C113&I113 -> NM01692485iShop | AO113: {=IFERROR(VLOOKUP(_xlfn.SINGLE(AN:AN),'[1]Pivot SI'!$R:$Y,{2,3,4,5,6,7,8},0),0)} -> 0 | AP113: 0 | AQ113: 0 | AR113: 0 | AS113: 0 | AT113: 0 | AU113: 0
...

Sheet Master iP17 iP18
A1: Marca | B1: ITEM iP18 | C1: Descripción iP18 | D1: Clase | E1: iTEM iP17 | F1: Descripción iP17 | G1: ITEM iP | H1: Descripcion
A2: Nomad | B2: NM009162858 | C2: Nomad Modern Leather Case - iPhone 18 Pro Max | Brown | Nomad Leather | D2: iPhone 18 Pro Max | E2: NM014278858 | F2: Nomad Modern Leather Case - iPhone 17 Pro Max | Brown | Nomad Leather | G2: =CONCATENATE(E2,"-",B2) -> NM014278858-NM009162858 | H2: =C2 -> Nomad Modern Leather Case - iPhone 18 Pro Max | Brown | Nomad Leather
A3: Nomad | B3: NM009179858 | C3: Nomad Modern Leather Case - iPhone 18 Pro Max | Black | Nomad Leather | D3: iPhone 18 Pro Max | E3: NM014285858 | F3: Nomad Modern Leather Case - iPhone 17 Pro Max | Black | Nomad Leather | G3: =CONCATENATE(E3,"-",B3) -> NM014285858-NM009179858 | H3: =C3 -> Nomad Modern Leather Case - iPhone 18 Pro Max | Black | Nomad Leather
A4: Nomad | B4: NM009247858 | C4: Nomad Modern Leather Case - iPhone 18 Pro | Brown | Nomad Leather | D4: iPhone 18 Pro | E4: NM014322858 | F4: Nomad Modern Leather Case - iPhone 17 Pro | Brown | Nomad Leather | G4: =CONCATENATE(E4,"-",B4) -> NM014322858-NM009247858 | H4: =C4 -> Nomad Modern Leather Case - iPhone 18 Pro | Brown | Nomad Leather
A5: Nomad | B5: NM009254858 | C5: Nomad Modern Leather Case - iPhone 18 Pro | Black | Nomad Leather | D5: iPhone 18 Pro | E5: NM014339858 | F5: Nomad Modern Leather Case - iPhone 17 Pro | Black | Nomad Leather | G5: =CONCATENATE(E5,"-",B5) -> NM014339858-NM009254858 | H5: =C5 -> Nomad Modern Leather Case - iPhone 18 Pro | Black | Nomad Leather
A6: Speck | B6: 151096-3261 | C6: Speck Presidio2 Grip + MagSafe/CC Deep Sea iPhone 18 Pro | D6: iPhone 18 Pro | E6: 151020-3261 | F6: Speck Presidio2 + MS iPhone 17 Pro Deep Sea/Silver Metallic/Spell Blue | G6: =CONCATENATE(E6,"-",B6) -> 151020-3261-151096-3261 | H6: =C6 -> Speck Presidio2 Grip + MagSafe/CC Deep Sea iPhone 18 Pro
A7: Speck | B7: 151096-D143 | C7: Speck Presidio2 Grip + MagSafe/CC Black iPhone 18 Pro | D7: iPhone 18 Pro | E7: 150976-D143 | F7: Speck Presidio2 Grip + MS iPhone 17 Pro Black | G7: =CONCATENATE(E7,"-",B7) -> 150976-D143-151096-D143 | H7: =C7 -> Speck Presidio2 Grip + MagSafe/CC Black iPhone 18 Pro
A8: Speck | B8: 151098-3240 | C8: Speck Presidio Perfect Clear + C-MagSafe/CC Clear iPhone 18 Pro | D8: iPhone 18 Pro | E8: 150972-3240 | F8: Speck Presidio Perfect-Clear iPhone 17 Pro Clear | G8: =CONCATENATE(E8,"-",B8) -> 150972-3240-151098-3240 | H8: =C8 -> Speck Presidio Perfect Clear + C-MagSafe/CC Clear iPhone 18 Pro
A9: Speck | B9: 151106-9221 | C9: Speck Presidio Lux + C-MagSafe/CC Gold Glitter iPhone 18 Pro | D9: iPhone 18 Pro | E9: 150978-9221 | F9: Speck Presidio Lux iPhone 17 Pro Glitter/Gold | G9: =CONCATENATE(E9,"-",B9) -> 150978-9221-151106-9221 | H9: =C9 -> Speck Presidio Lux + C-MagSafe/CC Gold Glitter iPhone 18 Pro
A10: Speck | B10: 151108-3261 | C10: Speck Presidio2 Grip + MagSafe/CC Deep Sea iPhone 18 Pro Max | D10: iPhone 18 Pro Max | E10: 151025-3261 | F10: Speck Presidio2 + MS iPhone 17 Pro Max Deep Sea/Silver Metallic/Spell Blue | G10: =CONCATENATE(E10,"-",B10) -> 151025-3261-151108-3261 | H10: =C10 -> Speck Presidio2 Grip + MagSafe/CC Deep Sea iPhone 18 Pro Max
A11: Speck | B11: 151108-D143 | C11: Speck Presidio2 Grip + MagSafe/CC Black iPhone 18 Pro Max | D11: iPhone 18 Pro Max | E11: 150986-D143 | F11: Speck Presidio2 Grip iPhone 17 Pro Max Black | G11: =CONCATENATE(E11,"-",B11) -> 150986-D143-151108-D143 | H11: =C11 -> Speck Presidio2 Grip + MagSafe/CC Black iPhone 18 Pro Max
A12: Speck | B12: 151110-3240 | C12: Speck Presidio Perfect Clear + C-MagSafe/CC Clear iPhone 18 Pro Max | D12: iPhone 18 Pro Max | E12: 150981-3240 | F12: Speck Presidio Perfect-Clear iPhone 17 Pro Max Clear | G12: =CONCATENATE(E12,"-",B12) -> 150981-3240-151110-3240 | H12: =C12 -> Speck Presidio Perfect Clear + C-MagSafe/CC Clear iPhone 18 Pro Max
A13: Speck | B13: 151118-9221 | C13: Speck Presidio Lux + C-MagSafe/CC Gold Glitter iPhone 18 Pro Max | D13: iPhone 18 Pro Max | E13: 150987-9221 | F13: Speck Presidio Lux iPhone 17 Pro Max Glitter/Gold | G13: =CONCATENATE(E13,"-",B13) -> 150987-9221-151118-9221 | H13: =C13 -> Speck Presidio Lux + C-MagSafe/CC Gold Glitter iPhone 18 Pro Max
... A18: Uniq | B18: UNIQ-IP6.3P(2026)-KEVAMCBLK | C18: UNIQ HYBRID IPHONE 18 PRO (2026) 6.3 MAGCLICK CHARGING KEVA - CARBON BLACK | D18: iPhone 18 Pro | E18: UNIQ-IP6.3P(2025)-KEVAMCBLK | F18: UNIQ HYBRID IPHONE 17 PRO MAGCLICK CHARGING KEVA - CARBON BLACK (CARBON BLACK) | G18: =CONCATENATE(E18,"-",B18) -> UNIQ-IP6.3P(2025)-KEVAMCBLK-UNIQ-IP6.3P(2026)-KEVAMCBLK | H18: =C18 -> UNIQ HYBRID IPHONE 18 PRO (2026) 6.3 MAGCLICK CHARGING KEVA - CARBON BLACK
A19: Uniq | B19: UNIQ-IP6.9P(2026)-KEVAMCBLK | C19: UNIQ HYBRID IPHONE 18 PRO MAX (2026) 6.9 MAGCLICK CHARGING KEVA - CARBON BLACK | D19: iPhone 18 Pro Max | E19: UNIQ-IP6.9P(2025)-KEVAMCBLK | F19: UNIQ HYBRID IPHONE 17 PRO MAX MAGCLICK CHARGING KEVA - CARBON BLACK (CARBON BLACK) | G19: iPhone 17 Pro Max

Sheet POs
D5: =SUBTOTAL(9,D7:D186) -> 0 | E5: =SUBTOTAL(9,E7:E186) -> 0 | F5: =SUBTOTAL(9,F7:F186) -> 0 | G5: =SUBTOTAL(9,G7:G186) -> 0 | H5: =SUBTOTAL(9,H7:H186) -> 0 | I5: =SUBTOTAL(9,I7:I186) -> 0
A6: Marca | B6: ITEM | C6: Descripción
A7: Nomad | B7: NM00736685 | C7: Nomad Sport Band - 45mm | Ultra Orange
B8: NM009162858 | C8: Nomad Modern Leather Case - iPhone 18 Pro Max | Brown | Nomad Leather
B9: NM009179858 | C9: Nomad Modern Leather Case - iPhone 18 Pro Max | Black | Nomad Leather
B10: NM009247858 | C10: Nomad Modern Leather Case - iPhone 18 Pro | Brown | Nomad Leather
B11: NM009254858 | C11: Nomad Modern Leather Case - iPhone 18 Pro | Black | Nomad Leather
B12: NM011116858 | C12: Nomad Stratos Band - 49mm | Black Titanium | Ultra Orange FKM
B13: NM011123858 | C13: Nomad Stratos Band - 49mm | Natural Titanium | Ultra Orange FKM
B14: NM011284858 | C14: Nomad Modern Leather Case - Airpods Pro 3 | Rustic Brown | Horween
B15: NM011291858 | C15: Nomad Modern Leather Case - Airpods Pro 3 | Black | Horween
B16: NM011697858 | C16: Nomad Rocky Point Band - 46mm/49mm | Carbon Black | Black Hardware
B17: NM01187585 | C17: Nomad AC Adapter - 65W | Slim | Carbide
B18: NM014278858 | C18: Nomad Modern Leather Case - iPhone 17 Pro Max | Brown | Nomad Leather
B19: NM014285858 | C19: Nomad Modern Leather Case - iPhone 17 Pro Max | Black | Nomad Leather
... B30: NM009797858 | C30: Nomad Tempo Band - 46mm | Seagrass
A31: Quikcell | B31: GQC2232 | C31: Quikcell Tempered Glass Screen Protector for iPhone 17 / Pro
B32: QC-LIQUIDG | C32: Quikcell Ultra LIQUID GLASS Screen Protector
B33: QCC3FT-BLK | C33: Quikcell USB-C to USB-C cable 3 ft. 3A current; PVC+Nylon
B34: QCC6FT-BLK | C34: Quikcell CHARGE & SYNC CABLE USB-C to USB-C - 6 ft - Black
B35: QCPD25W-WT | C35: Quikcell PD 25W Single USB-C Port Wall Charger White
B36: QCPD35W-WT | C36: Quikcell 35W PD A+C Dual Ports Wall Charger White
B37: QCVPA2005 | C37: Quikcell 37W DUAL PORT A+C CAR CHARGER - Black
A38: Speck | B38: 127573-9166 | C38: Speck Transfer Pro Pocket Universal Sleeve 13"/14" - Sweater Grey/Coastal Blue
B39: 140548-1050 | C39: Speck Balance Folio Case with Microban for iPad Pro 11" M1/Air 10.9" - Black
B40: 140999-1050 | C40: Speck Presidio Pro Folio Case for iPad Pro 11" 2/M1/M2 /Air 10.9" 4/5 - Black
B41: 142573-1050 | C41: Speck Balance Folio with Microban for iPad mini 6 - Black
B42: 144896-9352 | C42: Speck Smartshell Case with Microban for Macbook Pro 14" M1/M2 - Swell Blue
B43: 150225-3085 | C43: Speck Smartshell Case for Macbook Air 13" M2 2022 - Obsidian
B44: 150225-3086 | C44: Speck Smartshell Macbook Air M2/M3 Cozy Pink/Cozy Pink/Swtrgrey
B45: 150225-9992 | C45: Speck Smartshell Macbook Air M2/M3 Clear/Clear/Sweatergrey
B46: 150226-7265 | C46: Speck Balance Folio Case for iPad 10th Gen - Plumberry/Crushed Purple/Crepe Pink
B47: 150226-9969 | C47: Speck Balance Folio Case for iPad 10th Gen - Almond Milk /Mocha/Charcoal
B48: 150226-D143 | C48: Speck Balance Folio Case for iPad 10th Gen - Black/Black/White
B49: 150422-1041 | C49: Speck Car Vent Mount for MagSafe Black iPhone 15 Car
B50: 150423-1041 | C50: Speck Wallet for MagSafe® Black iPhone 15 Wallet
... B103: 151119-5085 | C103: Speck Presidio Perfect Clear Fold + MagSafe Clear iPhone 18 FOLD
A104: Tech21 | B104: T21-10260 | C104: Tech21 EvoLite for iPhone 15 - Clear
B105: T21-10441 | C105: Tech21 EvoLite for iPhone 15 - Lavender
B106: T21-10857 | C106: Tech21 EvoCrystal w/MagSafe for iPhone 16 - Black
B107: T21-11240 | C107: Tech21 EvoLite for AirPods 4 - Clear
B108: T21-11303 | C108: Tech21 EvoClear iPhone 17 Clear
B109: T21-11304 | C109: Tech21 EvoCrystal iPhone 17 Black
B110: T21-11323 | C110: Tech21 EvoClear iPhone 17 Pro Clear
B111: T21-11324 | C111: Tech21 EvoCrystal iPhone 17 Pro Black
B112: T21-11331 | C112: Tech21 EvoPro w/MagSafe Clear/Black iPhone 17 Pro
B113: T21-11334 | C113: Tech21 EvoClear iPhone 17 Pro Max Clear
B114: T21-11335 | C114: Tech21 EvoCrystal iPhone 17 Pro Max Black
B115: T21-11342 | C115: Tech21 EvoPro w/MagSafe Clear/Black iPhone 17 Pro Max
B116: T21-11353 | C116: Tech21 EvoCrystal iPhone 17 Pro Iridescent
... B152: T21-11741 | C152: Tech21 Apple AP-1042 EvoClear w/C-MagSafe/CC - Mandala Pattern
A153: Uniq | B153: UNIQ-45MM-REVPNKBEG | C153: UNIQ REVIX REVERSIBLE MAGNETIC APPLE WATCH STRAP 49/46/45/44MM - BLUSH (PINK/BEIGE)
B154: UNIQ-49MM-OSTABLK | C154: UNIQ OSTA APPLE WATCH STEEL STRAP WITH SELF-ADJUSTABLE LINKS 49/46/45/44MM - MIDNIGHT (BLACK)
B155: UNIQ-49MM-STRVMSIL | C155: UNIQ STROVA MAG APPLE WATCH SELF-ADJUSTABLE STEEL LINK BAND 49/46/45/44MM - TITANIUM (SILVER)
B156: UNIQ-AIRPODS(2024)-GLSPCBLU | C156: UNIQ GLASE PRO AIRPODS 4TH GEN LOCK CASE - CLOUDY BLUE (CLOUDY BLUE)
B157: UNIQ-AIRPODS(2024)-GLSPCPNK | C157: UNIQ GLASE PRO AIRPODS 4TH GEN LOCK CASE - CANDY PINK (CANDY PINK)
B158: UNIQ-AIRPODS(2024)-GLSPGCLR | C158: UNIQ GLASE PRO AIRPODS 4TH GEN LOCK CASE - GLOSSY CLEAR (GLOSSY CLEAR)
B159: UNIQ-AIRPODS(2024)-GLSPGSMK | C159: UNIQ GLASE PRO AIRPODS 4TH GEN LOCK CASE - GLOSSY SMOKE (GLOSSY SMOKE)
B160: UNIQ-AIRPODS(2024)-GLSPLLIM | C160: UNIQ GLASE PRO AIRPODS 4TH GEN LOCK CASE - LIGHT LIME (LIGHT LIME)
B161: UNIQ-AIRPODS(2024)-NEXOBLK | C161: UNIQ NEXO ACTIVE HYBRID SILICONE AIRPODS 4TH GEN (2024) CASE WITH SPORTS EAR HOOKS - BLACK (BLACK)
B162: UNIQ-AIRPODS(2024)-NEXOPBLU | C162: UNIQ NEXO ACTIVE HYBRID SILICONE AIRPODS 4TH GEN (2024) CASE WITH SPORTS EAR HOOKS - PACIFIC BLUE (PACIFIC BLUE)
B163: UNIQ-IP6.3P(2025)-COMAMFCLRLL | C163: UNIQ HYBRID IPHONE 17 PRO MAGCLICK CHARGING COMBAT ACTIVE - FROST CLEAR / LUME-LIME (FROST CLEAR / LUME-LIME)
B164: UNIQ-IP6.3P(2025)-COMAMFSMKO | C164: UNIQ HYBRID IPHONE 17 PRO MAGCLICK CHARGING COMBAT ACTIVE - FROST SMOKE / ORANGE (FROST SMOKE / ORANGE)
B165: UNIQ-IP6.3P(2025)-KEVAMCBLK | C165: UNIQ HYBRID IPHONE 17 PRO MAGCLICK CHARGING KEVA - CARBON BLACK (CARBON BLACK)
... B183: UNIQ-49MM-DANPMRSE | C183: UNIQ DANTE PRO APPLE WATCH SELF-ADJUSTABLE MESH STEEL BAND 49/46/45/44MM - METALLIC ROSE (METALLIC ROSE)
A184: Total general

Sheet Detalle
G1: =SUBTOTAL(9,G3:G181) -> 18720 | H1: =SUBTOTAL(9,H3:H181) -> 3980 | I1: =SUBTOTAL(9,I3:I181) -> 8385 | J1: =SUBTOTAL(9,J3:J181) -> 15716 | K1: =SUBTOTAL(9,K3:K181) -> 13785 | L1: =SUBTOTAL(9,L3:L181) -> 18532 | M1: =SUBTOTAL(9,M3:M181) -> 17672 | N1: =SUBTOTAL(9,N3:N181) -> 158466 | ... U1: =SUBTOTAL(9,U3:U181) -> 0 | AJ1: =SUBTOTAL(9,AJ3:AJ181) -> 1309 | AK1: =SUBTOTAL(9,AK3:AK181) -> 2277 | AL1: =SUBTOTAL(9,AL3:AL181) -> 3426 | AM1: =SUBTOTAL(9,AM3:AM181) -> 8571 | AN1: =SUBTOTAL(9,AN3:AN181) -> 16309 | AO1: =SUBTOTAL(9,AO3:AO181) -> 14566 | AS1: =SUBTOTAL(9,AS3:AS172) -> 594 | AT1: =SUBTOTAL(9,AT3:AT172) -> 1483 | AU1: =SUBTOTAL(9,AU3:AU172) -> 3125 | AV1: =SUBTOTAL(9,AV3:AV172) -> 8229 | AW1: =SUBTOTAL(9,AW3:AW172) -> 15941 | AX1: =SUBTOTAL(9,AX3:AX172) -> 14225 | BA1: =SUBTOTAL(9,BA3:BA181) -> 6936712.6 | BB1: =SUBTOTAL(9,BB3:BB181) -> 9461611.6 | BC1: =SUBTOTAL(9,BC3:BC181) -> 13460447 | BD1: =SUBTOTAL(9,BD3:BD181) -> 13387341 | BE1: =SUBTOTAL(9,BE3:BE181) -> 16356581 | BF1: =SUBTOTAL(9,BF3:BF181) -> 14956958
A2: Marca | B2: ITEM | C2: Descripción | D2: Clase | E2: Estatus | F2: Cost USD | G2: Roll Out | H2: Suma de Nec Jul | I2: Suma de Nec Aug | J2: Suma de Nec Sep | K2: Suma de Nec Oct | L2: Suma de Nec Nov | M2: Suma de Nec Dec | N2: OH ACA | O2: OO Jun | P2: OO Jul | Q2: OO Aug | R2: OO Sep | S2: OO Oct | T2: OO Nov | U2: OO Dec | V2: INV Final JUL | W2: INV Final AUG | X2: INV Final SEP | Y2: INV Final OCT | Z2: INV Final NOV | AA2: INV Final DEC | AB2: Esquema | AC2: Par iP17 | AD2: INV Aj Jul | AE2: INV Aj Aug | AF2: INV Aj Sep | AG2: INV Aj Oct | AH2: INV Aj Nov | AI2: INV Aj Dec | AJ2: In WHS Jul | AK2: In WHS Aug | AL2: In WHS Sep | AM2: In WHS Oct | AN2: In WHS Nov | AO2: In WHS Dec | AP2: W25 - Comentarios Generales | AQ2: x | AR2: Safety Stock | AS2: Safety PO Jul | AT2: Safety PO Aug | AU2: Safety PO Sep | AV2: Safety PO Oct | AW2: Safety PO Nov | AX2: Safety PO Dec | AY2: W27 - Comentarios Generales | AZ2: W30 comentarios Generales | BA2: Jul | BB2: Aug | BC2: Sep | BD2: Oct | BE2: Nov | BF2: Dec
A3: Speck | B3: 127573-9166 | C3: Speck Transfer Pro Pocket Universal Sleeve 13"/14" - Sweater Grey/Coastal Blue | D3: 13" Sleeves | E3: Activo | F3: 11 | G3: 0 | H3: =SUMIF(Consenso!$C:$C,$B3,Consenso!AM:AM) -> 9 | I3: =SUMIF(Consenso!$C:$C,$B3,Consenso!AN:AN) -> 21 | J3: =SUMIF(Consenso!$C:$C,$B3,Consenso!AO:AO) -> 12 | K3: =SUMIF(Consenso!$C:$C,$B3,Consenso!AP:AP) -> 33 | L3: =SUMIF(Consenso!$C:$C,$B3,Consenso!AQ:AQ) -> 12 | M3: =SUMIF(Consenso!$C:$C,$B3,Consenso!AR:AR) -> 12 | N3: =IFERROR(VLOOKUP(B:B,Consenso!C:P,14,0),0) -> 0 | O3: =SUMIF('On Orders'!$B:$B,$B3,'On Orders'!E:E) -> 0 | P3: =SUMIF('On Orders'!$B:$B,$B3,'On Orders'!F:F) -> 48 | Q3: =SUMIF('On Orders'!$B:$B,$B3,'On Orders'!G:G) -> 0 | R3: =SUMIF('On Orders'!$B:$B,$B3,'On Orders'!H:H) -> 0 | S3: 0 | T3: 0 | U3: 0 | V3: =(N3+O3+P3)-H3 -> 39 | W3: =(V3+Q3)-I3 -> 18 | X3: =(W3+R3)-J3 -> 6 | Y3: =(X3+S3)-K3 -> -27 | Z3: =(Y3+T3)-L3 -> -39 | AA3: =(Z3+U3)-M3 -> -51 | AB3: =IF(COUNTIF('Master iP17 iP18'!$B:$B,$B3)>0,"18",IF(COUNTIF('Master iP17 iP18'!$E:$E,$B3)>0,"17","NORMAL")) -> NORMAL | AC3: =IF($AB3="18",_xlfn.XLOOKUP($B3,'Master iP17 iP18'!$B:$B,'Master iP17 iP18'!$E:$E),"") | AD3: =IF($AB3="18",V3+IFERROR(_xlfn.XLOOKUP($AC3,$B:$B,V:V),0),V3) -> 39 | AE3: =IF($AB3="18",W3+IFERROR(_xlfn.XLOOKUP($AC3,$B:$B,W:W),0),W3) -> 18 | AF3: =IF($AB3="18",X3+IFERROR(_xlfn.XLOOKUP($AC3,$B:$B,X:X),0),X3) -> 6 | AG3: =IF($AB3="18",Y3+IFERROR(_xlfn.XLOOKUP($AC3,$B:$B,Y:Y),0),Y3) -> -27 | AH3: =IF($AB3="18",Z3+IFERROR(_xlfn.XLOOKUP($AC3,$B:$B,Z:Z),0),Z3) -> -39 | AI3: =IF($AB3="18",AA3+IFERROR(_xlfn.XLOOKUP($AC3,$B:$B,AA:AA),0),AA3) -> -51 | AJ3: =IF($AB3="17",0,MAX(0,-AD3)) -> 0 | AK3: =IF($AB3="17",0,MAX(0,MAX(0,-AE3)-MAX(0,-AD3))) -> 0 | AL3: =IF($AB3="17",0,MAX(0,MAX(0,-AF3)-MAX(0,-AE3))) -> 0 | AM3: =IF($AB3="17",0,MAX(0,MAX(0,-AG3)-MAX(0,-AF3))) -> 27 | AN3: =IF($AB3="17",0,MAX(0,MAX(0,-AH3)-MAX(0,-AG3))) -> 12 | AO3: =IF($AB3="17",0,MAX(0,MAX(0,-AI3)-MAX(0,-AH3))) -> 12 | AP3: Poner PO 40 Mediados Julio | AR3: =IFERROR(_xlfn.XLOOKUP(B3,#REF!,#REF!),"") | AS3: =IF($AR3="A",AJ3*1.2,IF($AR3="B",AJ3*1.1,AJ3)) -> 0 | AT3: =IF($AR3="A",AK3*1.2,IF($AR3="B",AK3*1.1,AK3)) -> 0 | AU3: =IF($AR3="A",AL3*1.2,IF($AR3="B",AL3*1.1,AL3)) -> 0 | AV3: =IF($AR3="A",AM3*1.2,IF($AR3="B",AM3*1.1,AM3)) -> 27 | AW3: =IF($AR3="A",AN3*1.2,IF($AR3="B",AN3*1.1,AN3)) -> 12 | AX3: =IF($AR3="A",AO3*1.2,IF($AR3="B",AO3*1.1,AO3)) -> 12 | BA3: =SUMIF(Consenso!$C:$C,$B3,Consenso!AZ:AZ) -> 5386.83 | BB3: =SUMIF(Consenso!$C:$C,$B3,Consenso!BA:BA) -> 19118.8 | BC3: =SUMIF(Consenso!$C:$C,$B3,Consenso!BB:BB) -> 11212.92 | BD3: =SUMIF(Consenso!$C:$C,$B3,Consenso!BC:BC) -> 19751.71 | BE3: =SUMIF(Consenso!$C:$C,$B3,Consenso!BD:BD) -> 11716.73 | BF3: =SUMIF(Consenso!$C:$C,$B3,Consenso!BE:BE) -> 14235.78
A4: Speck | B4: 150226-7265 | C4: Speck Balance Folio Case for iPad 10th Gen - Plumberry/Crushed Purple/Crepe Pink | D4: iPad 10th /11th - 10.9"/11" (2022-2025) | E4: Activo | F4: 14 | G4: 0 | H4: =SUMIF(Consenso!$C:$C,$B4,Consenso!AM:AM) -> 0 | I4: =SUMIF(Consenso!$C:$C,$B4,Consenso!AN:AN) -> 268 | J4: =SUMIF(Consenso!$C:$C,$B4,Consenso!AO:AO) -> 120 | K4: =SUMIF(Consenso!$C:$C,$B4,Consenso!AP:AP) -> 90 | L4: =SUMIF(Consenso!$C:$C,$B4,Consenso!AQ:AQ) -> 320 | M4: =SUMIF(Consenso!$C:$C,$B4,Consenso!AR:AR) -> 110 | N4: =IFERROR(VLOOKUP(B:B,Consenso!C:P,14,0),0) -> 0 | O4: =SUMIF('On Orders'!$B:$B,$B4,'On Orders'!E:E) -> 0 | P4: =SUMIF('On Orders'!$B:$B,$B4,'On Orders'!F:F) -> 352 | Q4: =SUMIF('On Orders'!$B:$B,$B4,'On Orders'!G:G) -> 0 | R4: =SUMIF('On Orders'!$B:$B,$B4,'On Orders'!H:H) -> 0 | S4: 0 | T4: 0 | U4: 0 | V4: =(N4+O4+P4)-H4 -> 352 | W4: =(V4+Q4)-I4 -> 84 | X4: =(W4+R4)-J4 -> -36 | Y4: =(X4+S4)-K4 -> -126 | Z4: =(Y4+T4)-L4 -> -446 | AA4: =(Z4+U4)-M4 -> -556 | AB4: =IF(COUNTIF('Master iP17 iP18'!$B:$B,$B4)>0,"18",IF(COUNTIF('Master iP17 iP18'!$E:$E,$B4)>0,"17","NORMAL")) -> NORMAL | AC4: =IF($AB4="18",_xlfn.XLOOKUP($B4,'Master iP17 iP18'!$B:$B,'Master iP17 iP18'!$E:$E),"") | AD4: =IF($AB4="18",V4+IFERROR(_xlfn.XLOOKUP($AC4,$B:$B,V:V),0),V4) -> 352 | AE4: =IF($AB4="18",W4+IFERROR(_xlfn.XLOOKUP($AC4,$B:$B,W:W),0),W4) -> 84 | AF4: =IF($AB4="18",X4+IFERROR(_xlfn.XLOOKUP($AC4,$B:$B,X:X),0),X4) -> -36 | AG4: =IF($AB4="18",Y4+IFERROR(_xlfn.XLOOKUP($AC4,$B:$B,Y:Y),0),Y4) -> -126 | AH4: =IF($AB4="18",Z4+IFERROR(_xlfn.XLOOKUP($AC4,$B:$B,Z:Z),0),Z4) -> -446 | AI4: =IF($AB4="18",AA4+IFERROR(_xlfn.XLOOKUP($AC4,$B:$B,AA:AA),0),AA4) -> -556 | AJ4: =IF($AB4="17",0,MAX(0,-AD4)) -> 0 | AK4: =IF($AB4="17",0,MAX(0,MAX(0,-AE4)-MAX(0,-AD4))) -> 0 | AL4: =IF($AB4="17",0,MAX(0,MAX(0,-AF4)-MAX(0,-AE4))) -> 36 | AM4: =IF($AB4="17",0,MAX(0,MAX(0,-AG4)-MAX(0,-AF4))) -> 90 | AN4: =IF($AB4="17",0,MAX(0,MAX(0,-AH4)-MAX(0,-AG4))) -> 320 | AO4: =IF($AB4="17",0,MAX(0,MAX(0,-AI4)-MAX(0,-AH4))) -> 110 | AP4: PO 350 Med Julio | AR4: =IFERROR(_xlfn.XLOOKUP(B4,#REF!,#REF!),"") | AS4: =IF($AR4="A",AJ4*1.2,IF($AR4="B",AJ4*1.1,AJ4)) -> 0 | AT4: =IF($AR4="A",AK4*1.2,IF($AR4="B",AK4*1.1,AK4)) -> 0 | AU4: =IF($AR4="A",AL4*1.2,IF($AR4="B",AL4*1.1,AL4)) -> 36 | AV4: =IF($AR4="A",AM4*1.2,IF($AR4="B",AM4*1.1,AM4)) -> 90 | AW4: =IF($AR4="A",AN4*1.2,IF($AR4="B",AN4*1.1,AN4)) -> 320 | AX4: =IF($AR4="A",AO4*1.2,IF($AR4="B",AO4*1.1,AO4)) -> 110 | AY4: Volar 352 - PO / FCST 1,400 resto del año | BA4: =SUMIF(Consenso!$C:$C,$B4,Consenso!AZ:AZ) -> 20656.21 | BB4: =SUMIF(Consenso!$C:$C,$B4,Consenso!BA:BA) -> 156209.41 | BC4: =SUMIF(Consenso!$C:$C,$B4,Consenso!BB:BB) -> 77366.31 | BD4: =SUMIF(Consenso!$C:$C,$B4,Consenso!BC:BC) -> 71501.65 | BE4: =SUMIF(Consenso!$C:$C,$B4,Consenso!BD:BD) -> 176585.37 | BF4: =SUMIF(Consenso!$C:$C,$B4,Consenso!BE:BE) -> 90189.85
A5: Speck | B5: 150226-9969 | C5: Speck Balance Folio Case for iPad 10th Gen - Almond Milk /Mocha/Charcoal | D5: iPad 10th /11th - 10.9"/11" (2022-2025) | E5: Activo | F5: 14 | G5: 0 | H5: =SUMIF(Consenso!$C:$C,$B5,Consenso!AM:AM) -> 73 | I5: =SUMIF(Consenso!$C:$C,$B5,Consenso!AN:AN) -> 175 | J5: =SUMIF(Consenso!$C:$C,$B5,Consenso!AO:AO) -> 123 | K5: =SUMIF(Consenso!$C:$C,$B5,Consenso!AP:AP) -> 80 | L5: =SUMIF(Consenso!$C:$C,$B5,Consenso!AQ:AQ) -> 280 | M5: =SUMIF(Consenso!$C:$C,$B5,Consenso!AR:AR) -> 95 | N5: =IFERROR(VLOOKUP(B:B,Consenso!C:P,14,0),0) -> 38 | O5: =SUMIF('On Orders'!$B:$B,$B5,'On Orders'!E:E) -> 0 | P5: =SUMIF('On Orders'!$B:$B,$B5,'On Orders'!F:F) -> 160 | Q5: =SUMIF('On Orders'!$B:$B,$B5,'On Orders'!G:G) -> 0 | R5: =SUMIF('On Orders'!$B:$B,$B5,'On Orders'!H:H) -> 0 | S5: 0 | T5: 0 | U5: 0 | V5: =(N5+O5+P5)-H5 -> 125 | W5: =(V5+Q5)-I5 -> -50 | X5: =(W5+R5)-J5 -> -173 | Y5: =(X5+S5)-K5 -> -253 | Z5: =(Y5+T5)-L5 -> -533 | AA5: =(Z5+U5)-M5 -> -628 | AB5: =IF(COUNTIF('Master iP17 iP18'!$B:$B,$B5)>0,"18",IF(COUNTIF('Master iP17 iP18'!$E:$E,$B5)>0,"17","NORMAL")) -> NORMAL | AC5: =IF($AB5="18",_xlfn.XLOOKUP($B5,'Master iP17 iP18'!$B:$B,'Master iP17 iP18'!$E:$E),"") | AD5: =IF($AB5="18",V5+IFERROR(_xlfn.XLOOKUP($AC5,$B:$B,V:V),0),V5) -> 125 | AE5: =IF($AB5="18",W5+IFERROR(_xlfn.XLOOKUP($AC5,$B:$B,W:W),0),W5) -> -50 | AF5: =IF($AB5="18",X5+IFERROR(_xlfn.XLOOKUP($AC5,$B:$B,X:X),0),X5) -> -173 | AG5: =IF($AB5="18",Y5+IFERROR(_xlfn.XLOOKUP($AC5,$B:$B,Y:Y),0),Y5) -> -253 | AH5: =IF($AB5="18",Z5+IFERROR(_xlfn.XLOOKUP($AC5,$B:$B,Z:Z),0),Z5) -> -533 | AI5: =IF($AB5="18",AA5+IFERROR(_xlfn.XLOOKUP($AC5,$B:$B,AA:AA),0),AA5) -> -628 | AJ5: =IF($AB5="17",0,MAX(0,-AD5)) -> 0 | AK5: =IF($AB5="17",0,MAX(0,MAX(0,-AE5)-MAX(0,-AD5))) -> 50 | AL5: =IF($AB5="17",0,MAX(0,MAX(0,-AF5)-MAX(0,-AE5))) -> 123 | AM5: =IF($AB5="17",0,MAX(0,MAX(0,-AG5)-MAX(0,-AF5))) -> 80 | AN5: =IF($AB5="17",0,MAX(0,MAX(0,-AH5)-MAX(0,-AG5))) -> 280 | AO5: =IF($AB5="17",0,MAX(0,MAX(0,-AI5)-MAX(0,-AH5))) -> 95 | AP5: PO 130 Med Julio | AR5: =IFERROR(_xlfn.XLOOKUP(B5,#REF!,#REF!),"") | AS5: =IF($AR5="A",AJ5*1.2,IF($AR5="B",AJ5*1.1,AJ5)) -> 0 | AT5: =IF($AR5="A",AK5*1.2,IF($AR5="B",AK5*1.1,AK5)) -> 50 | AU5: =IF($AR5="A",AL5*1.2,IF($AR5="B",AL5*1.1,AL5)) -> 123 | AV5: =IF($AR5="A",AM5*1.2,IF($AR5="B",AM5*1.1,AM5)) -> 80 | AW5: =IF($AR5="A",AN5*1.2,IF($AR5="B",AN5*1.1,AN5)) -> 280 | AX5: =IF($AR5="A",AO5*1.2,IF($AR5="B",AO5*1.1,AO5)) -> 95 | AY5: PO / FCST 650 resto del año | AZ5: PO 170 | BA5: =SUMIF(Consenso!$C:$C,$B5,Consenso!AZ:AZ) -> 52090.01 | BB5: =SUMIF(Consenso!$C:$C,$B5,Consenso!BA:BA) -> 109614.08 | BC5: =SUMIF(Consenso!$C:$C,$B5,Consenso!BB:BB) -> 81680.97 | BD5: =SUMIF(Consenso!$C:$C,$B5,Consenso!BC:BC) -> 64676.6 | BE5: =SUMIF(Consenso!$C:$C,$B5,Consenso!BD:BD) -> 156842.32 | BF5: =SUMIF(Consenso!$C:$C,$B5,Consenso!BE:BE) -> 69942.99
A6: Speck | B6: 150226-D143 | C6: Speck Balance Folio Case for iPad 10th Gen - Black/Black/White | D6: iPad 10th /11th - 10.9"/11" (2022-2025) | E6: Activo | F6: 14 | G6: 0 | H6: =SUMIF(Consenso!$C:$C,$B6,Consenso!AM:AM) -> 49 | I6: =SUMIF(Consenso!$C:$C,$B6,Consenso!AN:AN) -> 244 | J6: =SUMIF(Consenso!$C:$C,$B6,Consenso!AO:AO) -> 134 | K6: =SUMIF(Consenso!$C:$C,$B6,Consenso!AP:AP) -> 80 | L6: =SUMIF(Consenso!$C:$C,$B6,Consenso!AQ:AQ) -> 300 | M6: =SUMIF(Consenso!$C:$C,$B6,Consenso!AR:AR) -> 70 | N6: =IFERROR(VLOOKUP(B:B,Consenso!C:P,14,0),0) -> 91 | O6: =SUMIF('On Orders'!$B:$B,$B6,'On Orders'!E:E) -> 0 | P6: =SUMIF('On Orders'!$B:$B,$B6,'On Orders'!F:F) -> 192 | Q6: =SUMIF('On Orders'!$B:$B,$B6,'On Orders'!G:G) -> 0 | R6: =SUMIF('On Orders'!$B:$B,$B6,'On Orders'!H:H) -> 0 | S6: 0 | T6: 0 | U6: 0 | V6: =(N6+O6+P6)-H6 -> 234 | W6: =(V6+Q6)-I6 -> -10 | X6: =(W6+R6)-J6 -> -144 | Y6: =(X6+S6)-K6 -> -224 | Z6: =(Y6+T6)-L6 -> -524 | AA6: =(Z6+U6)-M6 -> -594 | AB6: =IF(COUNTIF('Master iP17 iP18'!$B:$B,$B6)>0,"18",IF(COUNTIF('Master iP17 iP18'!$E:$E,$B6)>0,"17","NORMAL")) -> NORMAL | AC6: =IF($AB6="18",_xlfn.XLOOKUP($B6,'Master iP17 iP18'!$B:$B,'Master iP17 iP18'!$E:$E),"") | AD6: =IF($AB6="18",V6+IFERROR(_xlfn.XLOOKUP($AC6,$B:$B,V:V),0),V6) -> 234 | AE6: =IF($AB6="18",W6+IFERROR(_xlfn.XLOOKUP($AC6,$B:$B,W:W),0),W6) -> -10 | AF6: =IF($AB6="18",X6+IFERROR(_xlfn.XLOOKUP($AC6,$B:$B,X:X),0),X6) -> -144 | AG6: =IF($AB6="18",Y6+IFERROR(_xlfn.XLOOKUP($AC6,$B:$B,Y:Y),0),Y6) -> -224 | AH6: =IF($AB6="18",Z6+IFERROR(_xlfn.XLOOKUP($AC6,$B:$B,Z:Z),0),Z6) -> -524 | AI6: =IF($AB6="18",AA6+IFERROR(_xlfn.XLOOKUP($AC6,$B:$B,AA:AA),0),AA6) -> -594 | AJ6: =IF($AB6="17",0,MAX(0,-AD6)) -> 0 | AK6: =IF($AB6="17",0,MAX(0,MAX(0,-AE6)-MAX(0,-AD6))) -> 10 | AL6: =IF($AB6="17",0,MAX(0,MAX(0,-AF6)-MAX(0,-AE6))) -> 134 | AM6: =IF($AB6="17",0,MAX(0,MAX(0,-AG6)-MAX(0,-AF6))) -> 80 | AN6: =IF($AB6="17",0,MAX(0,MAX(0,-AH6)-MAX(0,-AG6))) -> 300 | AO6: =IF($AB6="17",0,MAX(0,MAX(0,-AI6)-MAX(0,-AH6))) -> 70 | AP6: PO 180 Med Julio | AR6: =IFERROR(_xlfn.XLOOKUP(B6,#REF!,#REF!),"") | AS6: =IF($AR6="A",AJ6*1.2,IF($AR6="B",AJ6*1.1,AJ6)) -> 0 | AT6: =IF($AR6="A",AK6*1.2,IF($AR6="B",AK6*1.1,AK6)) -> 10 | AU6: =IF($AR6="A",AL6*1.2,IF($AR6="B",AL6*1.1,AL6)) -> 134 | AV6: =IF($AR6="A",AM6*1.2,IF($AR6="B",AM6*1.1,AM6)) -> 80 | AW6: =IF($AR6="A",AN6*1.2,IF($AR6="B",AN6*1.1,AN6)) -> 300 | AX6: =IF($AR6="A",AO6*1.2,IF($AR6="B",AO6*1.1,AO6)) -> 70 | AY6: PO / FCST 650 resto del año | AZ6: PO 150 | BA6: =SUMIF(Consenso!$C:$C,$B6,Consenso!AZ:AZ) -> 23211.79 | BB6: =SUMIF(Consenso!$C:$C,$B6,Consenso!BA:BA) -> 115585.24 | BC6: =SUMIF(Consenso!$C:$C,$B6,Consenso!BB:BB) -> 63477.14 | BD6: =SUMIF(Consenso!$C:$C,$B6,Consenso!BC:BC) -> 37896.8 | BE6: =SUMIF(Consenso!$C:$C,$B6,Consenso!BD:BD) -> 142113 | BF6: =SUMIF(Consenso!$C:$C,$B6,Consenso!BE:BE) -> 33159.7
A7: Speck | B7: 144896-9352 | C7: Speck Smartshell Case with Microban for Macbook Pro 14" M1/M2 - Swell Blue | D7: MacBook Pro 14" M1/M2 Cases | E7: Activo | F7: 14 | G7: 0 | H7: =SUMIF(Consenso!$C:$C,$B7,Consenso!AM:AM) -> 28 | I7: =SUMIF(Consenso!$C:$C,$B7,Consenso!AN:AN) -> 60 | J7: =SUMIF(Consenso!$C:$C,$B7,Consenso!AO:AO) -> 30 | K7: =SUMIF(Consenso!$C:$C,$B7,Consenso!AP:AP) -> 30 | L7: =SUMIF(Consenso!$C:$C,$B7,Consenso!AQ:AQ) -> 90 | M7: =SUMIF(Consenso!$C:$C,$B7,Consenso!AR:AR) -> 40 | N7: =IFERROR(VLOOKUP(B:B,Consenso!C:P,14,0),0) -> 27 | O7: =SUMIF('On Orders'!$B:$B,$B7,'On Orders'!E:E) -> 0 | P7: =SUMIF('On Orders'!$B:$B,$B7,'On Orders'!F:F) -> 64 | Q7: =SUMIF('On Orders'!$B:$B,$B7,'On Orders'!G:G) -> 0 | R7: =SUMIF('On Orders'!$B:$B,$B7,'On Orders'!H:H) -> 0 | S7: 0 | T7: 0 | U7: 0 | V7: =(N7+O7+P7)-H7 -> 63 | W7: =(V7+Q7)-I7 -> 3 | X7: =(W7+R7)-J7 -> -27 | Y7: =(X7+S7)-K7 -> -57 | Z7: =(Y7+T7)-L7 -> -147 | AA7: =(Z7+U7)-M7 -> -187 | AB7: =IF(COUNTIF('Master iP17 iP18'!$B:$B,$B7)>0,"18",IF(COUNTIF('Master iP17 iP18'!$E:$E,$B7)>0,"17","NORMAL")) -> NORMAL | AC7: =IF($AB7="18",_xlfn.XLOOKUP($B7,'Master iP17 iP18'!$B:$B,'Master iP17 iP18'!$E:$E),"") | AD7: =IF($AB7="18",V7+IFERROR(_xlfn.XLOOKUP($AC7,$B:$B,V:V),0),V7) -> 63 | AE7: =IF($AB7="18",W7+IFERROR(_xlfn.XLOOKUP($AC7,$B:$B,W:W),0),W7) -> 3 | AF7: =IF($AB7="18",X7+IFERROR(_xlfn.XLOOKUP($AC7,$B:$B,X:X),0),X7) -> -27 | AG7: =IF($AB7="18",Y7+IFERROR(_xlfn.XLOOKUP($AC7,$B:$B,Y:Y),0),Y7) -> -57 | AH7: =IF($AB7="18",Z7+IFERROR(_xlfn.XLOOKUP($AC7,$B:$B,Z:Z),0),Z7) -> -147 | AI7: =IF($AB7="18",AA7+IFERROR(_xlfn.XLOOKUP($AC7,$B:$B,AA:AA),0),AA7) -> -187 | AJ7: =IF($AB7="17",0,MAX(0,-AD7)) -> 0 | AK7: =IF($AB7="17",0,MAX(0,MAX(0,-AE7)-MAX(0,-AD7))) -> 0 | AL7: =IF($AB7="17",0,MAX(0,MAX(0,-AF7)-MAX(0,-AE7))) -> 27 | AM7: =IF($AB7="17",0,MAX(0,MAX(0,-AG7)-MAX(0,-AF7))) -> 30 | AN7: =IF($AB7="17",0,MAX(0,MAX(0,-AH7)-MAX(0,-AG7))) -> 90 | AO7: =IF($AB7="17",0,MAX(0,MAX(0,-AI7)-MAX(0,-AH7))) -> 40 | AP7: PO 50 Med Julio | AR7: =IFERROR(_xlfn.XLOOKUP(B7,#REF!,#REF!),"") | AS7: =IF($AR7="A",AJ7*1.2,IF($AR7="B",AJ7*1.1,AJ7)) -> 0 | AT7: =IF($AR7="A",AK7*1.2,IF($AR7="B",AK7*1.1,AK7)) -> 0 | AU7: =IF($AR7="A",AL7*1.2,IF($AR7="B",AL7*1.1,AL7)) -> 27 | AV7: =IF($AR7="A",AM7*1.2,IF($AR7="B",AM7*1.1,AM7)) -> 30 | AW7: =IF($AR7="A",AN7*1.2,IF($AR7="B",AN7*1.1,AN7)) -> 90 | AX7: =IF($AR7="A",AO7*1.2,IF($AR7="B",AO7*1.1,AO7)) -> 40 | AY7: PO FCST / 200 | BA7: =SUMIF(Consenso!$C:$C,$B7,Consenso!AZ:AZ) -> 12056.8 | BB7: =SUMIF(Consenso!$C:$C,$B7,Consenso!BA:BA) -> 25836 | BC7: =SUMIF(Consenso!$C:$C,$B7,Consenso!BB:BB) -> 12918 | BD7: =SUMIF(Consenso!$C:$C,$B7,Consenso!BC:BC) -> 12918 | BE7: =SUMIF(Consenso!$C:$C,$B7,Consenso!BD:BD) -> 38754 | BF7: =SUMIF(Consenso!$C:$C,$B7,Consenso!BE:BE) -> 17224
A8: Speck | B8: 150225-3085 | C8: Speck Smartshell Case for Macbook Air 13" M2 2022 - Obsidian | D8: MacBook Air 13" M4/M3/M2 | E8: Activo | F8: 14 | G8: 0 | H8: =SUMIF(Consenso!$C:$C,$B8,Consenso!AM:AM) -> 59 | I8: =SUMIF(Consenso!$C:$C,$B8,Consenso!AN:AN) -> 200 | J8: =SUMIF(Consenso!$C:$C,$B8,Consenso!AO:AO) -> 90 | K8: =SUMIF(Consenso!$C:$C,$B8,Consenso!AP:AP) -> 55 | L8: =SUMIF(Consenso!$C:$C,$B8,Consenso!AQ:AQ) -> 200 | M8: =SUMIF(Consenso!$C:$C,$B8,Consenso!AR:AR) -> 90 | N8: =IFERROR(VLOOKUP(B:B,Consenso!C:P,14,0),0) -> 45 | O8: =SUMIF('On Orders'!$B:$B,$B8,'On Orders'!E:E) -> 0 | P8: =SUMIF('On Orders'!$B:$B,$B8,'On Orders'!F:F) -> 240 | Q8: =SUMIF('On Orders'!$B:$B,$B8,'On Orders'!G:G) -> 0 | R8: =SUMIF('On Orders'!$B:$B,$B8,'On Orders'!H:H) -> 0 | S8: 0 | T8: 0 | U8: 0 | V8: =(N8+O8+P8)-H8 -> 226 | W8: =(V8+Q8)-I8 -> 26 | X8: =(W8+R8)-J8 -> -64 | Y8: =(X8+S8)-K8 -> -119 | Z8: =(Y8+T8)-L8 -> -319 | AA8: =(Z8+U8)-M8 -> -409 | AB8: =IF(COUNTIF('Master iP17 iP18'!$B:$B,$B8)>0,"18",IF(COUNTIF('Master iP17 iP18'!$E:$E,$B8)>0,"17","NORMAL")) -> NORMAL | AC8: =IF($AB8="18",_xlfn.XLOOKUP($B8,'Master iP17 iP18'!$B:$B,'Master iP17 iP18'!$E:$E),"") | AD8: =IF($AB8="18",V8+IFERROR(_xlfn.XLOOKUP($AC8,$B:$B,V:V),0),V8) -> 226 | AE8: =IF($AB8="18",W8+IFERROR(_xlfn.XLOOKUP($AC8,$B:$B,W:W),0),W8) -> 26 | AF8: =IF($AB8="18",X8+IFERROR(_xlfn.XLOOKUP($AC8,$B:$B,X:X),0),X8) -> -64 | AG8: =IF($AB8="18",Y8+IFERROR(_xlfn.XLOOKUP($AC8,$B:$B,Y:Y),0),Y8) -> -119 | AH8: =IF($AB8="18",Z8+IFERROR(_xlfn.XLOOKUP($AC8,$B:$B,Z:Z),0),Z8) -> -319 | AI8: =IF($AB8="18",AA8+IFERROR(_xlfn.XLOOKUP($AC8,$B:$B,AA:AA),0),AA8) -> -409 | AJ8: =IF($AB8="17",0,MAX(0,-AD8)) -> 0 | AK8: =IF($AB8="17",0,MAX(0,MAX(0,-AE8)-MAX(0,-AD8))) -> 0 | AL8: =IF($AB8="17",0,MAX(0,MAX(0,-AF8)-MAX(0,-AE8))) -> 64 | AM8: =IF($AB8="17",0,MAX(0,MAX(0,-AG8)-MAX(0,-AF8))) -> 55 | AN8: =IF($AB8="17",0,MAX(0,MAX(0,-AH8)-MAX(0,-AG8))) -> 200 | AO8: =IF($AB8="17",0,MAX(0,MAX(0,-AI8)-MAX(0,-AH8))) -> 90 | AP8: PO 230 Med Julio | AR8: =IFERROR(_xlfn.XLOOKUP(B8,#REF!,#REF!),"") | AS8: =IF($AR8="A",AJ8*1.2,IF($AR8="B",AJ8*1.1,AJ8)) -> 0 | AT8: =IF($AR8="A",AK8*1.2,IF($AR8="B",AK8*1.1,AK8)) -> 0 | AU8: =IF($AR8="A",AL8*1.2,IF($AR8="B",AL8*1.1,AL8)) -> 64 | AV8: =IF($AR8="A",AM8*1.2,IF($AR8="B",AM8*1.1,AM8)) -> 55 | AW8: =IF($AR8="A",AN8*1.2,IF($AR8="B",AN8*1.1,AN8)) -> 200 | AX8: =IF($AR8="A",AO8*1.2,IF($AR8="B",AO8*1.1,AO8)) -> 90 | AY8: PO FCST / 400 | BA8: =SUMIF(Consenso!$C:$C,$B8,Consenso!AZ:AZ) -> 37496.84 | BB8: =SUMIF(Consenso!$C:$C,$B8,Consenso!BA:BA) -> 119371.46 | BC8: =SUMIF(Consenso!$C:$C,$B8,Consenso!BB:BB) -> 68478.79 | BD8: =SUMIF(Consenso!$C:$C,$B8,Consenso!BC:BC) -> 50888.74 | BE8: =SUMIF(Consenso!$C:$C,$B8,Consenso!BD:BD) -> 118867.65 | BF8: =SUMIF(Consenso!$C:$C,$B8,Consenso!BE:BE) -> 74524.51
A9: Speck | B9: 150225-3086 | C9: Speck Smartshell Macbook Air M2/M3 Cozy Pink/Cozy Pink/Swtrgrey | D9: MacBook Air 13" M4/M3/M2 | E9: Activo | F9: 14 | G9: 0 | H9: =SUMIF(Consenso!$C:$C,$B9,Consenso!AM:AM) -> 18 | I9: =SUMIF(Consenso!$C:$C,$B9,Consenso!AN:AN) -> 55 | J9: =SUMIF(Consenso!$C:$C,$B9,Consenso!AO:AO) -> 42 | K9: =SUMIF(Consenso!$C:$C,$B9,Consenso!AP:AP) -> 30 | L9: =SUMIF(Consenso!$C:$C,$B9,Consenso!AQ:AQ) -> 115 | M9: =SUMIF(Consenso!$C:$C,$B9,Consenso!AR:AR) -> 136 | N9: =IFERROR(VLOOKUP(B:B,Consenso!C:P,14,0),0) -> 84 | O9: =SUMIF('On Orders'!$B:$B,$B9,'On Orders'!E:E) -> 0 | P9: =SUMIF('On Orders'!$B:$B,$B9,'On Orders'!F:F) -> 80 | Q9: =SUMIF('On Orders'!$B:$B,$B9,'On Orders'!G:G) -> 0 | R9: =SUMIF('On Orders'!$B:$B,$B9,'On Orders'!H:H) -> 0 | S9: 0 | T9: 0 | U9: 0 | V9: =(N9+O9+P9)-H9 -> 146 | W9: =(V9+Q9)-I9 -> 91 | X9: =(W9+R9)-J9 -> 49 | Y9: =(X9+S9)-K9 -> 19 | Z9: =(Y9+T9)-L9 -> -96 | AA9: =(Z9+U9)-M9 -> -232 | AB9: =IF(COUNTIF('Master iP17 iP18'!$B:$B,$B9)>0,"18",IF(COUNTIF('Master iP17 iP18'!$E:$E,$B9)>0,"17","NORMAL")) -> NORMAL | AC9: =IF($AB9="18",_xlfn.XLOOKUP($B9,'Master iP17 iP18'!$B:$B,'Master iP17 iP18'!$E:$E),"") | AD9: =IF($AB9="18",V9+IFERROR(_xlfn.XLOOKUP($AC9,$B:$B,V:V),0),V9) -> 146 | AE9: =IF($AB9="18",W9+IFERROR(_xlfn.XLOOKUP($AC9,$B:$B,W:W),0),W9) -> 91 | AF9: =IF($AB9="18",X9+IFERROR(_xlfn.XLOOKUP($AC9,$B:$B,X:X),0),X9) -> 49 | AG9: =IF($AB9="18",Y9+IFERROR(_xlfn.XLOOKUP($AC9,$B:$B,Y:Y),0),Y9) -> 19 | AH9: =IF($AB9="18",Z9+IFERROR(_xlfn.XLOOKUP($AC9,$B:$B,Z:Z),0),Z9) -> -96 | AI9: =IF($AB9="18",AA9+IFERROR(_xlfn.XLOOKUP($AC9,$B:$B,AA:AA),0),AA9) -> -232 | AJ9: =IF($AB9="17",0,MAX(0,-AD9)) -> 0 | AK9: =IF($AB9="17",0,MAX(0,MAX(0,-AE9)-MAX(0,-AD9))) -> 0 | AL9: =IF($AB9="17",0,MAX(0,MAX(0,-AF9)-MAX(0,-AE9))) -> 0 | AM9: =IF($AB9="17",0,MAX(0,MAX(0,-AG9)-MAX(0,-AF9))) -> 0 | AN9: =IF($AB9="17",0,MAX(0,MAX(0,-AH9)-MAX(0,-AG9))) -> 96 | AO9: =IF($AB9="17",0,MAX(0,MAX(0,-AI9)-MAX(0,-AH9))) -> 136 | AP9: PO 80 Med Julio | AR9: =IFERROR(_xlfn.XLOOKUP(B9,#REF!,#REF!),"") | AS9: =IF($AR9="A",AJ9*1.2,IF($AR9="B",AJ9*1.1,AJ9)) -> 0 | AT9: =IF($AR9="A",AK9*1.2,IF($AR9="B",AK9*1.1,AK9)) -> 0 | AU9: =IF($AR9="A",AL9*1.2,IF($AR9="B",AL9*1.1,AL9)) -> 0 | AV9: =IF($AR9="A",AM9*1.2,IF($AR9="B",AM9*1.1,AM9)) -> 0 | AW9: =IF($AR9="A",AN9*1.2,IF($AR9="B",AN9*1.1,AN9)) -> 96 | AX9: =IF($AR9="A",AO9*1.2,IF($AR9="B",AO9*1.1,AO9)) -> 136 | AY9: PO FCST / 300 | BA9: =SUMIF(Consenso!$C:$C,$B9,Consenso!AZ:AZ) -> 22789.54 | BB9: =SUMIF(Consenso!$C:$C,$B9,Consenso!BA:BA) -> 73441.27 | BC9: =SUMIF(Consenso!$C:$C,$B9,Consenso!BB:BB) -> 46290.19 | BD9: =SUMIF(Consenso!$C:$C,$B9,Consenso!BC:BC) -> 52928.93 | BE9: =SUMIF(Consenso!$C:$C,$B9,Consenso!BD:BD) -> 73945.08 | BF9: =SUMIF(Consenso!$C:$C,$B9,Consenso!BE:BE) -> 69900.16
A10: Speck | B10: 150225-9992 | C10: Speck Smartshell Macbook Air M2/M3 Clear/Clear/Sweatergrey | D10: MacBook Air 13" M4/M3/M2 | E10: Activo | F10: 14 | G10: 0 | H10: =SUMIF(Consenso!$C:$C,$B10,Consenso!AM:AM) -> 97 | I10: =SUMIF(Consenso!$C:$C,$B10,Consenso!AN:AN) -> 201 | J10: =SUMIF(Consenso!$C:$C,$B10,Consenso!AO:AO) -> 110 | K10: =SUMIF(Consenso!$C:$C,$B10,Consenso!AP:AP) -> 88 | L10: =SUMIF(Consenso!$C:$C,$B10,Consenso!AQ:AQ) -> 334 | M10: =SUMIF(Consenso!$C:$C,$B10,Consenso!AR:AR) -> 266 | N10: =IFERROR(VLOOKUP(B:B,Consenso!C:P,14,0),0) -> 152 | O10: =SUMIF('On Orders'!$B:$B,$B10,'On Orders'!E:E) -> 0 | P10: =SUMIF('On Orders'!$B:$B,$B10,'On Orders'!F:F) -> 50 | Q10: =SUMIF('On Orders'!$B:$B,$B10,'On Orders'!G:G) -> 0 | R10: =SUMIF('On Orders'!$B:$B,$B10,'On Orders'!H:H) -> 0 | S10: 0 | T10: 0 | U10: 0 | V10: =(N10+O10+P10)-H10 -> 105 | W10: =(V10+Q10)-I10 -> -96 | X10: =(W10+R10)-J10 -> -206 | Y10: =(X10+S10)-K10 -> -294 | Z10: =(Y10+T10)-L10 -> -628 | AA10: =(Z10+U10)-M10 -> -894 | AB10: =IF(COUNTIF('Master iP17 iP18'!$B:$B,$B10)>0,"18",IF(COUNTIF('Master iP17 iP18'!$E:$E,$B10)>0,"17","NORMAL")) -> NORMAL | AC10: =IF($AB10="18",_xlfn.XLOOKUP($B10,'Master iP17 iP18'!$B:$B,'Master iP17 iP18'!$E:$E),"") | AD10: =IF($AB10="18",V10+IFERROR(_xlfn.XLOOKUP($AC10,$B:$B,V:V),0),V10) -> 105 | AE10: =IF($AB10="18",W10+IFERROR(_xlfn.XLOOKUP($AC10,$B:$B,W:W),0),W10) -> -96 | AF10: =IF($AB10="18",X10+IFERROR(_xlfn.XLOOKUP($AC10,$B:$B,X:X),0),X10) -> -206 | AG10: =IF($AB10="18",Y10+IFERROR(_xlfn.XLOOKUP($AC10,$B:$B,Y:Y),0),Y10) -> -294 | AH10: =IF($AB10="18",Z10+IFERROR(_xlfn.XLOOKUP($AC10,$B:$B,Z:Z),0),Z10) -> -628 | AI10: =IF($AB10="18",AA10+IFERROR(_xlfn.XLOOKUP($AC10,$B:$B,AA:AA),0),AA10) -> -894 | AJ10: =IF($AB10="17",0,MAX(0,-AD10)) -> 0 | AK10: =IF($AB10="17",0,MAX(0,MAX(0,-AE10)-MAX(0,-AD10))) -> 96 | AL10: =IF($AB10="17",0,MAX(0,MAX(0,-AF10)-MAX(0,-AE10))) -> 110 | AM10: =IF($AB10="17",0,MAX(0,MAX(0,-AG10)-MAX(0,-AF10))) -> 88 | AN10: =IF($AB10="17",0,MAX(0,MAX(0,-AH10)-MAX(0,-AG10))) -> 334 | AO10: =IF($AB10="17",0,MAX(0,MAX(0,-AI10)-MAX(0,-AH10))) -> 266 | AP10: PO 230 Med Julio | AR10: =IFERROR(_xlfn.XLOOKUP(B10,#REF!,#REF!),"") | AS10: =IF($AR10="A",AJ10*1.2,IF($AR10="B",AJ10*1.1,AJ10)) -> 0 | AT10: =IF($AR10="A",AK10*1.2,IF($AR10="B",AK10*1.1,AK10)) -> 96 | AU10: =IF($AR10="A",AL10*1.2,IF($AR10="B",AL10*1.1,AL10)) -> 110 | AV10: =IF($AR10="A",AM10*1.2,IF($AR10="B",AM10*1.1,AM10)) -> 88 | AW10: =IF($AR10="A",AN10*1.2,IF($AR10="B",AN10*1.1,AN10)) -> 334 | AX10: =IF($AR10="A",AO10*1.2,IF($AR10="B",AO10*1.1,AO10)) -> 266 | AY10: 50 Air - 190 Barco NAPs - FCST / PO 1,000 resto del año | AZ10: PO 200 NAPs - Pendiente por confirmar desde Jul | BA10: =SUMIF(Consenso!$C:$C,$B10,Consenso!AZ:AZ) -> 78546.33 | BB10: =SUMIF(Consenso!$C:$C,$B10,Consenso!BA:BA) -> 153053.52 | BC10: =SUMIF(Consenso!$C:$C,$B10,Consenso!BB:BB) -> 103792.72 | BD10: =SUMIF(Consenso!$C:$C,$B10,Consenso!BC:BC) -> 77452.91 | BE10: =SUMIF(Consenso!$C:$C,$B10,Consenso!BD:BD) -> 153557.33 | BF10: =SUMIF(Consenso!$C:$C,$B10,Consenso!BE:BE) -> 125228.26
A11: Speck | B11: 150950-3260 | C11: Speck Stylefolio iPad 11" (2022-2025) Deep Sea Pull Up/Parchment/Early Grey | D11: iPad 10th /11th - 10.9"/11" (2022-2025) | E11: Activo | F11: 14 | G11: 0 | H11: =SUMIF(Consenso!$C:$C,$B11,Consenso!AM:AM) -> 0 | I11: =SUMIF(Consenso!$C:$C,$B11,Consenso!AN:AN) -> 0 | J11: =SUMIF(Consenso!$C:$C,$B11,Consenso!AO:AO) -> 0 | K11: =SUMIF(Consenso!$C:$C,$B11,Consenso!AP:AP) -> 0 | L11: =SUMIF(Consenso!$C:$C,$B11,Consenso!AQ:AQ) -> 40 | M11: =SUMIF(Consenso!$C:$C,$B11,Consenso!AR:AR) -> 62 | N11: =IFERROR(VLOOKUP(B:B,Consenso!C:P,14,0),0) -> 85 | O11: =SUMIF('On Orders'!$B:$B,$B11,'On Orders'!E:E) -> 0 | P11: =SUMIF('On Orders'!$B:$B,$B11,'On Orders'!F:F) -> 0 | Q11: =SUMIF('On Orders'!$B:$B,$B11,'On Orders'!G:G) -> 0 | R11: =SUMIF('On Orders'!$B:$B,$B11,'On Orders'!H:H) -> 0 | S11: 0 | T11: 0 | U11: 0 | V11: =(N11+O11+P11)-H11 -> 85 | W11: =(V11+Q11)-I11 -> 85 | X11: =(W11+R11)-J11 -> 85 | Y11: =(X11+S11)-K11 -> 85 | Z11: =(Y11+T11)-L11 -> 45 | AA11: =(Z11+U11)-M11 -> -17 | AB11: =IF(COUNTIF('Master iP17 iP18'!$B:$B,$B11)>0,"18",IF(COUNTIF('Master iP17 iP18'!$E:$E,$B11)>0,"17","NORMAL")) -> NORMAL | AC11: =IF($AB11="18",_xlfn.XLOOKUP($B11,'Master iP17 iP18'!$B:$B,'Master iP17 iP18'!$E:$E),"") | AD11: =IF($AB11="18",V11+IFERROR(_xlfn.XLOOKUP($AC11,$B:$B,V:V),0),V11) -> 85 | AE11: =IF($AB11="18",W11+IFERROR(_xlfn.XLOOKUP($AC11,$B:$B,W:W),0),W11) -> 85 | AF11: =IF($AB11="18",X11+IFERROR(_xlfn.XLOOKUP($AC11,$B:$B,X:X),0),X11) -> 85 | AG11: =IF($AB11="18",Y11+IFERROR(_xlfn.XLOOKUP($AC11,$B:$B,Y:Y),0),Y11) -> 85 | AH11: =IF($AB11="18",Z11+IFERROR(_xlfn.XLOOKUP($AC11,$B:$B,Z:Z),0),Z11) -> 45 | AI11: =IF($AB11="18",AA11+IFERROR(_xlfn.XLOOKUP($AC11,$B:$B,AA:AA),0),AA11) -> -17 | AJ11: =IF($AB11="17",0,MAX(0,-AD11)) -> 0 | AK11: =IF($AB11="17",0,MAX(0,MAX(0,-AE11)-MAX(0,-AD11))) -> 0 | AL11: =IF($AB11="17",0,MAX(0,MAX(0,-AF11)-MAX(0,-AE11))) -> 0 | AM11: =IF($AB11="17",0,MAX(0,MAX(0,-AG11)-MAX(0,-AF11))) -> 0 | AN11: =IF($AB11="17",0,MAX(0,MAX(0,-AH11)-MAX(0,-AG11))) -> 0 | AO11: =IF($AB11="17",0,MAX(0,MAX(0,-AI11)-MAX(0,-AH11))) -> 17 | AR11: =IFERROR(_xlfn.XLOOKUP(B11,#REF!,#REF!),"") | AS11: =IF($AR11="A",AJ11*1.2,IF($AR11="B",AJ11*1.1,AJ11)) -> 0 | AT11: =IF($AR11="A",AK11*1.2,IF($AR11="B",AK11*1.1,AK11)) -> 0 | AU11: =IF($AR11="A",AL11*1.2,IF($AR11="B",AL11*1.1,AL11)) -> 0 | AV11: =IF($AR11="A",AM11*1.2,IF($AR11="B",AM11*1.1,AM11)) -> 0 | AW11: =IF($AR11="A",AN11*1.2,IF($AR11="B",AN11*1.1,AN11)) -> 0 | AX11: =IF($AR11="A",AO11*1.2,IF($AR11="B",AO11*1.1,AO11)) -> 17 | BA11: =SUMIF(Consenso!$C:$C,$B11,Consenso!AZ:AZ) -> 19144.78 | BB11: =SUMIF(Consenso!$C:$C,$B11,Consenso!BA:BA) -> 26701.93 | BC11: =SUMIF(Consenso!$C:$C,$B11,Consenso!BB:BB) -> 23679.07 | BD11: =SUMIF(Consenso!$C:$C,$B11,Consenso!BC:BC) -> 23679.07 | BE11: =SUMIF(Consenso!$C:$C,$B11,Consenso!BD:BD) -> 28717.17 | BF11: =SUMIF(Consenso!$C:$C,$B11,Consenso!BE:BE) -> 31236.22
A12: Speck | B12: 150989-3264 | C12: Speck Balance Folio iPad 11" (2022-2025) Ibis Pink/Deep Malachite/Jelly Mint | D12: iPad 10th /11th - 10.9"/11" (2022-2025) | E12: Activo | F12: 14 | G12: 0 | H12: =SUMIF(Consenso!$C:$C,$B12,Consenso!AM:AM) -> 0 | I12: =SUMIF(Consenso!$C:$C,$B12,Consenso!AN:AN) -> 0 | J12: =SUMIF(Consenso!$C:$C,$B12,Consenso!AO:AO) -> 0 | K12: =SUMIF(Consenso!$C:$C,$B12,Consenso!AP:AP) -> 0 | L12: =SUMIF(Consenso!$C:$C,$B12,Consenso!AQ:AQ) -> 0 | M12: =SUMIF(Consenso!$C:$C,$B12,Consenso!AR:AR) -> 3 | N12: =IFERROR(VLOOKUP(B:B,Consenso!C:P,14,0),0) -> 332 | O12: =SUMIF('On Orders'!$B:$B,$B12,'On Orders'!E:E) -> 0 | P12: =SUMIF('On Orders'!$B:$B,$B12,'On Orders'!F:F) -> 0 | Q12: =SUMIF('On Orders'!$B:$B,$B12,'On Orders'!G:G) -> 0 | R12: =SUMIF('On Orders'!$B:$B,$B12,'On Orders'!H:H) -> 0 | S12: 0 | T12: 0 | U12: 0 | V12: =(N12+O12+P12)-H12 -> 332 | W12: =(V12+Q12)-I12 -> 332 | X12: =(W12+R12)-J12 -> 332 | Y12: =(X12+S12)-K12 -> 332 | Z12: =(Y12+T12)-L12 -> 332 | AA12: =(Z12+U12)-M12 -> 329 | AB12: =IF(COUNTIF('Master iP17 iP18'!$B:$B,$B12)>0,"18",IF(COUNTIF('Master iP17 iP18'!$E:$E,$B12)>0,"17","NORMAL")) -> NORMAL | AC12: =IF($AB12="18",_xlfn.XLOOKUP($B12,'Master iP17 iP18'!$B:$B,'Master iP17 iP18'!$E:$E),"") | AD12: =IF($AB12="18",V12+IFERROR(_xlfn.XLOOKUP($AC12,$B:$B,V:V),0),V12) -> 332 | AE12: =IF($AB12="18",W12+IFERROR(_xlfn.XLOOKUP($AC12,$B:$B,W:W),0),W12) -> 332 | AF12: =IF($AB12="18",X12+IFERROR(_xlfn.XLOOKUP($AC12,$B:$B,X:X),0),X12) -> 332 | AG12: =IF($AB12="18",Y12+IFERROR(_xlfn.XLOOKUP($AC12,$B:$B,Y:Y),0),Y12) -> 332 | AH12: =IF($AB12="18",Z12+IFERROR(_xlfn.XLOOKUP($AC12,$B:$B,Z:Z),0),Z12) -> 332 | AI12: =IF($AB12="18",AA12+IFERROR(_xlfn.XLOOKUP($AC12,$B:$B,AA:AA),0),AA12) -> 329 | AJ12: =IF($AB12="17",0,MAX(0,-AD12)) -> 0 | AK12: =IF($AB12="17",0,MAX(0,MAX(0,-AE12)-MAX(0,-AD12))) -> 0 | AL12: =IF($AB12="17",0,MAX(0,MAX(0,-AF12)-MAX(0,-AE12))) -> 0 | AM12: =IF($AB12="17",0,MAX(0,MAX(0,-AG12)-MAX(0,-AF12))) -> 0 | AN12: =IF($AB12="17",0,MAX(0,MAX(0,-AH12)-MAX(0,-AG12))) -> 0 | AO12: =IF($AB12="17",0,MAX(0,MAX(0,-AI12)-MAX(0,-AH12))) -> 0 | AR12: =IFERROR(_xlfn.XLOOKUP(B12,#REF!,#REF!),"") | AS12: =IF($AR12="A",AJ12*1.2,IF($AR12="B",AJ12*1.1,AJ12)) -> 0 | AT12: =IF($AR12="A",AK12*1.2,IF($AR12="B",AK12*1.1,AK12)) -> 0 | AU12: =IF($AR12="A",AL12*1.2,IF($AR12="B",AL12*1.1,AL12)) -> 0 | AV12: =IF($AR12="A",AM12*1.2,IF($AR12="B",AM12*1.1,AM12)) -> 0 | AW12: =IF($AR12="A",AN12*1.2,IF($AR12="B",AN12*1.1,AN12)) -> 0 | AX12: =IF($AR12="A",AO12*1.2,IF($AR12="B",AO12*1.1,AO12)) -> 0 | BA12: =SUMIF(Consenso!$C:$C,$B12,Consenso!AZ:AZ) -> 26198.12 | BB12: =SUMIF(Consenso!$C:$C,$B12,Consenso!BA:BA) -> 36274.32 | BC12: =SUMIF(Consenso!$C:$C,$B12,Consenso!BB:BB) -> 30228.6 | BD12: =SUMIF(Consenso!$C:$C,$B12,Consenso!BC:BC) -> 31236.22 | BE12: =SUMIF(Consenso!$C:$C,$B12,Consenso!BD:BD) -> 37785.75 | BF12: =SUMIF(Consenso!$C:$C,$B12,Consenso!BE:BE) -> 41312.42
A13: Speck | B13: 150989-3266 | C13: Speck Balance Folio iPad 11" (2022-2025) Sable/Blue Granite/Black | D13: iPad 10th /11th - 10.9"/11" (2022-2025) | E13: Activo | F13: 14 | G13: 0 | H13: =SUMIF(Consenso!$C:$C,$B13,Consenso!AM:AM) -> 0 | I13: =SUMIF(Consenso!$C:$C,$B13,Consenso!AN:AN) -> 0 | J13: =SUMIF(Consenso!$C:$C,$B13,Consenso!AO:AO) -> 0 | K13: =SUMIF(Consenso!$C:$C,$B13,Consenso!AP:AP) -> 0 | L13: =SUMIF(Consenso!$C:$C,$B13,Consenso!AQ:AQ) -> 0 | M13: =SUMIF(Consenso!$C:$C,$B13,Consenso!AR:AR) -> 0 | N13: =IFERROR(VLOOKUP(B:B,Consenso!C:P,14,0),0) -> 264 | O13: =SUMIF('On Orders'!$B:$B,$B13,'On Orders'!E:E) -> 0 | P13: =SUMIF('On Orders'!$B:$B,$B13,'On Orders'!F:F) -> 0 | Q13: =SUMIF('On Orders'!$B:$B,$B13,'On Orders'!G:G) -> 0 | R13: =SUMIF('On Orders'!$B:$B,$B13,'On Orders'!H:H) -> 0 | S13: 0 | T13: 0 | U13: 0 | V13: =(N13+O13+P13)-H13 -> 264 | W13: =(V13+Q13)-I13 -> 264 | X13: =(W13+R13)-J13 -> 264 | Y13: =(X13+S13)-K13 -> 264 | Z13: =(Y13+T13)-L13 -> 264 | AA13: =(Z13+U13)-M13 -> 264 | AB13: =IF(COUNTIF('Master iP17 iP18'!$B:$B,$B13)>0,"18",IF(COUNTIF('Master iP17 iP18'!$E:$E,$B13)>0,"17","NORMAL")) -> NORMAL | AC13: =IF($AB13="18",_xlfn.XLOOKUP($B13,'Master iP17 iP18'!$B:$B,'Master iP17 iP18'!$E:$E),"") | AD13: =IF($AB13="18",V13+IFERROR(_xlfn.XLOOKUP($AC13,$B:$B,V:V),0),V13) -> 264 | AE13: =IF($AB13="18",W13+IFERROR(_xlfn.XLOOKUP($AC13,$B:$B,W:W),0),W13) -> 264 | AF13: =IF($AB13="18",X13+IFERROR(_xlfn.XLOOKUP($AC13,$B:$B,X:X),0),X13) -> 264 | AG13: =IF($AB13="18",Y13+IFERROR(_xlfn.XLOOKUP($AC13,$B:$B,Y:Y),0),Y13) -> 264 | AH13: =IF($AB13="18",Z13+IFERROR(_xlfn.XLOOKUP($AC13,$B:$B,Z:Z),0),Z13) -> 264 | AI13: =IF($AB13="18",AA13+IFERROR(_xlfn.XLOOKUP($AC13,$B:$B,AA:AA),0),AA13) -> 264 | AJ13: =IF($AB13="17",0,MAX(0,-AD13)) -> 0 | AK13: =IF($AB13="17",0,MAX(0,MAX(0,-AE13)-MAX(0,-AD13))) -> 0 | AL13: =IF($AB13="17",0,MAX(0,MAX(0,-AF13)-MAX(0,-AE13))) -> 0 | AM13: =IF($AB13="17",0,MAX(0,MAX(0,-AG13)-MAX(0,-AF13))) -> 0 | AN13: =IF($AB13="17",0,MAX(0,MAX(0,-AH13)-MAX(0,-AG13))) -> 0 | AO13: =IF($AB13="17",0,MAX(0,MAX(0,-AI13)-MAX(0,-AH13))) -> 0 | AR13: =IFERROR(_xlfn.XLOOKUP(B13,#REF!,#REF!),"") | AS13: =IF($AR13="A",AJ13*1.2,IF($AR13="B",AJ13*1.1,AJ13)) -> 0 | AT13: =IF($AR13="A",AK13*1.2,IF($AR13="B",AK13*1.1,AK13)) -> 0 | AU13: =IF($AR13="A",AL13*1.2,IF($AR13="B",AL13*1.1,AL13)) -> 0 | AV13: =IF($AR13="A",AM13*1.2,IF($AR13="B",AM13*1.1,AM13)) -> 0 | AW13: =IF($AR13="A",AN13*1.2,IF($AR13="B",AN13*1.1,AN13)) -> 0 | AX13: =IF($AR13="A",AO13*1.2,IF($AR13="B",AO13*1.1,AO13)) -> 0 | BA13: =SUMIF(Consenso!$C:$C,$B13,Consenso!AZ:AZ) -> 8060.96 | BB13: =SUMIF(Consenso!$C:$C,$B13,Consenso!BA:BA) -> 24182.88 | BC13: =SUMIF(Consenso!$C:$C,$B13,Consenso!BB:BB) -> 1511.43 | BD13: =SUMIF(Consenso!$C:$C,$B13,Consenso!BC:BC) -> 0 | BE13: =SUMIF(Consenso!$C:$C,$B13,Consenso!BD:BD) -> 0 | BF13: =SUMIF(Consenso!$C:$C,$B13,Consenso!BE:BE) -> 0
A14: Speck | B14: 150422-1041 | C14: Speck Car Vent Mount for MagSafe Black iPhone 15 Car | D14: Car Vent | E14: Descontinuado | F14: 11.99 | G14: 0 | H14: =SUMIF(Consenso!$C:$C,$B14,Consenso!AM:AM) -> 0 | I14: =SUMIF(Consenso!$C:$C,$B14,Consenso!AN:AN) -> 0 | J14: =SUMIF(Consenso!$C:$C,$B14,Consenso!AO:AO) -> 0 | K14: =SUMIF(Consenso!$C:$C,$B14,Consenso!AP:AP) -> 0 | L14: =SUMIF(Consenso!$C:$C,$B14,Consenso!AQ:AQ) -> 0 | M14: =SUMIF(Consenso!$C:$C,$B14,Consenso!AR:AR) -> 0 | N14: =IFERROR(VLOOKUP(B:B,Consenso!C:P,14,0),0) -> 0 | O14: =SUMIF('On Orders'!$B:$B,$B14,'On Orders'!E:E) -> 0 | P14: =SUMIF('On Orders'!$B:$B,$B14,'On Orders'!F:F) -> 0 | Q14: =SUMIF('On Orders'!$B:$B,$B14,'On Orders'!G:G) -> 0 | R14: =SUMIF('On Orders'!$B:$B,$B14,'On Orders'!H:H) -> 0 | S14: 0 | T14: 0 | U14: 0 | V14: =(N14+O14+P14)-H14 -> 0 | W14: =(V14+Q14)-I14 -> 0 | X14: =(W14+R14)-J14 -> 0 | Y14: =(X14+S14)-K14 -> 0 | Z14: =(Y14+T14)-L14 -> 0 | AA14: =(Z14+U14)-M14 -> 0 | AB14: =IF(COUNTIF('Master iP17 iP18'!$B:$B,$B14)>0,"18",IF(COUNTIF('Master iP17 iP18'!$E:$E,$B14)>0,"17","NORMAL")) -> NORMAL | AC14: =IF($AB14="18",_xlfn.XLOOKUP($B14,'Master iP17 iP18'!$B:$B,'Master iP17 iP18'!$E:$E),"") | AD14: =IF($AB14="18",V14+IFERROR(_xlfn.XLOOKUP($AC14,$B:$B,V:V),0),V14) -> 0 | AE14: =IF($AB14="18",W14+IFERROR(_xlfn.XLOOKUP($AC14,$B:$B,W:W),0),W14) -> 0 | AF14: =IF($AB14="18",X14+IFERROR(_xlfn.XLOOKUP($AC14,$B:$B,X:X),0),X14) -> 0 | AG14: =IF($AB14="18",Y14+IFERROR(_xlfn.XLOOKUP($AC14,$B:$B,Y:Y),0),Y14) -> 0 | AH14: =IF($AB14="18",Z14+IFERROR(_xlfn.XLOOKUP($AC14,$B:$B,Z:Z),0),Z14) -> 0 | AI14: =IF($AB14="18",AA14+IFERROR(_xlfn.XLOOKUP($AC14,$B:$B,AA:AA),0),AA14) -> 0 | AJ14: =IF($AB14="17",0,MAX(0,-AD14)) -> 0 | AK14: =IF($AB14="17",0,MAX(0,MAX(0,-AE14)-MAX(0,-AD14))) -> 0 | AL14: =IF($AB14="17",0,MAX(0,MAX(0,-AF14)-MAX(0,-AE14))) -> 0 | AM14: =IF($AB14="17",0,MAX(0,MAX(0,-AG14)-MAX(0,-AF14))) -> 0 | AN14: =IF($AB14="17",0,MAX(0,MAX(0,-AH14)-MAX(0,-AG14))) -> 0 | AO14: =IF($AB14="17",0,MAX(0,MAX(0,-AI14)-MAX(0,-AH14))) -> 0 | AR14: =IFERROR(_xlfn.XLOOKUP(B14,#REF!,#REF!),"") | AS14: =IF($AR14="A",AJ14*1.2,IF($AR14="B",AJ14*1.1,AJ14)) -> 0 | AT14: =IF($AR14="A",AK14*1.2,IF($AR14="B",AK14*1.1,AK14)) -> 0 | AU14: =IF($AR14="A",AL14*1.2,IF($AR14="B",AL14*1.1,AL14)) -> 0 | AV14: =IF($AR14="A",AM14*1.2,IF($AR14="B",AM14*1.1,AM14)) -> 0 | AW14: =IF($AR14="A",AN14*1.2,IF($AR14="B",AN14*1.1,AN14)) -> 0 | AX14: =IF($AR14="A",AO14*1.2,IF($AR14="B",AO14*1.1,AO14)) -> 0 | BA14: =SUMIF(Consenso!$C:$C,$B14,Consenso!AZ:AZ) -> 4053.5 | BB14: =SUMIF(Consenso!$C:$C,$B14,Consenso!BA:BA) -> 7738.5 | BC14: =SUMIF(Consenso!$C:$C,$B14,Consenso!BB:BB) -> 7370 | BD14: =SUMIF(Consenso!$C:$C,$B14,Consenso!BC:BC) -> 7738.5 | BE14: =SUMIF(Consenso!$C:$C,$B14,Consenso!BD:BD) -> 9212.5 | BF14: =SUMIF(Consenso!$C:$C,$B14,Consenso!BE:BE) -> 9949.5
A15: Speck | B15: 150423-1041 | C15: Speck Wallet for MagSafe® Black iPhone 15 Wallet | D15: Wallet | E15: Activo | F15: 7.99 | G15: 0 | H15: =SUMIF(Consenso!$C:$C,$B15,Consenso!AM:AM) -> 30 | I15: =SUMIF(Consenso!$C:$C,$B15,Consenso!AN:AN) -> 27 | J15: =SUMIF(Consenso!$C:$C,$B15,Consenso!AO:AO) -> 38 | K15: =SUMIF(Consenso!$C:$C,$B15,Consenso!AP:AP) -> 10 | L15: =SUMIF(Consenso!$C:$C,$B15,Consenso!AQ:AQ) -> 40 | M15: =SUMIF(Consenso!$C:$C,$B15,Consenso!AR:AR) -> 38 | N15: =IFERROR(VLOOKUP(B:B,Consenso!C:P,14,0),0) -> 3 | O15: =SUMIF('On Orders'!$B:$B,$B15,'On Orders'!E:E) -> 0 | P15: =SUMIF('On Orders'!$B:$B,$B15,'On Orders'!F:F) -> 72 | Q15: =SUMIF('On Orders'!$B:$B,$B15,'On Orders'!G:G) -> 0 | R15: =SUMIF('On Orders'!$B:$B,$B15,'On Orders'!H:H) -> 0 | S15: 0 | T15: 0 | U15: 0 | V15: =(N15+O15+P15)-H15 -> 45 | W15: =(V15+Q15)-I15 -> 18 | X15: =(W15+R15)-J15 -> -20 | Y15: =(X15+S15)-K15 -> -30 | Z15: =(Y15+T15)-L15 -> -70 | AA15: =(Z15+U15)-M15 -> -108 | AB15: =IF(COUNTIF('Master iP17 iP18'!$B:$B,$B15)>0,"18",IF(COUNTIF('Master iP17 iP18'!$E:$E,$B15)>0,"17","NORMAL")) -> NORMAL | AC15: =IF($AB15="18",_xlfn.XLOOKUP($B15,'Master iP17 iP18'!$B:$B,'Master iP17 iP18'!$E:$E),"") | AD15: =IF($AB15="18",V15+IFERROR(_xlfn.XLOOKUP($AC15,$B:$B,V:V),0),V15) -> 45 | AE15: =IF($AB15="18",W15+IFERROR(_xlfn.XLOOKUP($AC15,$B:$B,W:W),0),W15) -> 18 | AF15: =IF($AB15="18",X15+IFERROR(_xlfn.XLOOKUP($AC15,$B:$B,X:X),0),X15) -> -20 | AG15: =IF($AB15="18",Y15+IFERROR(_xlfn.XLOOKUP($AC15,$B:$B,Y:Y),0),Y15) -> -30 | AH15: =IF($AB15="18",Z15+IFERROR(_xlfn.XLOOKUP($AC15,$B:$B,Z:Z),0),Z15) -> -70 | AI15: =IF($AB15="18",AA15+IFERROR(_xlfn.XLOOKUP($AC15,$B:$B,AA:AA),0),AA15) -> -108 | AJ15: =IF($AB15="17",0,MAX(0,-AD15)) -> 0 | AK15: =IF($AB15="17",0,MAX(0,MAX(0,-AE15)-MAX(0,-AD15))) -> 0 | AL15: =IF($AB15="17",0,MAX(0,MAX(0,-AF15)-MAX(0,-AE15))) -> 20 | AM15: =IF($AB15="17",0,MAX(0,MAX(0,-AG15)-MAX(0,-AF15))) -> 10 | AN15: =IF($AB15="17",0,MAX(0,MAX(0,-AH15)-MAX(0,-AG15))) -> 40 | AO15: =IF($AB15="17",0,MAX(0,MAX(0,-AI15)-MAX(0,-AH15))) -> 38 | AP15: PO 50 Med Julio | AR15: =IFERROR(_xlfn.XLOOKUP(B15,#REF!,#REF!),"") | AS15: =IF($AR15="A",AJ15*1.2,IF($AR15="B",AJ15*1.1,AJ15)) -> 0 | AT15: =IF($AR15="A",AK15*1.2,IF($AR15="B",AK15*1.1,AK15)) -> 0 | AU15: =IF($AR15="A",AL15*1.2,IF($AR15="B",AL15*1.1,AL15)) -> 20 | AV15: =IF($AR15="A",AM15*1.2,IF($AR15="B",AM15*1.1,AM15)) -> 10 | AW15: =IF($AR15="A",AN15*1.2,IF($AR15="B",AN15*1.1,AN15)) -> 40 | AX15: =IF($AR15="A",AO15*1.2,IF($AR15="B",AO15*1.1,AO15)) -> 38 | AZ15: 20 - NAPs | BA15: =SUMIF(Consenso!$C:$C,$B15,Consenso!AZ:AZ) -> 12822.15 | BB15: =SUMIF(Consenso!$C:$C,$B15,Consenso!BA:BA) -> 11824.14 | BC15: =SUMIF(Consenso!$C:$C,$B15,Consenso!BB:BB) -> 12910.75 | BD15: =SUMIF(Consenso!$C:$C,$B15,Consenso!BC:BC) -> 8334.13 | BE15: =SUMIF(Consenso!$C:$C,$B15,Consenso!BD:BD) -> 16075.34 | BF15: =SUMIF(Consenso!$C:$C,$B15,Consenso!BE:BE) -> 16690.54
A16: Speck | B16: 150439-3205 | C16: Speck Presidio®2 Grip Magsafe® Clicklock™ Black / Slate Grey iPhone 15 | D16: iPhone 16e / 15 / 14 / 13 | E16: Activo2 | F16: 13 | G16: 0 | H16: =SUMIF(Consenso!$C:$C,$B16,Consenso!AM:AM) -> 83 | I16: =SUMIF(Consenso!$C:$C,$B16,Consenso!AN:AN) -> 40 | J16: =SUMIF(Consenso!$C:$C,$B16,Consenso!AO:AO) -> 20 | K16: =SUMIF(Consenso!$C:$C,$B16,Consenso!AP:AP) -> 80 | L16: =SUMIF(Consenso!$C:$C,$B16,Consenso!AQ:AQ) -> 50 | M16: =SUMIF(Consenso!$C:$C,$B16,Consenso!AR:AR) -> 20 | N16: =IFERROR(VLOOKUP(B:B,Consenso!C:P,14,0),0) -> 0 | O16: =SUMIF('On Orders'!$B:$B,$B16,'On Orders'!E:E) -> 0 | P16: =SUMIF('On Orders'!$B:$B,$B16,'On Orders'!F:F) -> 0 | Q16: =SUMIF('On Orders'!$B:$B,$B16,'On Orders'!G:G) -> 0 | R16: =SUMIF('On Orders'!$B:$B,$B16,'On Orders'!H:H) -> 0 | S16: 0 | T16: 0 | U16: 0 | V16: =(N16+O16+P16)-H16 -> -83 | W16: =(V16+Q16)-I16 -> -123 | X16: =(W16+R16)-J16 -> -143 | Y16: =(X16+S16)-K16 -> -223 | Z16: =(Y16+T16)-L16 -> -273 | AA16: =(Z16+U16)-M16 -> -293 | AB16: =IF(COUNTIF('Master iP17 iP18'!$B:$B,$B16)>0,"18",IF(COUNTIF('Master iP17 iP18'!$E:$E,$B16)>0,"17","NORMAL")) -> NORMAL | AC16: =IF($AB16="18",_xlfn.XLOOKUP($B16,'Master iP17 iP18'!$B:$B,'Master iP17 iP18'!$E:$E),"") | AD16: =IF($AB16="18",V16+IFERROR(_xlfn.XLOOKUP($AC16,$B:$B,V:V),0),V16) -> -83 | AE16: =IF($AB16="18",W16+IFERROR(_xlfn.XLOOKUP($AC16,$B:$B,W:W),0),W16) -> -123 | AF16: =IF($AB16="18",X16+IFERROR(_xlfn.XLOOKUP($AC16,$B:$B,X:X),0),X16) -> -143 | AG16: =IF($AB16="18",Y16+IFERROR(_xlfn.XLOOKUP($AC16,$B:$B,Y:Y),0),Y16) -> -223 | AH16: =IF($AB16="18",Z16+IFERROR(_xlfn.XLOOKUP($AC16,$B:$B,Z:Z),0),Z16) -> -273 | AI16: =IF($AB16="18",AA16+IFERROR(_xlfn.XLOOKUP($AC16,$B:$B,AA:AA),0),AA16) -> -293 | AJ16: =IF($AB16="17",0,MAX(0,-AD16)) -> 83 | AK16: =IF($AB16="17",0,MAX(0,MAX(0,-AE16)-MAX(0,-AD16))) -> 40 | AL16: =IF($AB16="17",0,MAX(0,MAX(0,-AF16)-MAX(0,-AE16))) -> 20 | AM16: =IF($AB16="17",0,MAX(0,MAX(0,-AG16)-MAX(0,-AF16))) -> 80 | AN16: =IF($AB16="17",0,MAX(0,MAX(0,-AH16)-MAX(0,-AG16))) -> 50 | AO16: =IF($AB16="17",0,MAX(0,MAX(0,-AI16)-MAX(0,-AH16))) -> 20 | AR16: =IFERROR(_xlfn.XLOOKUP(B16,#REF!,#REF!),"") | AS16: =IF($AR16="A",AJ16*1.2,IF($AR16="B",AJ16*1.1,AJ16)) -> 83 | AT16: =IF($AR16="A",AK16*1.2,IF($AR16="B",AK16*1.1,AK16)) -> 40 | AU16: =IF($AR16="A",AL16*1.2,IF($AR16="B",AL16*1.1,AL16)) -> 20 | AV16: =IF($AR16="A",AM16*1.2,IF($AR16="B",AM16*1.1,AM16)) -> 80 | AW16: =IF($AR16="A",AN16*1.2,IF($AR16="B",AN16*1.1,AN16)) -> 50 | AX16: =IF($AR16="A",AO16*1.2,IF($AR16="B",AO16*1.1,AO16)) -> 20 | BA16: =SUMIF(Consenso!$C:$C,$B16,Consenso!AZ:AZ) -> 32165.82 | BB16: =SUMIF(Consenso!$C:$C,$B16,Consenso!BA:BA) -> 15501.6 | BC16: =SUMIF(Consenso!$C:$C,$B16,Consenso!BB:BB) -> 7750.8 | BD16: =SUMIF(Consenso!$C:$C,$B16,Consenso!BC:BC) -> 31003.2 | BE16: =SUMIF(Consenso!$C:$C,$B16,Consenso!BD:BD) -> 19377 | BF16: =SUMIF(Consenso!$C:$C,$B16,Consenso!BE:BE) -> 7750.8
A17: Speck | B17: 150443-3199 | C17: Speck Presidio® Perfect-Clear Grip Magsafe® Clicklock™ Clear/Clear/Chrome iPhone 15 | D17: iPhone 16e / 15 / 14 / 13 | E17: Descontinuado | F17: 13 | G17: 0 | H17: =SUMIF(Consenso!$C:$C,$B17,Consenso!AM:AM) -> 0 | I17: =SUMIF(Consenso!$C:$C,$B17,Consenso!AN:AN) -> 0 | J17: =SUMIF(Consenso!$C:$C,$B17,Consenso!AO:AO) -> 0 | K17: =SUMIF(Consenso!$C:$C,$B17,Consenso!AP:AP) -> 0 | L17: =SUMIF(Consenso!$C:$C,$B17,Consenso!AQ:AQ) -> 0 | M17: =SUMIF(Consenso!$C:$C,$B17,Consenso!AR:AR) -> 0 | N17: =IFERROR(VLOOKUP(B:B,Consenso!C:P,14,0),0) -> 0 | O17: =SUMIF('On Orders'!$B:$B,$B17,'On Orders'!E:E) -> 0 | P17: =SUMIF('On Orders'!$B:$B,$B17,'On Orders'!F:F) -> 0 | Q17: =SUMIF('On Orders'!$B:$B,$B17,'On Orders'!G:G) -> 0 | R17: =SUMIF('On Orders'!$B:$B,$B17,'On Orders'!H:H) -> 0 | S17: 0 | T17: 0 | U17: 0 | V17: =(N17+O17+P17)-H17 -> 0 | W17: =(V17+Q17)-I17 -> 0 | X17: =(W17+R17)-J17 -> 0 | Y17: =(X17+S17)-K17 -> 0 | Z17: =(Y17+T17)-L17 -> 0 | AA17: =(Z17+U17)-M17 -> 0 | AB17: =IF(COUNTIF('Master iP17 iP18'!$B:$B,$B17)>0,"18",IF(COUNTIF('Master iP17 iP18'!$E:$E,$B17)>0,"17","NORMAL")) -> NORMAL | AC17: =IF($AB17="18",_xlfn.XLOOKUP($B17,'Master iP17 iP18'!$B:$B,'Master iP17 iP18'!$E:$E),"") | AD17: =IF($AB17="18",V17+IFERROR(_xlfn.XLOOKUP($AC17,$B:$B,V:V),0),V17) -> 0 | AE17: =IF($AB17="18",W17+IFERROR(_xlfn.XLOOKUP($AC17,$B:$B,W:W),0),W17) -> 0 | AF17: =IF($AB17="18",X17+IFERROR(_xlfn.XLOOKUP($AC17,$B:$B,X:X),0),X17) -> 0 | AG17: =IF($AB17="18",Y17+IFERROR(_xlfn.XLOOKUP($AC17,$B:$B,Y:Y),0),Y17) -> 0 | AH17: =IF($AB17="18",Z17+IFERROR(_xlfn.XLOOKUP($AC17,$B:$B,Z:Z),0),Z17) -> 0 | AI17: =IF($AB17="18",AA17+IFERROR(_xlfn.XLOOKUP($AC17,$B:$B,AA:AA),0),AA17) -> 0 | AJ17: =IF($AB17="17",0,MAX(0,-AD17)) -> 0 | AK17: =IF($AB17="17",0,MAX(0,MAX(0,-AE17)-MAX(0,-AD17))) -> 0 | AL17: =IF($AB17="17",0,MAX(0,MAX(0,-AF17)-MAX(0,-AE17))) -> 0 | AM17: =IF($AB17="17",0,MAX(0,MAX(0,-AG17)-MAX(0,-AF17))) -> 0 | AN17: =IF($AB17="17",0,MAX(0,MAX(0,-AH17)-MAX(0,-AG17))) -> 0 | AO17: =IF($AB17="17",0,MAX(0,MAX(0,-AI17)-MAX(0,-AH17))) -> 0 | AR17: =IFERROR(_xlfn.XLOOKUP(B17,#REF!,#REF!),"") | AS17: =IF($AR17="A",AJ17*1.2,IF($AR17="B",AJ17*1.1,AJ17)) -> 0 | AT17: =IF($AR17="A",AK17*1.2,IF($AR17="B",AK17*1.1,AK17)) -> 0 | AU17: =IF($AR17="A",AL17*1.2,IF($AR17="B",AL17*1.1,AL17)) -> 0 | AV17: =IF($AR17="A",AM17*1.2,IF($AR17="B",AM17*1.1,AM17)) -> 0 | AW17: =IF($AR17="A",AN17*1.2,IF($AR17="B",AN17*1.1,AN17)) -> 0 | AX17: =IF($AR17="A",AO17*1.2,IF($AR17="B",AO17*1.1,AO17)) -> 0 | BA17: =SUMIF(Consenso!$C:$C,$B17,Consenso!AZ:AZ) -> 460.75 | BB17: =SUMIF(Consenso!$C:$C,$B17,Consenso!BA:BA) -> 0 | BC17: =SUMIF(Consenso!$C:$C,$B17,Consenso!BB:BB) -> 0 | BD17: =SUMIF(Consenso!$C:$C,$B17,Consenso!BC:BC) -> 0 | BE17: =SUMIF(Consenso!$C:$C,$B17,Consenso!BD:BD) -> 0 | BF17: =SUMIF(Consenso!$C:$C,$B17,Consenso!BE:BE) -> 0
A18: Speck | B18: 150491-5085 | C18: Speck GemShell® iPhone 15 | D18: iPhone 16e / 15 / 14 / 13 | E18: Activo | F18: 7.98 | G18: 0 | H18: =SUMIF(Consenso!$C:$C,$B18,Consenso!AM:AM) -> 125 | I18: =SUMIF(Consenso!$C:$C,$B18,Consenso!AN:AN) -> 50 | J18: =SUMIF(Consenso!$C:$C,$B18,Consenso!AO:AO) -> 30 | K18: =SUMIF(Consenso!$C:$C,$B18,Consenso!AP:AP) -> 30 | L18: =SUMIF(Consenso!$C:$C,$B18,Consenso!AQ:AQ) -> 80 | M18: =SUMIF(Consenso!$C:$C,$B18,Consenso!AR:AR) -> 30 | N18: =IFERROR(VLOOKUP(B:B,Consenso!C:P,14,0),0) -> 15 | O18: =SUMIF('On Orders'!$B:$B,$B18,'On Orders'!E:E) -> 0 | P18: =SUMIF('On Orders'!$B:$B,$B18,'On Orders'!F:F) -> 0 | Q18: =SUMIF('On Orders'!$B:$B,$B18,'On Orders'!G:G) -> 0 | R18: =SUMIF('On Orders'!$B:$B,$B18,'On Orders'!H:H) -> 0 | S18: 0 | T18: 0 | U18: 0 | V18: =(N18+O18+P18)-H18 -> -110 | W18: =(V18+Q18)-I18 -> -160 | X18: =(W18+R18)-J18 -> -190 | Y18: =(X18+S18)-K18 -> -220 | Z18: =(Y18+T18)-L18 -> -300 | AA18: =(Z18+U18)-M18 -> -330 | AB18: =IF(COUNTIF('Master iP17 iP18'!$B:$B,$B18)>0,"18",IF(COUNTIF('Master iP17 iP18'!$E:$E,$B18)>0,"17","NORMAL")) -> NORMAL | AC18: =IF($AB18="18",_xlfn.XLOOKUP($B18,'Master iP17 iP18'!$B:$B,'Master iP17 iP18'!$E:$E),"") | AD18: =IF($AB18="18",V18+IFERROR(_xlfn.XLOOKUP($AC18,$B:$B,V:V),0),V18) -> -110 | AE18: =IF($AB18="18",W18+IFERROR(_xlfn.XLOOKUP($AC18,$B:$B,W:W),0),W18) -> -160 | AF18: =IF($AB18="18",X18+IFERROR(_xlfn.XLOOKUP($AC18,$B:$B,X:X),0),X18) -> -190 | AG18: =IF($AB18="18",Y18+IFERROR(_xlfn.XLOOKUP($AC18,$B:$B,Y:Y),0),Y18) -> -220 | AH18: =IF($AB18="18",Z18+IFERROR(_xlfn.XLOOKUP($AC18,$B:$B,Z:Z),0),Z18) -> -300 | AI18: =IF($AB18="18",AA18+IFERROR(_xlfn.XLOOKUP($AC18,$B:$B,AA:AA),0),AA18) -> -330 | AJ18: =IF($AB18="17",0,MAX(0,-AD18)) -> 110 | AK18: =IF($AB18="17",0,MAX(0,MAX(0,-AE18)-MAX(0,-AD18))) -> 50 | AL18: =IF($AB18="17",0,MAX(0,MAX(0,-AF18)-MAX(0,-AE18))) -> 30 | AM18: =IF($AB18="17",0,MAX(0,MAX(0,-AG18)-MAX(0,-AF18))) -> 30 | AN18: =IF($AB18="17",0,MAX(0,MAX(0,-AH18)-MAX(0,-AG18))) -> 80 | AO18: =IF($AB18="17",0,MAX(0,MAX(0,-AI18)-MAX(0,-AH18))) -> 30 | AR18: =IFERROR(_xlfn.XLOOKUP(B18,#REF!,#REF!),"") | AS18: =IF($AR18="A",AJ18*1.2,IF($AR18="B",AJ18*1.1,AJ18)) -> 110 | AT18: =IF($AR18="A",AK18*1.2,IF($AR18="B",AK18*1.1,AK18)) -> 50 | AU18: =IF($AR18="A",AL18*1.2,IF($AR18="B",AL18*1.1,AL18)) -> 30 | AV18: =IF($AR18="A",AM18*1.2,IF($AR18="B",AM18*1.1,AM18)) -> 30 | AW18: =IF($AR18="A",AN18*1.2,IF($AR18="B",AN18*1.1,AN18)) -> 80 | AX18: =IF($AR18="A",AO18*1.2,IF($AR18="B",AO18*1.1,AO18)) -> 30 | AZ18: PO 70 NAPs | BA18: =SUMIF(Consenso!$C:$C,$B18,Consenso!AZ:AZ) -> 24197.5 | BB18: =SUMIF(Consenso!$C:$C,$B18,Consenso!BA:BA) -> 9679 | BC18: =SUMIF(Consenso!$C:$C,$B18,Consenso!BB:BB) -> 5807.4 | BD18: =SUMIF(Consenso!$C:$C,$B18,Consenso!BC:BC) -> 5807.4 | BE18: =SUMIF(Consenso!$C:$C,$B18,Consenso!BD:BD) -> 15486.4 | BF18: =SUMIF(Consenso!$C:$C,$B18,Consenso!BE:BE) -> 5807.4
A19: Speck | B19: 150989-3267 | C19: Speck Balance Folio iPad 11" (2022-2025) Ceramic Grey/Autumn Sky/Black | D19: iPad 10th /11th - 10.9"/11" (2022-2025) | E19: Activo | F19: 14 | G19: 0 | H19: =SUMIF(Consenso!$C:$C,$B19,Consenso!AM:AM) -> 0 | I19: =SUMIF(Consenso!$C:$C,$B19,Consenso!AN:AN) -> 120 | J19: =SUMIF(Consenso!$C:$C,$B19,Consenso!AO:AO) -> 80 | K19: =SUMIF(Consenso!$C:$C,$B19,Consenso!AP:AP) -> 70 | L19: =SUMIF(Consenso!$C:$C,$B19,Consenso!AQ:AQ) -> 80 | M19: =SUMIF(Consenso!$C:$C,$B19,Consenso!AR:AR) -> 80 | N19: =IFERROR(VLOOKUP(B:B,Consenso!C:P,14,0),0) -> 0 | O19: =SUMIF('On Orders'!$B:$B,$B19,'On Orders'!E:E) -> 0 | P19: =SUMIF('On Orders'!$B:$B,$B19,'On Orders'!F:F) -> 216 | Q19: =SUMIF('On Orders'!$B:$B,$B19,'On Orders'!G:G) -> 0 | R19: =SUMIF('On Orders'!$B:$B,$B19,'On Orders'!H:H) -> 0 | S19: 0 | T19: 0 | U19: 0 | V19: =(N19+O19+P19)-H19 -> 216 | W19: =(V19+Q19)-I19 -> 96 | X19: =(W19+R19)-J19 -> 16 | Y19: =(X19+S19)-K19 -> -54 | Z19: =(Y19+T19)-L19 -> -134 | AA19: =(Z19+U19)-M19 -> -214 | AB19: =IF(COUNTIF('Master iP17 iP18'!$B:$B,$B19)>0,"18",IF(COUNTIF('Master iP17 iP18'!$E:$E,$B19)>0,"17","NORMAL")) -> NORMAL | AC19: =IF($AB19="18",_xlfn.XLOOKUP($B19,'Master iP17 iP18'!$B:$B,'Master iP17 iP18'!$E:$E),"") | AD19: =IF($AB19="18",V19+IFERROR(_xlfn.XLOOKUP($AC19,$B:$B,V:V),0),V19) -> 216 | AE19: =IF($AB19="18",W19+IFERROR(_xlfn.XLOOKUP($AC19,$B:$B,W:W),0),W19) -> 96 | AF19: =IF($AB19="18",X19+IFERROR(_xlfn.XLOOKUP($AC19,$B:$B,X:X),0),X19) -> 16 | AG19: =IF($AB19="18",Y19+IFERROR(_xlfn.XLOOKUP($AC19,$B:$B,Y:Y),0),Y19) -> -54 | AH19: =IF($AB19="18",Z19+IFERROR(_xlfn.XLOOKUP($AC19,$B:$B,Z:Z),0),Z19) -> -134 | AI19: =IF($AB19="18",AA19+IFERROR(_xlfn.XLOOKUP($AC19,$B:$B,AA:AA),0),AA19) -> -214 | AJ19: =IF($AB19="17",0,MAX(0,-AD19)) -> 0 | AK19: =IF($AB19="17",0,MAX(0,MAX(0,-AE19)-MAX(0,-AD19))) -> 0 | AL19: =IF($AB19="17",0,MAX(0,MAX(0,-AF19)-MAX(0,-AE19))) -> 0 | AM19: =IF($AB19="17",0,MAX(0,MAX(0,-AG19)-MAX(0,-AF19))) -> 54 | AN19: =IF($AB19="17",0,MAX(0,MAX(0,-AH19)-MAX(0,-AG19))) -> 80 | AO19: =IF($AB19="17",0,MAX(0,MAX(0,-AI19)-MAX(0,-AH19))) -> 80 | AP19: PO 200 Mediados Julio | AR19: =IFERROR(_xlfn.XLOOKUP(B19,#REF!,#REF!),"") | AS19: =IF($AR19="A",AJ19*1.2,IF($AR19="B",AJ19*1.1,AJ19)) -> 0 | AT19: =IF($AR19="A",AK19*1.2,IF($AR19="B",AK19*1.1,AK19)) -> 0 | AU19: =IF($AR19="A",AL19*1.2,IF($AR19="B",AL19*1.1,AL19)) -> 0 | AV19: =IF($AR19="A",AM19*1.2,IF($AR19="B",AM19*1.1,AM19)) -> 54 | AW19: =IF($AR19="A",AN19*1.2,IF($AR19="B",AN19*1.1,AN19)) -> 80 | AX19: =IF($AR19="A",AO19*1.2,IF($AR19="B",AO19*1.1,AO19)) -> 80 | AY19: Volar 216 - PO / FCST 700 resto del año | BA19: =SUMIF(Consenso!$C:$C,$B19,Consenso!AZ:AZ) -> 12091.44 | BB19: =SUMIF(Consenso!$C:$C,$B19,Consenso!BA:BA) -> 71824.4 | BC19: =SUMIF(Consenso!$C:$C,$B19,Consenso!BB:BB) -> 55608.02 | BD19: =SUMIF(Consenso!$C:$C,$B19,Consenso!BC:BC) -> 47775.35 | BE19: =SUMIF(Consenso!$C:$C,$B19,Consenso!BD:BD) -> 55608.02 | BF19: =SUMIF(Consenso!$C:$C,$B19,Consenso!BE:BE) -> 58127.07
A20: Speck | B20: 150990-9323 | C20: Speck Case-E-Run iPad 11" (2022-2025) Charge Blue/Brave Blue | D20: iPad 10th /11th - 10.9"/11" (2022-2025) | E20: Activo | F20: 10.5 | G20: 0 | H20: =SUMIF(Consenso!$C:$C,$B20,Consenso!AM:AM) -> 0 | I20: =SUMIF(Consenso!$C:$C,$B20,Consenso!AN:AN) -> 0 | J20: =SUMIF(Consenso!$C:$C,$B20,Consenso!AO:AO) -> 64 | K20: =SUMIF(Consenso!$C:$C,$B20,Consenso!AP:AP) -> 73 | L20: =SUMIF(Consenso!$C:$C,$B20,Consenso!AQ:AQ) -> 88 | M20: =SUMIF(Consenso!$C:$C,$B20,Consenso!AR:AR) -> 97 | N20: =IFERROR(VLOOKUP(B:B,Consenso!C:P,14,0),0) -> 129 | O20: =SUMIF('On Orders'!$B:$B,$B20,'On Orders'!E:E) -> 0 | P20: =SUMIF('On Orders'!$B:$B,$B20,'On Orders'!F:F) -> 0 | Q20: =SUMIF('On Orders'!$B:$B,$B20,'On Orders'!G:G) -> 0 | R20: =SUMIF('On Orders'!$B:$B,$B20,'On Orders'!H:H) -> 0 | S20: 0 | T20: 0 | U20: 0 | V20: =(N20+O20+P20)-H20 -> 129 | W20: =(V20+Q20)-I20 -> 129 | X20: =(W20+R20)-J20 -> 65 | Y20: =(X20+S20)-K20 -> -8 | Z20: =(Y20+T20)-L20 -> -96 | AA20: =(Z20+U20)-M20 -> -193 | AB20: =IF(COUNTIF('Master iP17 iP18'!$B:$B,$B20)>0,"18",IF(COUNTIF('Master iP17 iP18'!$E:$E,$B20)>0,"17","NORMAL")) -> NORMAL | AC20: =IF($AB20="18",_xlfn.XLOOKUP($B20,'Master iP17 iP18'!$B:$B,'Master iP17 iP18'!$E:$E),"") | AD20: =IF($AB20="18",V20+IFERROR(_xlfn.XLOOKUP($AC20,$B:$B,V:V),0),V20) -> 129 | AE20: =IF($AB20="18",W20+IFERROR(_xlfn.XLOOKUP($AC20,$B:$B,W:W),0),W20) -> 129 | AF20: =IF($AB20="18",X20+IFERROR(_xlfn.XLOOKUP($AC20,$B:$B,X:X),0),X20) -> 65 | AG20: =IF($AB20="18",Y20+IFERROR(_xlfn.XLOOKUP($AC20,$B:$B,Y:Y),0),Y20) -> -8 | AH20: =IF($AB20="18",Z20+IFERROR(_xlfn.XLOOKUP($AC20,$B:$B,Z:Z),0),Z20) -> -96 | AI20: =IF($AB20="18",AA20+IFERROR(_xlfn.XLOOKUP($AC20,$B:$B,AA:AA),0),AA20) -> -193 | AJ20: =IF($AB20="17",0,MAX(0,-AD20)) -> 0 | AK20: =IF($AB20="17",0,MAX(0,MAX(0,-AE20)-MAX(0,-AD20))) -> 0 | AL20: =IF($AB20="17",0,MAX(0,MAX(0,-AF20)-MAX(0,-AE20))) -> 0 | AM20: =IF($AB20="17",0,MAX(0,MAX(0,-AG20)-MAX(0,-AF20))) -> 8 | AN20: =IF($AB20="17",0,MAX(0,MAX(0,-AH20)-MAX(0,-AG20))) -> 88 | AO20: =IF($AB20="17",0,MAX(0,MAX(0,-AI20)-MAX(0,-AH20))) -> 97 | AR20: =IFERROR(_xlfn.XLOOKUP(B20,#REF!,#REF!),"") | AS20: =IF($AR20="A",AJ20*1.2,IF($AR20="B",AJ20*1.1,AJ20)) -> 0 | AT20: =IF($AR20="A",AK20*1.2,IF($AR20="B",AK20*1.1,AK20)) -> 0 | AU20: =IF($AR20="A",AL20*1.2,IF($AR20="B",AL20*1.1,AL20)) -> 0 | AV20: =IF($AR20="A",AM20*1.2,IF($AR20="B",AM20*1.1,AM20)) -> 8 | AW20: =IF($AR20="A",AN20*1.2,IF($AR20="B",AN20*1.1,AN20)) -> 88 | AX20: =IF($AR20="A",AO20*1.2,IF($AR20="B",AO20*1.1,AO20)) -> 97 | AY20: PO FCST / 200 | BA20: =SUMIF(Consenso!$C:$C,$B20,Consenso!AZ:AZ) -> 25389.28 | BB20: =SUMIF(Consenso!$C:$C,$B20,Consenso!BA:BA) -> 36270.4 | BC20: =SUMIF(Consenso!$C:$C,$B20,Consenso!BB:BB) -> 29016.32 | BD20: =SUMIF(Consenso!$C:$C,$B20,Consenso!BC:BC) -> 33096.74 | BE20: =SUMIF(Consenso!$C:$C,$B20,Consenso!BD:BD) -> 39897.44 | BF20: =SUMIF(Consenso!$C:$C,$B20,Consenso!BE:BE) -> 43977.86
A21: Speck | B21: 150553-3240 | C21: PRESIDIO CLEAR +MS (CLEAR/CLEAR/CHROME FINISH) | D21: iPhone 16e / 15 / 14 / 13 | E21: Activo2 | F21: 13 | G21: 0 | H21: =SUMIF(Consenso!$C:$C,$B21,Consenso!AM:AM) -> 96 | I21: =SUMIF(Consenso!$C:$C,$B21,Consenso!AN:AN) -> 72 | J21: =SUMIF(Consenso!$C:$C,$B21,Consenso!AO:AO) -> 0 | K21: =SUMIF(Consenso!$C:$C,$B21,Consenso!AP:AP) -> 0 | L21: =SUMIF(Consenso!$C:$C,$B21,Consenso!AQ:AQ) -> 0 | M21: =SUMIF(Consenso!$C:$C,$B21,Consenso!AR:AR) -> 0 | N21: =IFERROR(VLOOKUP(B:B,Consenso!C:P,14,0),0) -> 72 | O21: =SUMIF('On Orders'!$B:$B,$B21,'On Orders'!E:E) -> 0 | P21: =SUMIF('On Orders'!$B:$B,$B21,'On Orders'!F:F) -> 0 | Q21: =SUMIF('On Orders'!$B:$B,$B21,'On Orders'!G:G) -> 0 | R21: =SUMIF('On Orders'!$B:$B,$B21,'On Orders'!H:H) -> 0 | S21: 0 | T21: 0 | U21: 0 | V21: =(N21+O21+P21)-H21 -> -24 | W21: =(V21+Q21)-I21 -> -96 | X21: =(W21+R21)-J21 -> -96 | Y21: =(X21+S21)-K21 -> -96 | Z21: =(Y21+T21)-L21 -> -96 | AA21: =(Z21+U21)-M21 -> -96 | AB21: =IF(COUNTIF('Master iP17 iP18'!$B:$B,$B21)>0,"18",IF(COUNTIF('Master iP17 iP18'!$E:$E,$B21)>0,"17","NORMAL")) -> NORMAL | AC21: =IF($AB21="18",_xlfn.XLOOKUP($B21,'Master iP17 iP18'!$B:$B,'Master iP17 iP18'!$E:$E),"") | AD21: =IF($AB21="18",V21+IFERROR(_xlfn.XLOOKUP($AC21,$B:$B,V:V),0),V21) -> -24 | AE21: =IF($AB21="18",W21+IFERROR(_xlfn.XLOOKUP($AC21,$B:$B,W:W),0),W21) -> -96 | AF21: =IF($AB21="18",X21+IFERROR(_xlfn.XLOOKUP($AC21,$B:$B,X:X),0),X21) -> -96 | AG21: =IF($AB21="18",Y21+IFERROR(_xlfn.XLOOKUP($AC21,$B:$B,Y:Y),0),Y21) -> -96 | AH21: =IF($AB21="18",Z21+IFERROR(_xlfn.XLOOKUP($AC21,$B:$B,Z:Z),0),Z21) -> -96 | AI21: =IF($AB21="18",AA21+IFERROR(_xlfn.XLOOKUP($AC21,$B:$B,AA:AA),0),AA21) -> -96 | AJ21: =IF($AB21="17",0,MAX(0,-AD21)) -> 24 | AK21: =IF($AB21="17",0,MAX(0,MAX(0,-AE21)-MAX(0,-AD21))) -> 72 | AL21: =IF($AB21="17",0,MAX(0,MAX(0,-AF21)-MAX(0,-AE21))) -> 0 | AM21: =IF($AB21="17",0,MAX(0,MAX(0,-AG21)-MAX(0,-AF21))) -> 0 | AN21: =IF($AB21="17",0,MAX(0,MAX(0,-AH21)-MAX(0,-AG21))) -> 0 | AO21: =IF($AB21="17",0,MAX(0,MAX(0,-AI21)-MAX(0,-AH21))) -> 0 | AR21: =IFERROR(_xlfn.XLOOKUP(B21,#REF!,#REF!),"") | AS21: =IF($AR21="A",AJ21*1.2,IF($AR21="B",AJ21*1.1,AJ21)) -> 24 | AT21: =IF($AR21="A",AK21*1.2,IF($AR21="B",AK21*1.1,AK21)) -> 72 | AU21: =IF($AR21="A",AL21*1.2,IF($AR21="B",AL21*1.1,AL21)) -> 0 | AV21: =IF($AR21="A",AM21*1.2,IF($AR21="B",AM21*1.1,AM21)) -> 0 | AW21: =IF($AR21="A",AN21*1.2,IF($AR21="B",AN21*1.1,AN21)) -> 0 | AX21: =IF($AR21="A",AO21*1.2,IF($AR21="B",AO21*1.1,AO21)) -> 0 | BA21: =SUMIF(Consenso!$C:$C,$B21,Consenso!AZ:AZ) -> 37203.84 | BB21: =SUMIF(Consenso!$C:$C,$B21,Consenso!BA:BA) -> 19377 | BC21: =SUMIF(Consenso!$C:$C,$B21,Consenso!BB:BB) -> 8525.88 | BD21: =SUMIF(Consenso!$C:$C,$B21,Consenso!BC:BC) -> 0 | BE21: =SUMIF(Consenso!$C:$C,$B21,Consenso!BD:BD) -> 0 | BF21: =SUMIF(Consenso!$C:$C,$B21,Consenso!BE:BE) -> 0
A22: Speck | B22: 150584-3085 | C22: Speck Smartshell for Mackbook Air 15" - Obsidian/Sweater Grey | D22: MacBook Air 15" M2/M3 | E22: Activo | F22: 18 | G22: 0 | H22: =SUMIF(Consenso!$C:$C,$B22,Consenso!AM:AM) -> 21 | I22: =SUMIF(Consenso!$C:$C,$B22,Consenso!AN:AN) -> 34 | J22: =SUMIF(Consenso!$C:$C,$B22,Consenso!AO:AO) -> 15 | K22: =SUMIF(Consenso!$C:$C,$B22,Consenso!AP:AP) -> 32 | L22: =SUMIF(Consenso!$C:$C,$B22,Consenso!AQ:AQ) -> 56 | M22: =SUMIF(Consenso!$C:$C,$B22,Consenso!AR:AR) -> 47 | N22: =IFERROR(VLOOKUP(B:B,Consenso!C:P,14,0),0) -> 11 | O22: =SUMIF('On Orders'!$B:$B,$B22,'On Orders'!E:E) -> 0 | P22: =SUMIF('On Orders'!$B:$B,$B22,'On Orders'!F:F) -> 48 | Q22: =SUMIF('On Orders'!$B:$B,$B22,'On Orders'!G:G) -> 0 | R22: =SUMIF('On Orders'!$B:$B,$B22,'On Orders'!H:H) -> 0 | S22: 0 | T22: 0 | U22: 0 | V22: =(N22+O22+P22)-H22 -> 38 | W22: =(V22+Q22)-I22 -> 4 | X22: =(W22+R22)-J22 -> -11 | Y22: =(X22+S22)-K22 -> -43 | Z22: =(Y22+T22)-L22 -> -99 | AA22: =(Z22+U22)-M22 -> -146 | AB22: =IF(COUNTIF('Master iP17 iP18'!$B:$B,$B22)>0,"18",IF(COUNTIF('Master iP17 iP18'!$E:$E,$B22)>0,"17","NORMAL")) -> NORMAL | AC22: =IF($AB22="18",_xlfn.XLOOKUP($B22,'Master iP17 iP18'!$B:$B,'Master iP17 iP18'!$E:$E),"") | AD22: =IF($AB22="18",V22+IFERROR(_xlfn.XLOOKUP($AC22,$B:$B,V:V),0),V22) -> 38 | AE22: =IF($AB22="18",W22+IFERROR(_xlfn.XLOOKUP($AC22,$B:$B,W:W),0),W22) -> 4 | AF22: =IF($AB22="18",X22+IFERROR(_xlfn.XLOOKUP($AC22,$B:$B,X:X),0),X22) -> -11 | AG22: =IF($AB22="18",Y22+IFERROR(_xlfn.XLOOKUP($AC22,$B:$B,Y:Y),0),Y22) -> -43 | AH22: =IF($AB22="18",Z22+IFERROR(_xlfn.XLOOKUP($AC22,$B:$B,Z:Z),0),Z22) -> -99 | AI22: =IF($AB22="18",AA22+IFERROR(_xlfn.XLOOKUP($AC22,$B:$B,AA:AA),0),AA22) -> -146 | AJ22: =IF($AB22="17",0,MAX(0,-AD22)) -> 0 | AK22: =IF($AB22="17",0,MAX(0,MAX(0,-AE22)-MAX(0,-AD22))) -> 0 | AL22: =IF($AB22="17",0,MAX(0,MAX(0,-AF22)-MAX(0,-AE22))) -> 11 | AM22: =IF($AB22="17",0,MAX(0,MAX(0,-AG22)-MAX(0,-AF22))) -> 32 | AN22: =IF($AB22="17",0,MAX(0,MAX(0,-AH22)-MAX(0,-AG22))) -> 56 | AO22: =IF($AB22="17",0,MAX(0,MAX(0,-AI22)-MAX(0,-AH22))) -> 47 | AP22: PO 40 Med Julio | AR22: =IFERROR(_xlfn.XLOOKUP(B22,#REF!,#REF!),"") | AS22: =IF($AR22="A",AJ22*1.2,IF($AR22="B",AJ22*1.1,AJ22)) -> 0 | AT22: =IF($AR22="A",AK22*1.2,IF($AR22="B",AK22*1.1,AK22)) -> 0 | AU22: =IF($AR22="A",AL22*1.2,IF($AR22="B",AL22*1.1,AL22)) -> 11 | AV22: =IF($AR22="A",AM22*1.2,IF($AR22="B",AM22*1.1,AM22)) -> 32 | AW22: =IF($AR22="A",AN22*1.2,IF($AR22="B",AN22*1.1,AN22)) -> 56 | AX22: =IF($AR22="A",AO22*1.2,IF($AR22="B",AO22*1.1,AO22)) -> 47 | AY22: PO FCST / 150 | BA22: =SUMIF(Consenso!$C:$C,$B22,Consenso!AZ:AZ) -> 11305.56 | BB22: =SUMIF(Consenso!$C:$C,$B22,Consenso!BA:BA) -> 18304.24 | BC22: =SUMIF(Consenso!$C:$C,$B22,Consenso!BB:BB) -> 8075.4 | BD22: =SUMIF(Consenso!$C:$C,$B22,Consenso!BC:BC) -> 17227.52 | BE22: =SUMIF(Consenso!$C:$C,$B22,Consenso!BD:BD) -> 30148.16 | BF22: =SUMIF(Consenso!$C:$C,$B22,Consenso!BE:BE) -> 25302.92
A23: Speck | B23: 150584-9992 | C23: Speck Smartshell for Mackbook Air 15" - Clear/Sweater Grey | D23: MacBook Air 15" M2/M3 | E23: Activo | F23: 18 | G23: 0 | H23: =SUMIF(Consenso!$C:$C,$B23,Consenso!AM:AM) -> 45 | I23: =SUMIF(Consenso!$C:$C,$B23,Consenso!AN:AN) -> 50 | J23: =SUMIF(Consenso!$C:$C,$B23,Consenso!AO:AO) -> 20 | K23: =SUMIF(Consenso!$C:$C,$B23,Consenso!AP:AP) -> 80 | L23: =SUMIF(Consenso!$C:$C,$B23,Consenso!AQ:AQ) -> 80 | M23: =SUMIF(Consenso!$C:$C,$B23,Consenso!AR:AR) -> 100 | N23: =IFERROR(VLOOKUP(B:B,Consenso!C:P,14,0),0) -> 12 | O23: =SUMIF('On Orders'!$B:$B,$B23,'On Orders'!E:E) -> 0 | P23: =SUMIF('On Orders'!$B:$B,$B23,'On Orders'!F:F) -> 48 | Q23: =SUMIF('On Orders'!$B:$B,$B23,'On Orders'!G:G) -> 0 | R23: =SUMIF('On Orders'!$B:$B,$B23,'On Orders'!H:H) -> 0 | S23: 0 | T23: 0 | U23: 0 | V23: =(N23+O23+P23)-H23 -> 15 | W23: =(V23+Q23)-I23 -> -35 | X23: =(W23+R23)-J23 -> -55 | Y23: =(X23+S23)-K23 -> -135 | Z23: =(Y23+T23)-L23 -> -215 | AA23: =(Z23+U23)-M23 -> -315 | AB23: =IF(COUNTIF('Master iP17 iP18'!$B:$B,$B23)>0,"18",IF(COUNTIF('Master iP17 iP18'!$E:$E,$B23)>0,"17","NORMAL")) -> NORMAL | AC23: =IF($AB23="18",_xlfn.XLOOKUP($B23,'Master iP17 iP18'!$B:$B,'Master iP17 iP18'!$E:$E),"") | AD23: =IF($AB23="18",V23+IFERROR(_xlfn.XLOOKUP($AC23,$B:$B,V:V),0),V23) -> 15 | AE23: =IF($AB23="18",W23+IFERROR(_xlfn.XLOOKUP($AC23,$B:$B,W:W),0),W23) -> -35 | AF23: =IF($AB23="18",X23+IFERROR(_xlfn.XLOOKUP($AC23,$B:$B,X:X),0),X23) -> -55 | AG23: =IF($AB23="18",Y23+IFERROR(_xlfn.XLOOKUP($AC23,$B:$B,Y:Y),0),Y23) -> -135 | AH23: =IF($AB23="18",Z23+IFERROR(_xlfn.XLOOKUP($AC23,$B:$B,Z:Z),0),Z23) -> -215 | AI23: =IF($AB23="18",AA23+IFERROR(_xlfn.XLOOKUP($AC23,$B:$B,AA:AA),0),AA23) -> -315 | AJ23: =IF($AB23="17",0,MAX(0,-AD23)) -> 0 | AK23: =IF($AB23="17",0,MAX(0,MAX(0,-AE23)-MAX(0,-AD23))) -> 35 | AL23: =IF($AB23="17",0,MAX(0,MAX(0,-AF23)-MAX(0,-AE23))) -> 20 | AM23: =IF($AB23="17",0,MAX(0,MAX(0,-AG23)-MAX(0,-AF23))) -> 80 | AN23: =IF($AB23="17",0,MAX(0,MAX(0,-AH23)-MAX(0,-AG23))) -> 80 | AO23: =IF($AB23="17",0,MAX(0,MAX(0,-AI23)-MAX(0,-AH23))) -> 100 | AP23: PO 40 Med Julio | AR23: =IFERROR(_xlfn.XLOOKUP(B23,#REF!,#REF!),"") | AS23: =IF($AR23="A",AJ23*1.2,IF($AR23="B",AJ23*1.1,AJ23)) -> 0 | AT23: =IF($AR23="A",AK23*1.2,IF($AR23="B",AK23*1.1,AK23)) -> 35 | AU23: =IF($AR23="A",AL23*1.2,IF($AR23="B",AL23*1.1,AL23)) -> 20 | AV23: =IF($AR23="A",AM23*1.2,IF($AR23="B",AM23*1.1,AM23)) -> 80 | AW23: =IF($AR23="A",AN23*1.2,IF($AR23="B",AN23*1.1,AN23)) -> 80 | AX23: =IF($AR23="A",AO23*1.2,IF($AR23="B",AO23*1.1,AO23)) -> 100 | AY23: PO FCST / 300 | AZ23: PO 60 | BA23: =SUMIF(Consenso!$C:$C,$B23,Consenso!AZ:AZ) -> 24226.2 | BB23: =SUMIF(Consenso!$C:$C,$B23,Consenso!BA:BA) -> 26918 | BC23: =SUMIF(Consenso!$C:$C,$B23,Consenso!BB:BB) -> 10767.2 | BD23: =SUMIF(Consenso!$C:$C,$B23,Consenso!BC:BC) -> 43068.8 | BE23: =SUMIF(Consenso!$C:$C,$B23,Consenso!BD:BD) -> 43068.8 | BF23: =SUMIF(Consenso!$C:$C,$B23,Consenso!BE:BE) -> 53836
A24: Speck | B24: 150585-1568 | C24: Speck Tagimals 4-Pack - Mulicolor | D24: AirTag | E24: Activo | F24: 7 | G24: 0 | H24: =SUMIF(Consenso!$C:$C,$B24,Consenso!AM:AM) -> 1 | I24: =SUMIF(Consenso!$C:$C,$B24,Consenso!AN:AN) -> 80 | J24: =SUMIF(Consenso!$C:$C,$B24,Consenso!AO:AO) -> 36 | K24: =SUMIF(Consenso!$C:$C,$B24,Consenso!AP:AP) -> 84 | L24: =SUMIF(Consenso!$C:$C,$B24,Consenso!AQ:AQ) -> 100 | M24: =SUMIF(Consenso!$C:$C,$B24,Consenso!AR:AR) -> 51 | N24: =IFERROR(VLOOKUP(B:B,Consenso!C:P,14,0),0) -> 0 | O24: =SUMIF('On Orders'!$B:$B,$B24,'On Orders'!E:E) -> 0 | P24: =SUMIF('On Orders'!$B:$B,$B24,'On Orders'!F:F) -> 168 | Q24: =SUMIF('On Orders'!$B:$B,$B24,'On Orders'!G:G) -> 0 | R24: =SUMIF('On Orders'!$B:$B,$B24,'On Orders'!H:H) -> 0 | S24: 0 | T24: 0 | U24: 0 | V24: =(N24+O24+P24)-H24 -> 167 | W24: =(V24+Q24)-I24 -> 87 | X24: =(W24+R24)-J24 -> 51 | Y24: =(X24+S24)-K24 -> -33 | Z24: =(Y24+T24)-L24 -> -133 | AA24: =(Z24+U24)-M24 -> -184 | AB24: =IF(COUNTIF('Master iP17 iP18'!$B:$B,$B24)>0,"18",IF(COUNTIF('Master iP17 iP18'!$E:$E,$B24)>0,"17","NORMAL")) -> NORMAL | AC24: =IF($AB24="18",_xlfn.XLOOKUP($B24,'Master iP17 iP18'!$B:$B,'Master iP17 iP18'!$E:$E),"") | AD24: =IF($AB24="18",V24+IFERROR(_xlfn.XLOOKUP($AC24,$B:$B,V:V),0),V24) -> 167 | AE24: =IF($AB24="18",W24+IFERROR(_xlfn.XLOOKUP($AC24,$B:$B,W:W),0),W24) -> 87 | AF24: =IF($AB24="18",X24+IFERROR(_xlfn.XLOOKUP($AC24,$B:$B,X:X),0),X24) -> 51 | AG24: =IF($AB24="18",Y24+IFERROR(_xlfn.XLOOKUP($AC24,$B:$B,Y:Y),0),Y24) -> -33 | AH24: =IF($AB24="18",Z24+IFERROR(_xlfn.XLOOKUP($AC24,$B:$B,Z:Z),0),Z24) -> -133 | AI24: =IF($AB24="18",AA24+IFERROR(_xlfn.XLOOKUP($AC24,$B:$B,AA:AA),0),AA24) -> -184 | AJ24: =IF($AB24="17",0,MAX(0,-AD24)) -> 0 | AK24: =IF($AB24="17",0,MAX(0,MAX(0,-AE24)-MAX(0,-AD24))) -> 0 | AL24: =IF($AB24="17",0,MAX(0,MAX(0,-AF24)-MAX(0,-AE24))) -> 0 | AM24: =IF($AB24="17",0,MAX(0,MAX(0,-AG24)-MAX(0,-AF24))) -> 33 | AN24: =IF($AB24="17",0,MAX(0,MAX(0,-AH24)-MAX(0,-AG24))) -> 100 | AO24: =IF($AB24="17",0,MAX(0,MAX(0,-AI24)-MAX(0,-AH24))) -> 51 | AP24: PO 150 Med Julio | AR24: =IFERROR(_xlfn.XLOOKUP(B24,#REF!,#REF!),"") | AS24: =IF($AR24="A",AJ24*1.2,IF($AR24="B",AJ24*1.1,AJ24)) -> 0 | AT24: =IF($AR24="A",AK24*1.2,IF($AR24="B",AK24*1.1,AK24)) -> 0 | AU24: =IF($AR24="A",AL24*1.2,IF($AR24="B",AL24*1.1,AL24)) -> 0 | AV24: =IF($AR24="A",AM24*1.2,IF($AR24="B",AM24*1.1,AM24)) -> 33 | AW24: =IF($AR24="A",AN24*1.2,IF($AR24="B",AN24*1.1,AN24)) -> 100 | AX24: =IF($AR24="A",AO24*1.2,IF($AR24="B",AO24*1.1,AO24)) -> 51 | AZ24: 10 - Naps | BA24: =SUMIF(Consenso!$C:$C,$B24,Consenso!AZ:AZ) -> 11107.25 | BB24: =SUMIF(Consenso!$C:$C,$B24,Consenso!BA:BA) -> 28558.24 | BC24: =SUMIF(Consenso!$C:$C,$B24,Consenso!BB:BB) -> 16219.4 | BD24: =SUMIF(Consenso!$C:$C,$B24,Consenso!BC:BC) -> 28581.48 | BE24: =SUMIF(Consenso!$C:$C,$B24,Consenso!BD:BD) -> 34111.88 | BF24: =SUMIF(Consenso!$C:$C,$B24,Consenso!BE:BE) -> 23631.99
A25: Speck | B25: 150697-5085 | C25: Speck iPhone 16 Gemshell Grip +Ms Clear/Clear | D25: iPhone 16 | E25: Descontinuado | F25: 13 | G25: 0 | H25: =SUMIF(Consenso!$C:$C,$B25,Consenso!AM:AM) -> 0 | I25: =SUMIF(Consenso!$C:$C,$B25,Consenso!AN:AN) -> 0 | J25: =SUMIF(Consenso!$C:$C,$B25,Consenso!AO:AO) -> 0 | K25: =SUMIF(Consenso!$C:$C,$B25,Consenso!AP:AP) -> 0 | L25: =SUMIF(Consenso!$C:$C,$B25,Consenso!AQ:AQ) -> 0 | M25: =SUMIF(Consenso!$C:$C,$B25,Consenso!AR:AR) -> 0 | N25: =IFERROR(VLOOKUP(B:B,Consenso!C:P,14,0),0) -> 116 | O25: =SUMIF('On Orders'!$B:$B,$B25,'On Orders'!E:E) -> 0 | P25: =SUMIF('On Orders'!$B:$B,$B25,'On Orders'!F:F) -> 0 | Q25: =SUMIF('On Orders'!$B:$B,$B25,'On Orders'!G:G) -> 0 | R25: =SUMIF('On Orders'!$B:$B,$B25,'On Orders'!H:H) -> 0 | S25: 0 | T25: 0 | U25: 0 | V25: =(N25+O25+P25)-H25 -> 116 | W25: =(V25+Q25)-I25 -> 116 | X25: =(W25+R25)-J25 -> 116 | Y25: =(X25+S25)-K25 -> 116 | Z25: =(Y25+T25)-L25 -> 116 | AA25: =(Z25+U25)-M25 -> 116 | AB25: =IF(COUNTIF('Master iP17 iP18'!$B:$B,$B25)>0,"18",IF(COUNTIF('Master iP17 iP18'!$E:$E,$B25)>0,"17","NORMAL")) -> NORMAL | AC25: =IF($AB25="18",_xlfn.XLOOKUP($B25,'Master iP17 iP18'!$B:$B,'Master iP17 iP18'!$E:$E),"") | AD25: =IF($AB25="18",V25+IFERROR(_xlfn.XLOOKUP($AC25,$B:$B,V:V),0),V25) -> 116 | AE25: =IF($AB25="18",W25+IFERROR(_xlfn.XLOOKUP($AC25,$B:$B,W:W),0),W25) -> 116 | AF25: =IF($AB25="18",X25+IFERROR(_xlfn.XLOOKUP($AC25,$B:$B,X:X),0),X25) -> 116 | AG25: =IF($AB25="18",Y25+IFERROR(_xlfn.XLOOKUP($AC25,$B:$B,Y:Y),0),Y25) -> 116 | AH25: =IF($AB25="18",Z25+IFERROR(_xlfn.XLOOKUP($AC25,$B:$B,Z:Z),0),Z25) -> 116 | AI25: =IF($AB25="18",AA25+IFERROR(_xlfn.XLOOKUP($AC25,$B:$B,AA:AA),0),AA25) -> 116 | AJ25: =IF($AB25="17",0,MAX(0,-AD25)) -> 0 | AK25: =IF($AB25="17",0,MAX(0,MAX(0,-AE25)-MAX(0,-AD25))) -> 0 | AL25: =IF($AB25="17",0,MAX(0,MAX(0,-AF25)-MAX(0,-AE25))) -> 0 | AM25: =IF($AB25="17",0,MAX(0,MAX(0,-AG25)-MAX(0,-AF25))) -> 0 | AN25: =IF($AB25="17",0,MAX(0,MAX(0,-AH25)-MAX(0,-AG25))) -> 0 | AO25: =IF($AB25="17",0,MAX(0,MAX(0,-AI25)-MAX(0,-AH25))) -> 0 | AR25: =IFERROR(_xlfn.XLOOKUP(B25,#REF!,#REF!),"") | AS25: =IF($AR25="A",AJ25*1.2,IF($AR25="B",AJ25*1.1,AJ25)) -> 0 | AT25: =IF($AR25="A",AK25*1.2,IF($AR25="B",AK25*1.1,AK25)) -> 0 | AU25: =IF($AR25="A",AL25*1.2,IF($AR25="B",AL25*1.1,AL25)) -> 0 | AV25: =IF($AR25="A",AM25*1.2,IF($AR25="B",AM25*1.1,AM25)) -> 0 | AW25: =IF($AR25="A",AN25*1.2,IF($AR25="B",AN25*1.1,AN25)) -> 0 | AX25: =IF($AR25="A",AO25*1.2,IF($AR25="B",AO25*1.1,AO25)) -> 0 | BA25: =SUMIF(Consenso!$C:$C,$B25,Consenso!AZ:AZ) -> 0 | BB25: =SUMIF(Consenso!$C:$C,$B25,Consenso!BA:BA) -> 0 | BC25: =SUMIF(Consenso!$C:$C,$B25,Consenso!BB:BB) -> 0 | BD25: =SUMIF(Consenso!$C:$C,$B25,Consenso!BC:BC) -> 0 | BE25: =SUMIF(Consenso!$C:$C,$B25,Consenso!BD:BD) -> 0 | BF25: =SUMIF(Consenso!$C:$C,$B25,Consenso!BE:BE) -> 0
A26: Speck | B26: 150698-9508 | C26: Speck iPhone 16 Gemshell Clear/ Platinum Glitter | D26: iPhone 16 | E26: Descontinuado | F26: 11 | G26: 0 | H26: =SUMIF(Consenso!$C:$C,$B26,Consenso!AM:AM) -> 0 | I26: =SUMIF(Consenso!$C:$C,$B26,Consenso!AN:AN) -> 0 | J26: =SUMIF(Consenso!$C:$C,$B26,Consenso!AO:AO) -> 0 | K26: =SUMIF(Consenso!$C:$C,$B26,Consenso!AP:AP) -> 0 | L26: =SUMIF(Consenso!$C:$C,$B26,Consenso!AQ:AQ) -> 0 | M26: =SUMIF(Consenso!$C:$C,$B26,Consenso!AR:AR) -> 0 | N26: =IFERROR(VLOOKUP(B:B,Consenso!C:P,14,0),0) -> 280 | O26: =SUMIF('On Orders'!$B:$B,$B26,'On Orders'!E:E) -> 0 | P26: =SUMIF('On Orders'!$B:$B,$B26,'On Orders'!F:F) -> 0 | Q26: =SUMIF('On Orders'!$B:$B,$B26,'On Orders'!G:G) -> 0 | R26: =SUMIF('On Orders'!$B:$B,$B26,'On Orders'!H:H) -> 0 | S26: 0 | T26: 0 | U26: 0 | V26: =(N26+O26+P26)-H26 -> 280 | W26: =(V26+Q26)-I26 -> 280 | X26: =(W26+R26)-J26 -> 280 | Y26: =(X26+S26)-K26 -> 280 | Z26: =(Y26+T26)-L26 -> 280 | AA26: =(Z26+U26)-M26 -> 280 | AB26: =IF(COUNTIF('Master iP17 iP18'!$B:$B,$B26)>0,"18",IF(COUNTIF('Master iP17 iP18'!$E:$E,$B26)>0,"17","NORMAL")) -> NORMAL | AC26: =IF($AB26="18",_xlfn.XLOOKUP($B26,'Master iP17 iP18'!$B:$B,'Master iP17 iP18'!$E:$E),"") | AD26: =IF($AB26="18",V26+IFERROR(_xlfn.XLOOKUP($AC26,$B:$B,V:V),0),V26) -> 280 | AE26: =IF($AB26="18",W26+IFERROR(_xlfn.XLOOKUP($AC26,$B:$B,W:W),0),W26) -> 280 | AF26: =IF($AB26="18",X26+IFERROR(_xlfn.XLOOKUP($AC26,$B:$B,X:X),0),X26) -> 280 | AG26: =IF($AB26="18",Y26+IFERROR(_xlfn.XLOOKUP($AC26,$B:$B,Y:Y),0),Y26) -> 280 | AH26: =IF($AB26="18",Z26+IFERROR(_xlfn.XLOOKUP($AC26,$B:$B,Z:Z),0),Z26) -> 280 | AI26: =IF($AB26="18",AA26+IFERROR(_xlfn.XLOOKUP($AC26,$B:$B,AA:AA),0),AA26) -> 280 | AJ26: =IF($AB26="17",0,MAX(0,-AD26)) -> 0 | AK26: =IF($AB26="17",0,MAX(0,MAX(0,-AE26)-MAX(0,-AD26))) -> 0 | AL26: =IF($AB26="17",0,MAX(0,MAX(0,-AF26)-MAX(0,-AE26))) -> 0 | AM26: =IF($AB26="17",0,MAX(0,MAX(0,-AG26)-MAX(0,-AF26))) -> 0 | AN26: =IF($AB26="17",0,MAX(0,MAX(0,-AH26)-MAX(0,-AG26))) -> 0 | AO26: =IF($AB26="17",0,MAX(0,MAX(0,-AI26)-MAX(0,-AH26))) -> 0 | AR26: =IFERROR(_xlfn.XLOOKUP(B26,#REF!,#REF!),"") | AS26: =IF($AR26="A",AJ26*1.2,IF($AR26="B",AJ26*1.1,AJ26)) -> 0 | AT26: =IF($AR26="A",AK26*1.2,IF($AR26="B",AK26*1.1,AK26)) -> 0 | AU26: =IF($AR26="A",AL26*1.2,IF($AR26="B",AL26*1.1,AL26)) -> 0 | AV26: =IF($AR26="A",AM26*1.2,IF($AR26="B",AM26*1.1,AM26)) -> 0 | AW26: =IF($AR26="A",AN26*1.2,IF($AR26="B",AN26*1.1,AN26)) -> 0 | AX26: =IF($AR26="A",AO26*1.2,IF($AR26="B",AO26*1.1,AO26)) -> 0 | BA26: =SUMIF(Consenso!$C:$C,$B26,Consenso!AZ:AZ) -> 5525.2 | BB26: =SUMIF(Consenso!$C:$C,$B26,Consenso!BA:BA) -> 5902.17 | BC26: =SUMIF(Consenso!$C:$C,$B26,Consenso!BB:BB) -> 8179.39 | BD26: =SUMIF(Consenso!$C:$C,$B26,Consenso!BC:BC) -> 5592.34 | BE26: =SUMIF(Consenso!$C:$C,$B26,Consenso!BD:BD) -> 5592.34 | BF26: =SUMIF(Consenso!$C:$C,$B26,Consenso!BE:BE) -> 6178.43
A27: Speck | B27: 142573-1050 | C27: Speck Balance Folio with Microban for iPad mini 6 - Black | D27: iPad mini 6 | E27: Descontinuado | F27: 11 | G27: 0 | H27: =SUMIF(Consenso!$C:$C,$B27,Consenso!AM:AM) -> 88 | I27: =SUMIF(Consenso!$C:$C,$B27,Consenso!AN:AN) -> 60 | J27: =SUMIF(Consenso!$C:$C,$B27,Consenso!AO:AO) -> 40 | K27: =SUMIF(Consenso!$C:$C,$B27,Consenso!AP:AP) -> 0 | L27: =SUMIF(Consenso!$C:$C,$B27,Consenso!AQ:AQ) -> 0 | M27: =SUMIF(Consenso!$C:$C,$B27,Consenso!AR:AR) -> 0 | N27: =IFERROR(VLOOKUP(B:B,Consenso!C:P,14,0),0) -> 132 | O27: =SUMIF('On Orders'!$B:$B,$B27,'On Orders'!E:E) -> 0 | P27: =SUMIF('On Orders'!$B:$B,$B27,'On Orders'!F:F) -> 0 | Q27: =SUMIF('On Orders'!$B:$B,$B27,'On Orders'!G:G) -> 0 | R27: =SUMIF('On Orders'!$B:$B,$B27,'On Orders'!H:H) -> 0 | S27: 0 | T27: 0 | U27: 0 | V27: =(N27+O27+P27)-H27 -> 44 | W27: =(V27+Q27)-I27 -> -16 | X27: =(W27+R27)-J27 -> -56 | Y27: =(X27+S27)-K27 -> -56 | Z27: =(Y27+T27)-L27 -> -56 | AA27: =(Z27+U27)-M27 -> -56 | AB27: =IF(COUNTIF('Master iP17 iP18'!$B:$B,$B27)>0,"18",IF(COUNTIF('Master iP17 iP18'!$E:$E,$B27)>0,"17","NORMAL")) -> NORMAL | AC27: =IF($AB27="18",_xlfn.XLOOKUP($B27,'Master iP17 iP18'!$B:$B,'Master iP17 iP18'!$E:$E),"") | AD27: =IF($AB27="18",V27+IFERROR(_xlfn.XLOOKUP($AC27,$B:$B,V:V),0),V27) -> 44 | AE27: =IF($AB27="18",W27+IFERROR(_xlfn.XLOOKUP($AC27,$B:$B,W:W),0),W27) -> -16 | AF27: =IF($AB27="18",X27+IFERROR(_xlfn.XLOOKUP($AC27,$B:$B,X:X),0),X27) -> -56 | AG27: =IF($AB27="18",Y27+IFERROR(_xlfn.XLOOKUP($AC27,$B:$B,Y:Y),0),Y27) -> -56 | AH27: =IF($AB27="18",Z27+IFERROR(_xlfn.XLOOKUP($AC27,$B:$B,Z:Z),0),Z27) -> -56 | AI27: =IF($AB27="18",AA27+IFERROR(_xlfn.XLOOKUP($AC27,$B:$B,AA:AA),0),AA27) -> -56 | AJ27: =IF($AB27="17",0,MAX(0,-AD27)) -> 0 | AK27: =IF($AB27="17",0,MAX(0,MAX(0,-AE27)-MAX(0,-AD27))) -> 16 | AL27: =IF($AB27="17",0,MAX(0,MAX(0,-AF27)-MAX(0,-AE27))) -> 40 | AM27: =IF($AB27="17",0,MAX(0,MAX(0,-AG27)-MAX(0,-AF27))) -> 0 | AN27: =IF($AB27="17",0,MAX(0,MAX(0,-AH27)-MAX(0,-AG27))) -> 0 | AO27: =IF($AB27="17",0,MAX(0,MAX(0,-AI27)-MAX(0,-AH27))) -> 0 | AR27: =IFERROR(_xlfn.XLOOKUP(B27,#REF!,#REF!),"") | AS27: =IF($AR27="A",AJ27*1.2,IF($AR27="B",AJ27*1.1,AJ27)) -> 0 | AT27: =IF($AR27="A",AK27*1.2,IF($AR27="B",AK27*1.1,AK27)) -> 16 | AU27: =IF($AR27="A",AL27*1.2,IF($AR27="B",AL27*1.1,AL27)) -> 40 | AV27: =IF($AR27="A",AM27*1.2,IF($AR27="B",AM27*1.1,AM27)) -> 0 | AW27: =IF($AR27="A",AN27*1.2,IF($AR27="B",AN27*1.1,AN27)) -> 0 | AX27: =IF($AR27="A",AO27*1.2,IF($AR27="B",AO27*1.1,AO27)) -> 0 | AY27: Pushback iShop | BA27: =SUMIF(Consenso!$C:$C,$B27,Consenso!AZ:AZ) -> 30307.2 | BB27: =SUMIF(Consenso!$C:$C,$B27,Consenso!BA:BA) -> 20664 | BC27: =SUMIF(Consenso!$C:$C,$B27,Consenso!BB:BB) -> 13776 | BD27: =SUMIF(Consenso!$C:$C,$B27,Consenso!BC:BC) -> 0 | BE27: =SUMIF(Consenso!$C:$C,$B27,Consenso!BD:BD) -> 0 | BF27: =SUMIF(Consenso!$C:$C,$B27,Consenso!BE:BE) -> 0
A28: Speck | B28: 150954-3240 | C28: Speck Presidio Perfect-Clear + MS iPhone 17 Clear | D28: iPhone 17 | E28: Descontinuado | F28: 13 | G28: 0 | H28: =SUMIF(Consenso!$C:$C,$B28,Consenso!AM:AM) -> 0 | I28: =SUMIF(Consenso!$C:$C,$B28,Consenso!AN:AN) -> 0 | J28: =SUMIF(Consenso!$C:$C,$B28,Consenso!AO:AO) -> 0 | K28: =SUMIF(Consenso!$C:$C,$B28,Consenso!AP:AP) -> 0 | L28: =SUMIF(Consenso!$C:$C,$B28,Consenso!AQ:AQ) -> 0 | M28: =SUMIF(Consenso!$C:$C,$B28,Consenso!AR:AR) -> 0 | N28: =IFERROR(VLOOKUP(B:B,Consenso!C:P,14,0),0) -> 0 | O28: =SUMIF('On Orders'!$B:$B,$B28,'On Orders'!E:E) -> 0 | P28: =SUMIF('On Orders'!$B:$B,$B28,'On Orders'!F:F) -> 23 | Q28: =SUMIF('On Orders'!$B:$B,$B28,'On Orders'!G:G) -> 0 | R28: =SUMIF('On Orders'!$B:$B,$B28,'On Orders'!H:H) -> 0 | S28: 0 | T28: 0 | U28: 0 | V28: =(N28+O28+P28)-H28 -> 23 | W28: =(V28+Q28)-I28 -> 23 | X28: =(W28+R28)-J28 -> 23 | Y28: =(X28+S28)-K28 -> 23 | Z28: =(Y28+T28)-L28 -> 23 | AA28: =(Z28+U28)-M28 -> 23 | AB28: =IF(COUNTIF('Master iP17 iP18'!$B:$B,$B28)>0,"18",IF(COUNTIF('Master iP17 iP18'!$E:$E,$B28)>0,"17","NORMAL")) -> NORMAL | AC28: =IF($AB28="18",_xlfn.XLOOKUP($B28,'Master iP17 iP18'!$B:$B,'Master iP17 iP18'!$E:$E),"") | AD28: =IF($AB28="18",V28+IFERROR(_xlfn.XLOOKUP($AC28,$B:$B,V:V),0),V28) -> 23 | AE28: =IF($AB28="18",W28+IFERROR(_xlfn.XLOOKUP($AC28,$B:$B,W:W),0),W28) -> 23 | AF28: =IF($AB28="18",X28+IFERROR(_xlfn.XLOOKUP($AC28,$B:$B,X:X),0),X28) -> 23 | AG28: =IF($AB28="18",Y28+IFERROR(_xlfn.XLOOKUP($AC28,$B:$B,Y:Y),0),Y28) -> 23 | AH28: =IF($AB28="18",Z28+IFERROR(_xlfn.XLOOKUP($AC28,$B:$B,Z:Z),0),Z28) -> 23 | AI28: =IF($AB28="18",AA28+IFERROR(_xlfn.XLOOKUP($AC28,$B:$B,AA:AA),0),AA28) -> 23 | AJ28: =IF($AB28="17",0,MAX(0,-AD28)) -> 0 | AK28: =IF($AB28="17",0,MAX(0,MAX(0,-AE28)-MAX(0,-AD28))) -> 0 | AL28: =IF($AB28="17",0,MAX(0,MAX(0,-AF28)-MAX(0,-AE28))) -> 0 | AM28: =IF($AB28="17",0,MAX(0,MAX(0,-AG28)-MAX(0,-AF28))) -> 0 | AN28: =IF($AB28="17",0,MAX(0,MAX(0,-AH28)-MAX(0,-AG28))) -> 0 | AO28: =IF($AB28="17",0,MAX(0,MAX(0,-AI28)-MAX(0,-AH28))) -> 0 | AR28: =IFERROR(_xlfn.XLOOKUP(B28,#REF!,#REF!),"") | AS28: =IF($AR28="A",AJ28*1.2,IF($AR28="B",AJ28*1.1,AJ28)) -> 0 | AT28: =IF($AR28="A",AK28*1.2,IF($AR28="B",AK28*1.1,AK28)) -> 0 | AU28: =IF($AR28="A",AL28*1.2,IF($AR28="B",AL28*1.1,AL28)) -> 0 | AV28: =IF($AR28="A",AM28*1.2,IF($AR28="B",AM28*1.1,AM28)) -> 0 | AW28: =IF($AR28="A",AN28*1.2,IF($AR28="B",AN28*1.1,AN28)) -> 0 | AX28: =IF($AR28="A",AO28*1.2,IF($AR28="B",AO28*1.1,AO28)) -> 0 | BA28: =SUMIF(Consenso!$C:$C,$B28,Consenso!AZ:AZ) -> 11884.56 | BB28: =SUMIF(Consenso!$C:$C,$B28,Consenso!BA:BA) -> 11884.56 | BC28: =SUMIF(Consenso!$C:$C,$B28,Consenso!BB:BB) -> 7234.08 | BD28: =SUMIF(Consenso!$C:$C,$B28,Consenso!BC:BC) -> 8267.52 | BE28: =SUMIF(Consenso!$C:$C,$B28,Consenso!BD:BD) -> 5167.2 | BF28: =SUMIF(Consenso!$C:$C,$B28,Consenso!BE:BE) -> 5683.92
A29: Speck | B29: 150957-D143 | C29: Speck Presidio2 + MS iPhone 17 Black/Slate Grey/White | D29: iPhone 17 | E29: Descontinuado | F29: 13 | G29: 0 | H29: =SUMIF(Consenso!$C:$C,$B29,Consenso!AM:AM) -> 34 | I29: =SUMIF(Consenso!$C:$C,$B29,Consenso!AN:AN) -> 11 | J29: =SUMIF(Consenso!$C:$C,$B29,Consenso!AO:AO) -> 11 | K29: =SUMIF(Consenso!$C:$C,$B29,Consenso!AP:AP) -> 11 | L29: =SUMIF(Consenso!$C:$C,$B29,Consenso!AQ:AQ) -> 11 | M29: =SUMIF(Consenso!$C:$C,$B29,Consenso!AR:AR) -> 11 | N29: =IFERROR(VLOOKUP(B:B,Consenso!C:P,14,0),0) -> 186 | O29: =SUMIF('On Orders'!$B:$B,$B29,'On Orders'!E:E) -> 0 | P29: =SUMIF('On Orders'!$B:$B,$B29,'On Orders'!F:F) -> 0 | Q29: =SUMIF('On Orders'!$B:$B,$B29,'On Orders'!G:G) -> 0 | R29: =SUMIF('On Orders'!$B:$B,$B29,'On Orders'!H:H) -> 0 | S29: 0 | T29: 0 | U29: 0 | V29: =(N29+O29+P29)-H29 -> 152 | W29: =(V29+Q29)-I29 -> 141 | X29: =(W29+R29)-J29 -> 130 | Y29: =(X29+S29)-K29 -> 119 | Z29: =(Y29+T29)-L29 -> 108 | AA29: =(Z29+U29)-M29 -> 97 | AB29: =IF(COUNTIF('Master iP17 iP18'!$B:$B,$B29)>0,"18",IF(COUNTIF('Master iP17 iP18'!$E:$E,$B29)>0,"17","NORMAL")) -> NORMAL | AC29: =IF($AB29="18",_xlfn.XLOOKUP($B29,'Master iP17 iP18'!$B:$B,'Master iP17 iP18'!$E:$E),"") | AD29: =IF($AB29="18",V29+IFERROR(_xlfn.XLOOKUP($AC29,$B:$B,V:V),0),V29) -> 152 | AE29: =IF($AB29="18",W29+IFERROR(_xlfn.XLOOKUP($AC29,$B:$B,W:W),0),W29) -> 141 | AF29: =IF($AB29="18",X29+IFERROR(_xlfn.XLOOKUP($AC29,$B:$B,X:X),0),X29) -> 130 | AG29: =IF($AB29="18",Y29+IFERROR(_xlfn.XLOOKUP($AC29,$B:$B,Y:Y),0),Y29) -> 119 | AH29: =IF($AB29="18",Z29+IFERROR(_xlfn.XLOOKUP($AC29,$B:$B,Z:Z),0),Z29) -> 108 | AI29: =IF($AB29="18",AA29+IFERROR(_xlfn.XLOOKUP($AC29,$B:$B,AA:AA),0),AA29) -> 97 | AJ29: =IF($AB29="17",0,MAX(0,-AD29)) -> 0 | AK29: =IF($AB29="17",0,MAX(0,MAX(0,-AE29)-MAX(0,-AD29))) -> 0 | AL29: =IF($AB29="17",0,MAX(0,MAX(0,-AF29)-MAX(0,-AE29))) -> 0 | AM29: =IF($AB29="17",0,MAX(0,MAX(0,-AG29)-MAX(0,-AF29))) -> 0 | AN29: =IF($AB29="17",0,MAX(0,MAX(0,-AH29)-MAX(0,-AG29))) -> 0 | AO29: =IF($AB29="17",0,MAX(0,MAX(0,-AI29)-MAX(0,-AH29))) -> 0 | AR29: =IFERROR(_xlfn.XLOOKUP(B29,#REF!,#REF!),"") | AS29: =IF($AR29="A",AJ29*1.2,IF($AR29="B",AJ29*1.1,AJ29)) -> 0 | AT29: =IF($AR29="A",AK29*1.2,IF($AR29="B",AK29*1.1,AK29)) -> 0 | AU29: =IF($AR29="A",AL29*1.2,IF($AR29="B",AL29*1.1,AL29)) -> 0 | AV29: =IF($AR29="A",AM29*1.2,IF($AR29="B",AM29*1.1,AM29)) -> 0 | AW29: =IF($AR29="A",AN29*1.2,IF($AR29="B",AN29*1.1,AN29)) -> 0 | AX29: =IF($AR29="A",AO29*1.2,IF($AR29="B",AO29*1.1,AO29)) -> 0 | BA29: =SUMIF(Consenso!$C:$C,$B29,Consenso!AZ:AZ) -> 13176.36 | BB29: =SUMIF(Consenso!$C:$C,$B29,Consenso!BA:BA) -> 4262.94 | BC29: =SUMIF(Consenso!$C:$C,$B29,Consenso!BB:BB) -> 4262.94 | BD29: =SUMIF(Consenso!$C:$C,$B29,Consenso!BC:BC) -> 4262.94 | BE29: =SUMIF(Consenso!$C:$C,$B29,Consenso!BD:BD) -> 4262.94 | BF29: =SUMIF(Consenso!$C:$C,$B29,Consenso!BE:BE) -> 4262.94
A30: Speck | B30: 150958-D143 | C30: Speck Presidio2 Grip + MS iPhone 17 Black | D30: iPhone 17 | E30: Descontinuado | F30: 13 | G30: 0 | H30: =SUMIF(Consenso!$C:$C,$B30,Consenso!AM:AM) -> 0 | I30: =SUMIF(Consenso!$C:$C,$B30,Consenso!AN:AN) -> 0 | J30: =SUMIF(Consenso!$C:$C,$B30,Consenso!AO:AO) -> 0 | K30: =SUMIF(Consenso!$C:$C,$B30,Consenso!AP:AP) -> 0 | L30: =SUMIF(Consenso!$C:$C,$B30,Consenso!AQ:AQ) -> 0 | M30: =SUMIF(Consenso!$C:$C,$B30,Consenso!AR:AR) -> 0 | N30: =IFERROR(VLOOKUP(B:B,Consenso!C:P,14,0),0) -> 253 | O30: =SUMIF('On Orders'!$B:$B,$B30,'On Orders'!E:E) -> 0 | P30: =SUMIF('On Orders'!$B:$B,$B30,'On Orders'!F:F) -> 0 | Q30: =SUMIF('On Orders'!$B:$B,$B30,'On Orders'!G:G) -> 0 | R30: =SUMIF('On Orders'!$B:$B,$B30,'On Orders'!H:H) -> 0 | S30: 0 | T30: 0 | U30: 0 | V30: =(N30+O30+P30)-H30 -> 253 | W30: =(V30+Q30)-I30 -> 253 | X30: =(W30+R30)-J30 -> 253 | Y30: =(X30+S30)-K30 -> 253 | Z30: =(Y30+T30)-L30 -> 253 | AA30: =(Z30+U30)-M30 -> 253 | AB30: =IF(COUNTIF('Master iP17 iP18'!$B:$B,$B30)>0,"18",IF(COUNTIF('Master iP17 iP18'!$E:$E,$B30)>0,"17","NORMAL")) -> NORMAL | AC30: =IF($AB30="18",_xlfn.XLOOKUP($B30,'Master iP17 iP18'!$B:$B,'Master iP17 iP18'!$E:$E),"") | AD30: =IF($AB30="18",V30+IFERROR(_xlfn.XLOOKUP($AC30,$B:$B,V:V),0),V30) -> 253 | AE30: =IF($AB30="18",W30+IFERROR(_xlfn.XLOOKUP($AC30,$B:$B,W:W),0),W30) -> 253 | AF30: =IF($AB30="18",X30+IFERROR(_xlfn.XLOOKUP($AC30,$B:$B,X:X),0),X30) -> 253 | AG30: =IF($AB30="18",Y30+IFERROR(_xlfn.XLOOKUP($AC30,$B:$B,Y:Y),0),Y30) -> 253 | AH30: =IF($AB30="18",Z30+IFERROR(_xlfn.XLOOKUP($AC30,$B:$B,Z:Z),0),Z30) -> 253 | AI30: =IF($AB30="18",AA30+IFERROR(_xlfn.XLOOKUP($AC30,$B:$B,AA:AA),0),AA30) -> 253 | AJ30: =IF($AB30="17",0,MAX(0,-AD30)) -> 0 | AK30: =IF($AB30="17",0,MAX(0,MAX(0,-AE30)-MAX(0,-AD30))) -> 0 | AL30: =IF($AB30="17",0,MAX(0,MAX(0,-AF30)-MAX(0,-AE30))) -> 0 | AM30: =IF($AB30="17",0,MAX(0,MAX(0,-AG30)-MAX(0,-AF30))) -> 0 | AN30: =IF($AB30="17",0,MAX(0,MAX(0,-AH30)-MAX(0,-AG30))) -> 0 | AO30: =IF($AB30="17",0,MAX(0,MAX(0,-AI30)-MAX(0,-AH30))) -> 0 | AR30: =IFERROR(_xlfn.XLOOKUP(B30,#REF!,#REF!),"") | AS30: =IF($AR30="A",AJ30*1.2,IF($AR30="B",AJ30*1.1,AJ30)) -> 0 | AT30: =IF($AR30="A",AK30*1.2,IF($AR30="B",AK30*1.1,AK30)) -> 0 | AU30: =IF($AR30="A",AL30*1.2,IF($AR30="B",AL30*1.1,AL30)) -> 0 | AV30: =IF($AR30="A",AM30*1.2,IF($AR30="B",AM30*1.1,AM30)) -> 0 | AW30: =IF($AR30="A",AN30*1.2,IF($AR30="B",AN30*1.1,AN30)) -> 0 | AX30: =IF($AR30="A",AO30*1.2,IF($AR30="B",AO30*1.1,AO30)) -> 0 | BA30: =SUMIF(Consenso!$C:$C,$B30,Consenso!AZ:AZ) -> 0 | BB30: =SUMIF(Consenso!$C:$C,$B30,Consenso!BA:BA) -> 0 | BC30: =SUMIF(Consenso!$C:$C,$B30,Consenso!BB:BB) -> 0 | BD30: =SUMIF(Consenso!$C:$C,$B30,Consenso!BC:BC) -> 0 | BE30: =SUMIF(Consenso!$C:$C,$B30,Consenso!BD:BD) -> 0 | BF30: =SUMIF(Consenso!$C:$C,$B30,Consenso!BE:BE) -> 0
A31: Speck | B31: 150972-3240 | C31: Speck Presidio Perfect-Clear iPhone 17 Pro Clear | D31: iPhone 17 Pro | E31: Activo2 | F31: 13 | G31: 0 | H31: =SUMIF(Consenso!$C:$C,$B31,Consenso!AM:AM) -> 58 | I31: =SUMIF(Consenso!$C:$C,$B31,Consenso!AN:AN) -> 25 | J31: =SUMIF(Consenso!$C:$C,$B31,Consenso!AO:AO) -> 0 | K31: =SUMIF(Consenso!$C:$C,$B31,Consenso!AP:AP) -> 0 | L31: =SUMIF(Consenso!$C:$C,$B31,Consenso!AQ:AQ) -> 0 | M31: =SUMIF(Consenso!$C:$C,$B31,Consenso!AR:AR) -> 0 | N31: =IFERROR(VLOOKUP(B:B,Consenso!C:P,14,0),0) -> 98 | O31: =SUMIF('On Orders'!$B:$B,$B31,'On Orders'!E:E) -> 0 | P31: =SUMIF('On Orders'!$B:$B,$B31,'On Orders'!F:F) -> 0 | Q31: =SUMIF('On Orders'!$B:$B,$B31,'On Orders'!G:G) -> 0 | R31: =SUMIF('On Orders'!$B:$B,$B31,'On Orders'!H:H) -> 0 | S31: 0 | T31: 0 | U31: 0 | V31: =(N31+O31+P31)-H31 -> 40 | W31: =(V31+Q31)-I31 -> 15 | X31: =(W31+R31)-J31 -> 15 | Y31: =(X31+S31)-K31 -> 15 | Z31: =(Y31+T31)-L31 -> 15 | AA31: =(Z31+U31)-M31 -> 15 | AB31: =IF(COUNTIF('Master iP17 iP18'!$B:$B,$B31)>0,"18",IF(COUNTIF('Master iP17 iP18'!$E:$E,$B31)>0,"17","NORMAL")) -> 17 | AC31: =IF($AB31="18",_xlfn.XLOOKUP($B31,'Master iP17 iP18'!$B:$B,'Master iP17 iP18'!$E:$E),"") | AD31: =IF($AB31="18",V31+IFERROR(_xlfn.XLOOKUP($AC31,$B:$B,V:V),0),V31) -> 40 | AE31: =IF($AB31="18",W31+IFERROR(_xlfn.XLOOKUP($AC31,$B:$B,W:W),0),W31) -> 15 | AF31: =IF($AB31="18",X31+IFERROR(_xlfn.XLOOKUP($AC31,$B:$B,X:X),0),X31) -> 15 | AG31: =IF($AB31="18",Y31+IFERROR(_xlfn.XLOOKUP($AC31,$B:$B,Y:Y),0),Y31) -> 15 | AH31: =IF($AB31="18",Z31+IFERROR(_xlfn.XLOOKUP($AC31,$B:$B,Z:Z),0),Z31) -> 15 | AI31: =IF($AB31="18",AA31+IFERROR(_xlfn.XLOOKUP($AC31,$B:$B,AA:AA),0),AA31) -> 15 | AJ31: =IF($AB31="17",0,MAX(0,-AD31)) -> 0 | AK31: =IF($AB31="17",0,MAX(0,MAX(0,-AE31)-MAX(0,-AD31))) -> 0 | AL31: =IF($AB31="17",0,MAX(0,MAX(0,-AF31)-MAX(0,-AE31))) -> 0 | AM31: =IF($AB31="17",0,MAX(0,MAX(0,-AG31)-MAX(0,-AF31))) -> 0 | AN31: =IF($AB31="17",0,MAX(0,MAX(0,-AH31)-MAX(0,-AG31))) -> 0 | AO31: =IF($AB31="17",0,MAX(0,MAX(0,-AI31)-MAX(0,-AH31))) -> 0 | AR31: =IFERROR(_xlfn.XLOOKUP(B31,#REF!,#REF!),"") | AS31: =IF($AR31="A",AJ31*1.2,IF($AR31="B",AJ31*1.1,AJ31)) -> 0 | AT31: =IF($AR31="A",AK31*1.2,IF($AR31="B",AK31*1.1,AK31)) -> 0 | AU31: =IF($AR31="A",AL31*1.2,IF($AR31="B",AL31*1.1,AL31)) -> 0 | AV31: =IF($AR31="A",AM31*1.2,IF($AR31="B",AM31*1.1,AM31)) -> 0 | AW31: =IF($AR31="A",AN31*1.2,IF($AR31="B",AN31*1.1,AN31)) -> 0 | AX31: =IF($AR31="A",AO31*1.2,IF($AR31="B",AO31*1.1,AO31)) -> 0 | BA31: =SUMIF(Consenso!$C:$C,$B31,Consenso!AZ:AZ) -> 227809.05 | BB31: =SUMIF(Consenso!$C:$C,$B31,Consenso!BA:BA) -> 185343.31 | BC31: =SUMIF(Consenso!$C:$C,$B31,Consenso!BB:BB) -> 90576.91 | BD31: =SUMIF(Consenso!$C:$C,$B31,Consenso!BC:BC) -> 148449.55 | BE31: =SUMIF(Consenso!$C:$C,$B31,Consenso!BD:BD) -> 143058.47 | BF31: =SUMIF(Consenso!$C:$C,$B31,Consenso!BE:BE) -> 123771.92
A32: Speck | B32: 150975-D143 | C32: Speck Presidio2 + MS iPhone 17 Pro Black/Slate Grey/White | D32: iPhone 17 Pro | E32: Descontinuado | F32: 13 | G32: 0 | H32: =SUMIF(Consenso!$C:$C,$B32,Consenso!AM:AM) -> 36 | I32: =SUMIF(Consenso!$C:$C,$B32,Consenso!AN:AN) -> 0 | J32: =SUMIF(Consenso!$C:$C,$B32,Consenso!AO:AO) -> 0 | K32: =SUMIF(Consenso!$C:$C,$B32,Consenso!AP:AP) -> 0 | L32: =SUMIF(Consenso!$C:$C,$B32,Consenso!AQ:AQ) -> 0 | M32: =SUMIF(Consenso!$C:$C,$B32,Consenso!AR:AR) -> 0 | N32: =IFERROR(VLOOKUP(B:B,Consenso!C:P,14,0),0) -> 111 | O32: =SUMIF('On Orders'!$B:$B,$B32,'On Orders'!E:E) -> 0 | P32: =SUMIF('On Orders'!$B:$B,$B32,'On Orders'!F:F) -> 0 | Q32: =SUMIF('On Orders'!$B:$B,$B32,'On Orders'!G:G) -> 0 | R32: =SUMIF('On Orders'!$B:$B,$B32,'On Orders'!H:H) -> 0 | S32: 0 | T32: 0 | U32: 0 | V32: =(N32+O32+P32)-H32 -> 75 | W32: =(V32+Q32)-I32 -> 75 | X32: =(W32+R32)-J32 -> 75 | Y32: =(X32+S32)-K32 -> 75 | Z32: =(Y32+T32)-L32 -> 75 | AA32: =(Z32+U32)-M32 -> 75 | AB32: =IF(COUNTIF('Master iP17 iP18'!$B:$B,$B32)>0,"18",IF(COUNTIF('Master iP17 iP18'!$E:$E,$B32)>0,"17","NORMAL")) -> NORMAL | AC32: =IF($AB32="18",_xlfn.XLOOKUP($B32,'Master iP17 iP18'!$B:$B,'Master iP17 iP18'!$E:$E),"") | AD32: =IF($AB32="18",V32+IFERROR(_xlfn.XLOOKUP($AC32,$B:$B,V:V),0),V32) -> 75 | AE32: =IF($AB32="18",W32+IFERROR(_xlfn.XLOOKUP($AC32,$B:$B,W:W),0),W32) -> 75 | AF32: =IF($AB32="18",X32+IFERROR(_xlfn.XLOOKUP($AC32,$B:$B,X:X),0),X32) -> 75 | AG32: =IF($AB32="18",Y32+IFERROR(_xlfn.XLOOKUP($AC32,$B:$B,Y:Y),0),Y32) -> 75 | AH32: =IF($AB32="18",Z32+IFERROR(_xlfn.XLOOKUP($AC32,$B:$B,Z:Z),0),Z32) -> 75 | AI32: =IF($AB32="18",AA32+IFERROR(_xlfn.XLOOKUP($AC32,$B:$B,AA:AA),0),AA32) -> 75 | AJ32: =IF($AB32="17",0,MAX(0,-AD32)) -> 0 | AK32: =IF($AB32="17",0,MAX(0,MAX(0,-AE32)-MAX(0,-AD32))) -> 0 | AL32: =IF($AB32="17",0,MAX(0,MAX(0,-AF32)-MAX(0,-AE32))) -> 0 | AM32: =IF($AB32="17",0,MAX(0,MAX(0,-AG32)-MAX(0,-AF32))) -> 0 | AN32: =IF($AB32="17",0,MAX(0,MAX(0,-AH32)-MAX(0,-AG32))) -> 0 | AO32: =IF($AB32="17",0,MAX(0,MAX(0,-AI32)-MAX(0,-AH32))) -> 0 | AR32: =IFERROR(_xlfn.XLOOKUP(B32,#REF!,#REF!),"") | AS32: =IF($AR32="A",AJ32*1.2,IF($AR32="B",AJ32*1.1,AJ32)) -> 0 | AT32: =IF($AR32="A",AK32*1.2,IF($AR32="B",AK32*1.1,AK32)) -> 0 | AU32: =IF($AR32="A",AL32*1.2,IF($AR32="B",AL32*1.1,AL32)) -> 0 | AV32: =IF($AR32="A",AM32*1.2,IF($AR32="B",AM32*1.1,AM32)) -> 0 | AW32: =IF($AR32="A",AN32*1.2,IF($AR32="B",AN32*1.1,AN32)) -> 0 | AX32: =IF($AR32="A",AO32*1.2,IF($AR32="B",AO32*1.1,AO32)) -> 0 | BA32: =SUMIF(Consenso!$C:$C,$B32,Consenso!AZ:AZ) -> 13951.44 | BB32: =SUMIF(Consenso!$C:$C,$B32,Consenso!BA:BA) -> 0 | BC32: =SUMIF(Consenso!$C:$C,$B32,Consenso!BB:BB) -> 0 | BD32: =SUMIF(Consenso!$C:$C,$B32,Consenso!BC:BC) -> 0 | BE32: =SUMIF(Consenso!$C:$C,$B32,Consenso!BD:BD) -> 0 | BF32: =SUMIF(Consenso!$C:$C,$B32,Consenso!BE:BE) -> 0
A33: Speck | B33: 150976-D143 | C33: Speck Presidio2 Grip + MS iPhone 17 Pro Black | D33: iPhone 17 Pro | E33: Descontinuado | F33: 13 | G33: 0 | H33: =SUMIF(Consenso!$C:$C,$B33,Consenso!AM:AM) -> 55 | I33: =SUMIF(Consenso!$C:$C,$B33,Consenso!AN:AN) -> 4 | J33: =SUMIF(Consenso!$C:$C,$B33,Consenso!AO:AO) -> 130 | K33: =SUMIF(Consenso!$C:$C,$B33,Consenso!AP:AP) -> 0 | L33: =SUMIF(Consenso!$C:$C,$B33,Consenso!AQ:AQ) -> 0 | M33: =SUMIF(Consenso!$C:$C,$B33,Consenso!AR:AR) -> 0 | N33: =IFERROR(VLOOKUP(B:B,Consenso!C:P,14,0),0) -> 166 | O33: =SUMIF('On Orders'!$B:$B,$B33,'On Orders'!E:E) -> 0 | P33: =SUMIF('On Orders'!$B:$B,$B33,'On Orders'!F:F) -> 0 | Q33: =SUMIF('On Orders'!$B:$B,$B33,'On Orders'!G:G) -> 0 | R33: =SUMIF('On Orders'!$B:$B,$B33,'On Orders'!H:H) -> 0 | S33: 0 | T33: 0 | U33: 0 | V33: =(N33+O33+P33)-H33 -> 111 | W33: =(V33+Q33)-I33 -> 107 | X33: =(W33+R33)-J33 -> -23 | Y33: =(X33+S33)-K33 -> -23 | Z33: =(Y33+T33)-L33 -> -23 | AA33: =(Z33+U33)-M33 -> -23 | AB33: =IF(COUNTIF('Master iP17 iP18'!$B:$B,$B33)>0,"18",IF(COUNTIF('Master iP17 iP18'!$E:$E,$B33)>0,"17","NORMAL")) -> 17 | AC33: =IF($AB33="18",_xlfn.XLOOKUP($B33,'Master iP17 iP18'!$B:$B,'Master iP17 iP18'!$E:$E),"") | AD33: =IF($AB33="18",V33+IFERROR(_xlfn.XLOOKUP($AC33,$B:$B,V:V),0),V33) -> 111 | AE33: =IF($AB33="18",W33+IFERROR(_xlfn.XLOOKUP($AC33,$B:$B,W:W),0),W33) -> 107 | AF33: =IF($AB33="18",X33+IFERROR(_xlfn.XLOOKUP($AC33,$B:$B,X:X),0),X33) -> -23 | AG33: =IF($AB33="18",Y33+IFERROR(_xlfn.XLOOKUP($AC33,$B:$B,Y:Y),0),Y33) -> -23 | AH33: =IF($AB33="18",Z33+IFERROR(_xlfn.XLOOKUP($AC33,$B:$B,Z:Z),0),Z33) -> -23 | AI33: =IF($AB33="18",AA33+IFERROR(_xlfn.XLOOKUP($AC33,$B:$B,AA:AA),0),AA33) -> -23 | AJ33: =IF($AB33="17",0,MAX(0,-AD33)) -> 0 | AK33: =IF($AB33="17",0,MAX(0,MAX(0,-AE33)-MAX(0,-AD33))) -> 0 | AL33: =IF($AB33="17",0,MAX(0,MAX(0,-AF33)-MAX(0,-AE33))) -> 0 | AM33: =IF($AB33="17",0,MAX(0,MAX(0,-AG33)-MAX(0,-AF33))) -> 0 | AN33: =IF($AB33="17",0,MAX(0,MAX(0,-AH33)-MAX(0,-AG33))) -> 0 | AO33: =IF($AB33="17",0,MAX(0,MAX(0,-AI33)-MAX(0,-AH33))) -> 0 | AR33: =IFERROR(_xlfn.XLOOKUP(B33,#REF!,#REF!),"") | AS33: =IF($AR33="A",AJ33*1.2,IF($AR33="B",AJ33*1.1,AJ33)) -> 0 | AT33: =IF($AR33="A",AK33*1.2,IF($AR33="B",AK33*1.1,AK33)) -> 0 | AU33: =IF($AR33="A",AL33*1.2,IF($AR33="B",AL33*1.1,AL33)) -> 0 | AV33: =IF($AR33="A",AM33*1.2,IF($AR33="B",AM33*1.1,AM33)) -> 0 | AW33: =IF($AR33="A",AN33*1.2,IF($AR33="B",AN33*1.1,AN33)) -> 0 | AX33: =IF($AR33="A",AO33*1.2,IF($AR33="B",AO33*1.1,AO33)) -> 0 | BA33: =SUMIF(Consenso!$C:$C,$B33,Consenso!AZ:AZ) -> 21314.7 | BB33: =SUMIF(Consenso!$C:$C,$B33,Consenso!BA:BA) -> 1550.16 | BC33: =SUMIF(Consenso!$C:$C,$B33,Consenso!BB:BB) -> 50380.2 | BD33: =SUMIF(Consenso!$C:$C,$B33,Consenso!BC:BC) -> 0 | BE33: =SUMIF(Consenso!$C:$C,$B33,Consenso!BD:BD) -> 0 | BF33: =SUMIF(Consenso!$C:$C,$B33,Consenso!BE:BE) -> 0
A34: Speck | B34: 150978-9221 | C34: Speck Presidio Lux iPhone 17 Pro Glitter/Gold | D34: iPhone 17 Pro | E34: Descontinuado | F34: 13 | G34: 0 | H34: =SUMIF(Consenso!$C:$C,$B34,Consenso!AM:AM) -> 0 | I34: =SUMIF(Consenso!$C:$C,$B34,Consenso!AN:AN) -> 0 | J34: =SUMIF(Consenso!$C:$C,$B34,Consenso!AO:AO) -> 0 | K34: =SUMIF(Consenso!$C:$C,$B34,Consenso!AP:AP) -> 0 | L34: =SUMIF(Consenso!$C:$C,$B34,Consenso!AQ:AQ) -> 0 | M34: =SUMIF(Consenso!$C:$C,$B34,Consenso!AR:AR) -> 0 | N34: =IFERROR(VLOOKUP(B:B,Consenso!C:P,14,0),0) -> 82 | O34: =SUMIF('On Orders'!$B:$B,$B34,'On Orders'!E:E) -> 0 | P34: =SUMIF('On Orders'!$B:$B,$B34,'On Orders'!F:F) -> 0 | Q34: =SUMIF('On Orders'!$B:$B,$B34,'On Orders'!G:G) -> 0 | R34: =SUMIF('On Orders'!$B:$B,$B34,'On Orders'!H:H) -> 0 | S34: 0 | T34: 0 | U34: 0 | V34: =(N34+O34+P34)-H34 -> 82 | W34: =(V34+Q34)-I34 -> 82 | X34: =(W34+R34)-J34 -> 82 | Y34: =(X34+S34)-K34 -> 82 | Z34: =(Y34+T34)-L34 -> 82 | AA34: =(Z34+U34)-M34 -> 82 | AB34: =IF(COUNTIF('Master iP17 iP18'!$B:$B,$B34)>0,"18",IF(COUNTIF('Master iP17 iP18'!$E:$E,$B34)>0,"17","NORMAL")) -> 17 | AC34: =IF($AB34="18",_xlfn.XLOOKUP($B34,'Master iP17 iP18'!$B:$B,'Master iP17 iP18'!$E:$E),"") | AD34: =IF($AB34="18",V34+IFERROR(_xlfn.XLOOKUP($AC34,$B:$B,V:V),0),V34) -> 82 | AE34: =IF($AB34="18",W34+IFERROR(_xlfn.XLOOKUP($AC34,$B:$B,W:W),0),W34) -> 82 | AF34: =IF($AB34="18",X34+IFERROR(_xlfn.XLOOKUP($AC34,$B:$B,X:X),0),X34) -> 82 | AG34: =IF($AB34="18",Y34+IFERROR(_xlfn.XLOOKUP($AC34,$B:$B,Y:Y),0),Y34) -> 82 | AH34: =IF($AB34="18",Z34+IFERROR(_xlfn.XLOOKUP($AC34,$B:$B,Z:Z),0),Z34) -> 82 | AI34: =IF($AB34="18",AA34+IFERROR(_xlfn.XLOOKUP($AC34,$B:$B,AA:AA),0),AA34) -> 82 | AJ34: =IF($AB34="17",0,MAX(0,-AD34)) -> 0 | AK34: =IF($AB34="17",0,MAX(0,MAX(0,-AE34)-MAX(0,-AD34))) -> 0 | AL34: =IF($AB34="17",0,MAX(0,MAX(0,-AF34)-MAX(0,-AE34))) -> 0 | AM34: =IF($AB34="17",0,MAX(0,MAX(0,-AG34)-MAX(0,-AF34))) -> 0 | AN34: =IF($AB34="17",0,MAX(0,MAX(0,-AH34)-MAX(0,-AG34))) -> 0 | AO34: =IF($AB34="17",0,MAX(0,MAX(0,-AI34)-MAX(0,-AH34))) -> 0 | AR34: =IFERROR(_xlfn.XLOOKUP(B34,#REF!,#REF!),"") | AS34: =IF($AR34="A",AJ34*1.2,IF($AR34="B",AJ34*1.1,AJ34)) -> 0 | AT34: =IF($AR34="A",AK34*1.2,IF($AR34="B",AK34*1.1,AK34)) -> 0 | AU34: =IF($AR34="A",AL34*1.2,IF($AR34="B",AL34*1.1,AL34)) -> 0 | AV34: =IF($AR34="A",AM34*1.2,IF($AR34="B",AM34*1.1,AM34)) -> 0 | AW34: =IF($AR34="A",AN34*1.2,IF($AR34="B",AN34*1.1,AN34)) -> 0 | AX34: =IF($AR34="A",AO34*1.2,IF($AR34="B",AO34*1.1,AO34)) -> 0 | BA34: =SUMIF(Consenso!$C:$C,$B34,Consenso!AZ:AZ) -> 15665.5 | BB34: =SUMIF(Consenso!$C:$C,$B34,Consenso!BA:BA) -> 27645 | BC34: =SUMIF(Consenso!$C:$C,$B34,Consenso!BB:BB) -> 36860 | BD34: =SUMIF(Consenso!$C:$C,$B34,Consenso!BC:BC) -> 32252.5 | BE34: =SUMIF(Consenso!$C:$C,$B34,Consenso!BD:BD) -> 34556.25 | BF34: =SUMIF(Consenso!$C:$C,$B34,Consenso!BE:BE) -> 34556.25
A35: Speck | B35: 150981-3240 | C35: Speck Presidio Perfect-Clear iPhone 17 Pro Max Clear | D35: iPhone 17 Pro Max | E35: Descontinuado | F35: 13 | G35: 0 | H35: =SUMIF(Consenso!$C:$C,$B35,Consenso!AM:AM) -> 2 | I35: =SUMIF(Consenso!$C:$C,$B35,Consenso!AN:AN) -> 70 | J35: =SUMIF(Consenso!$C:$C,$B35,Consenso!AO:AO) -> 0 | K35: =SUMIF(Consenso!$C:$C,$B35,Consenso!AP:AP) -> 0 | L35: =SUMIF(Consenso!$C:$C,$B35,Consenso!AQ:AQ) -> 0 | M35: =SUMIF(Consenso!$C:$C,$B35,Consenso!AR:AR) -> 0 | N35: =IFERROR(VLOOKUP(B:B,Consenso!C:P,14,0),0) -> 0 | O35: =SUMIF('On Orders'!$B:$B,$B35,'On Orders'!E:E) -> 0 | P35: =SUMIF('On Orders'!$B:$B,$B35,'On Orders'!F:F) -> 0 | Q35: =SUMIF('On Orders'!$B:$B,$B35,'On Orders'!G:G) -> 0 | R35: =SUMIF('On Orders'!$B:$B,$B35,'On Orders'!H:H) -> 0 | S35: 0 | T35: 0 | U35: 0 | V35: =(N35+O35+P35)-H35 -> -2 | W35: =(V35+Q35)-I35 -> -72 | X35: =(W35+R35)-J35 -> -72 | Y35: =(X35+S35)-K35 -> -72 | Z35: =(Y35+T35)-L35 -> -72 | AA35: =(Z35+U35)-M35 -> -72 | AB35: =IF(COUNTIF('Master iP17 iP18'!$B:$B,$B35)>0,"18",IF(COUNTIF('Master iP17 iP18'!$E:$E,$B35)>0,"17","NORMAL")) -> 17 | AC35: =IF($AB35="18",_xlfn.XLOOKUP($B35,'Master iP17 iP18'!$B:$B,'Master iP17 iP18'!$E:$E),"") | AD35: =IF($AB35="18",V35+IFERROR(_xlfn.XLOOKUP($AC35,$B:$B,V:V),0),V35) -> -2 | AE35: =IF($AB35="18",W35+IFERROR(_xlfn.XLOOKUP($AC35,$B:$B,W:W),0),W35) -> -72 | AF35: =IF($AB35="18",X35+IFERROR(_xlfn.XLOOKUP($AC35,$B:$B,X:X),0),X35) -> -72 | AG35: =IF($AB35="18",Y35+IFERROR(_xlfn.XLOOKUP($AC35,$B:$B,Y:Y),0),Y35) -> -72 | AH35: =IF($AB35="18",Z35+IFERROR(_xlfn.XLOOKUP($AC35,$B:$B,Z:Z),0),Z35) -> -72 | AI35: =IF($AB35="18",AA35+IFERROR(_xlfn.XLOOKUP($AC35,$B:$B,AA:AA),0),AA35) -> -72 | AJ35: =IF($AB35="17",0,MAX(0,-AD35)) -> 0 | AK35: =IF($AB35="17",0,MAX(0,MAX(0,-AE35)-MAX(0,-AD35))) -> 0 | AL35: =IF($AB35="17",0,MAX(0,MAX(0,-AF35)-MAX(0,-AE35))) -> 0 | AM35: =IF($AB35="17",0,MAX(0,MAX(0,-AG35)-MAX(0,-AF35))) -> 0 | AN35: =IF($AB35="17",0,MAX(0,MAX(0,-AH35)-MAX(0,-AG35))) -> 0 | AO35: =IF($AB35="17",0,MAX(0,MAX(0,-AI35)-MAX(0,-AH35))) -> 0 | AR35: =IFERROR(_xlfn.XLOOKUP(B35,#REF!,#REF!),"") | AS35: =IF($AR35="A",AJ35*1.2,IF($AR35="B",AJ35*1.1,AJ35)) -> 0 | AT35: =IF($AR35="A",AK35*1.2,IF($AR35="B",AK35*1.1,AK35)) -> 0 | AU35: =IF($AR35="A",AL35*1.2,IF($AR35="B",AL35*1.1,AL35)) -> 0 | AV35: =IF($AR35="A",AM35*1.2,IF($AR35="B",AM35*1.1,AM35)) -> 0 | AW35: =IF($AR35="A",AN35*1.2,IF($AR35="B",AN35*1.1,AN35)) -> 0 | AX35: =IF($AR35="A",AO35*1.2,IF($AR35="B",AO35*1.1,AO35)) -> 0 | BA35: =SUMIF(Consenso!$C:$C,$B35,Consenso!AZ:AZ) -> 39938.83 | BB35: =SUMIF(Consenso!$C:$C,$B35,Consenso!BA:BA) -> 73202.8 | BC35: =SUMIF(Consenso!$C:$C,$B35,Consenso!BB:BB) -> 0 | BD35: =SUMIF(Consenso!$C:$C,$B35,Consenso!BC:BC) -> 0 | BE35: =SUMIF(Consenso!$C:$C,$B35,Consenso!BD:BD) -> 0 | BF35: =SUMIF(Consenso!$C:$C,$B35,Consenso!BE:BE) -> 0
A36: Speck | B36: 150984-D143 | C36: Speck Presidio2 + MS iPhone 17 Pro Max Black/Slate Grey/White | D36: iPhone 17 Pro Max | E36: Descontinuado | F36: 13 | G36: 0 | H36: =SUMIF(Consenso!$C:$C,$B36,Consenso!AM:AM) -> 0 | I36: =SUMIF(Consenso!$C:$C,$B36,Consenso!AN:AN) -> 0 | J36: =SUMIF(Consenso!$C:$C,$B36,Consenso!AO:AO) -> 0 | K36: =SUMIF(Consenso!$C:$C,$B36,Consenso!AP:AP) -> 0 | L36: =SUMIF(Consenso!$C:$C,$B36,Consenso!AQ:AQ) -> 0 | M36: =SUMIF(Consenso!$C:$C,$B36,Consenso!AR:AR) -> 0 | N36: =IFERROR(VLOOKUP(B:B,Consenso!C:P,14,0),0) -> 0 | O36: =SUMIF('On Orders'!$B:$B,$B36,'On Orders'!E:E) -> 0 | P36: =SUMIF('On Orders'!$B:$B,$B36,'On Orders'!F:F) -> 0 | Q36: =SUMIF('On Orders'!$B:$B,$B36,'On Orders'!G:G) -> 0 | R36: =SUMIF('On Orders'!$B:$B,$B36,'On Orders'!H:H) -> 0 | S36: 0 | T36: 0 | U36: 0 | V36: =(N36+O36+P36)-H36 -> 0 | W36: =(V36+Q36)-I36 -> 0 | X36: =(W36+R36)-J36 -> 0 | Y36: =(X36+S36)-K36 -> 0 | Z36: =(Y36+T36)-L36 -> 0 | AA36: =(Z36+U36)-M36 -> 0 | AB36: =IF(COUNTIF('Master iP17 iP18'!$B:$B,$B36)>0,"18",IF(COUNTIF('Master iP17 iP18'!$E:$E,$B36)>0,"17","NORMAL")) -> NORMAL | AC36: =IF($AB36="18",_xlfn.XLOOKUP($B36,'Master iP17 iP18'!$B:$B,'Master iP17 iP18'!$E:$E),"") | AD36: =IF($AB36="18",V36+IFERROR(_xlfn.XLOOKUP($AC36,$B:$B,V:V),0),V36) -> 0 | AE36: =IF($AB36="18",W36+IFERROR(_xlfn.XLOOKUP($AC36,$B:$B,W:W),0),W36) -> 0 | AF36: =IF($AB36="18",X36+IFERROR(_xlfn.XLOOKUP($AC36,$B:$B,X:X),0),X36) -> 0 | AG36: =IF($AB36="18",Y36+IFERROR(_xlfn.XLOOKUP($AC36,$B:$B,Y:Y),0),Y36) -> 0 | AH36: =IF($AB36="18",Z36+IFERROR(_xlfn.XLOOKUP($AC36,$B:$B,Z:Z),0),Z36) -> 0 | AI36: =IF($AB36="18",AA36+IFERROR(_xlfn.XLOOKUP($AC36,$B:$B,AA:AA),0),AA36) -> 0 | AJ36: =IF($AB36="17",0,MAX(0,-AD36)) -> 0 | AK36: =IF($AB36="17",0,MAX(0,MAX(0,-AE36)-MAX(0,-AD36))) -> 0 | AL36: =IF($AB36="17",0,MAX(0,MAX(0,-AF36)-MAX(0,-AE36))) -> 0 | AM36: =IF($AB36="17",0,MAX(0,MAX(0,-AG36)-MAX(0,-AF36))) -> 0 | AN36: =IF($AB36="17",0,MAX(0,MAX(0,-AH36)-MAX(0,-AG36))) -> 0 | AO36: =IF($AB36="17",0,MAX(0,MAX(0,-AI36)-MAX(0,-AH36))) -> 0 | AR36: =IFERROR(_xlfn.XLOOKUP(B36,#REF!,#REF!),"") | AS36: =IF($AR36="A",AJ36*1.2,IF($AR36="B",AJ36*1.1,AJ36)) -> 0 | AT36: =IF($AR36="A",AK36*1.2,IF($AR36="B",AK36*1.1,AK36)) -> 0 | AU36: =IF($AR36="A",AL36*1.2,IF($AR36="B",AL36*1.1,AL36)) -> 0 | AV36: =IF($AR36="A",AM36*1.2,IF($AR36="B",AM36*1.1,AM36)) -> 0 | AW36: =IF($AR36="A",AN36*1.2,IF($AR36="B",AN36*1.1,AN36)) -> 0 | AX36: =IF($AR36="A",AO36*1.2,IF($AR36="B",AO36*1.1,AO36)) -> 0 | BA36: =SUMIF(Consenso!$C:$C,$B36,Consenso!AZ:AZ) -> 6200.64 | BB36: =SUMIF(Consenso!$C:$C,$B36,Consenso!BA:BA) -> 0 | BC36: =SUMIF(Consenso!$C:$C,$B36,Consenso!BB:BB) -> 0 | BD36: =SUMIF(Consenso!$C:$C,$B36,Consenso!BC:BC) -> 0 | BE36: =SUMIF(Consenso!$C:$C,$B36,Consenso!BD:BD) -> 0 | BF36: =SUMIF(Consenso!$C:$C,$B36,Consenso!BE:BE) -> 0
A37: Speck | B37: 150986-D143 | C37: Speck Presidio2 Grip iPhone 17 Pro Max Black | D37: iPhone 17 Pro Max | E37: Descontinuado | F37: 13 | G37: 0 | H37: =SUMIF(Consenso!$C:$C,$B37,Consenso!AM:AM) -> 0 | I37: =SUMIF(Consenso!$C:$C,$B37,Consenso!AN:AN) -> 0 | J37: =SUMIF(Consenso!$C:$C,$B37,Consenso!AO:AO) -> 0 | K37: =SUMIF(Consenso!$C:$C,$B37,Consenso!AP:AP) -> 0 | L37: =SUMIF(Consenso!$C:$C,$B37,Consenso!AQ:AQ) -> 0 | M37: =SUMIF(Consenso!$C:$C,$B37,Consenso!AR:AR) -> 0 | N37: =IFERROR(VLOOKUP(B:B,Consenso!C:P,14,0),0) -> 0 | O37: =SUMIF('On Orders'!$B:$B,$B37,'On Orders'!E:E) -> 0 | P37: =SUMIF('On Orders'!$B:$B,$B37,'On Orders'!F:F) -> 0 | Q37: =SUMIF('On Orders'!$B:$B,$B37,'On Orders'!G:G) -> 0 | R37: =SUMIF('On Orders'!$B:$B,$B37,'On Orders'!H:H) -> 0 | S37: 0 | T37: 0 | U37: 0 | V37: =(N37+O37+P37)-H37 -> 0 | W37: =(V37+Q37)-I37 -> 0 | X37: =(W37+R37)-J37 -> 0 | Y37: =(X37+S37)-K37 -> 0 | Z37: =(Y37+T37)-L37 -> 0 | AA37: =(Z37+U37)-M37 -> 0 | AB37: =IF(COUNTIF('Master iP17 iP18'!$B:$B,$B37)>0,"18",IF(COUNTIF('Master iP17 iP18'!$E:$E,$B37)>0,"17","NORMAL")) -> 17 | AC37: =IF($AB37="18",_xlfn.XLOOKUP($B37,'Master iP17 iP18'!$B:$B,'Master iP17 iP18'!$E:$E),"") | AD37: =IF($AB37="18",V37+IFERROR(_xlfn.XLOOKUP($AC37,$B:$B,V:V),0),V37) -> 0 | AE37: =IF($AB37="18",W37+IFERROR(_xlfn.XLOOKUP($AC37,$B:$B,W:W),0),W37) -> 0 | AF37: =IF($AB37="18",X37+IFERROR(_xlfn.XLOOKUP($AC37,$B:$B,X:X),0),X37) -> 0 | AG37: =IF($AB37="18",Y37+IFERROR(_xlfn.XLOOKUP($AC37,$B:$B,Y:Y),0),Y37) -> 0 | AH37: =IF($AB37="18",Z37+IFERROR(_xlfn.XLOOKUP($AC37,$B:$B,Z:Z),0),Z37) -> 0 | AI37: =IF($AB37="18",AA37+IFERROR(_xlfn.XLOOKUP($AC37,$B:$B,AA:AA),0),AA37) -> 0 | AJ37: =IF($AB37="17",0,MAX(0,-AD37)) -> 0 | AK37: =IF($AB37="17",0,MAX(0,MAX(0,-AE37)-MAX(0,-AD37))) -> 0 | AL37: =IF($AB37="17",0,MAX(0,MAX(0,-AF37)-MAX(0,-AE37))) -> 0 | AM37: =IF($AB37="17",0,MAX(0,MAX(0,-AG37)-MAX(0,-AF37))) -> 0 | AN37: =IF($AB37="17",0,MAX(0,MAX(0,-AH37)-MAX(0,-AG37))) -> 0 | AO37: =IF($AB37="17",0,MAX(0,MAX(0,-AI37)-MAX(0,-AH37))) -> 0 | AR37: =IFERROR(_xlfn.XLOOKUP(B37,#REF!,#REF!),"") | AS37: =IF($AR37="A",AJ37*1.2,IF($AR37="B",AJ37*1.1,AJ37)) -> 0 | AT37: =IF($AR37="A",AK37*1.2,IF($AR37="B",AK37*1.1,AK37)) -> 0 | AU37: =IF($AR37="A",AL37*1.2,IF($AR37="B",AL37*1.1,AL37)) -> 0 | AV37: =IF($AR37="A",AM37*1.2,IF($AR37="B",AM37*1.1,AM37)) -> 0 | AW37: =IF($AR37="A",AN37*1.2,IF($AR37="B",AN37*1.1,AN37)) -> 0 | AX37: =IF($AR37="A",AO37*1.2,IF($AR37="B",AO37*1.1,AO37)) -> 0 | BA37: =SUMIF(Consenso!$C:$C,$B37,Consenso!AZ:AZ) -> 15665.5 | BB37: =SUMIF(Consenso!$C:$C,$B37,Consenso!BA:BA) -> 9215 | BC37: =SUMIF(Consenso!$C:$C,$B37,Consenso!BB:BB) -> 0 | BD37: =SUMIF(Consenso!$C:$C,$B37,Consenso!BC:BC) -> 0 | BE37: =SUMIF(Consenso!$C:$C,$B37,Consenso!BD:BD) -> 0 | BF37: =SUMIF(Consenso!$C:$C,$B37,Consenso!BE:BE) -> 0
A38: Speck | B38: 150987-9221 | C38: Speck Presidio Lux iPhone 17 Pro Max Glitter/Gold | D38: iPhone 17 Pro Max | E38: Descontinuado | F38: 13 | G38: 0 | H38: =SUMIF(Consenso!$C:$C,$B38,Consenso!AM:AM) -> 0 | I38: =SUMIF(Consenso!$C:$C,$B38,Consenso!AN:AN) -> 0 | J38: =SUMIF(Consenso!$C:$C,$B38,Consenso!AO:AO) -> 0 | K38: =SUMIF(Consenso!$C:$C,$B38,Consenso!AP:AP) -> 0 | L38: =SUMIF(Consenso!$C:$C,$B38,Consenso!AQ:AQ) -> 0 | M38: =SUMIF(Consenso!$C:$C,$B38,Consenso!AR:AR) -> 0 | N38: =IFERROR(VLOOKUP(B:B,Consenso!C:P,14,0),0) -> 0 | O38: =SUMIF('On Orders'!$B:$B,$B38,'On Orders'!E:E) -> 0 | P38: =SUMIF('On Orders'!$B:$B,$B38,'On Orders'!F:F) -> 0 | Q38: =SUMIF('On Orders'!$B:$B,$B38,'On Orders'!G:G) -> 0 | R38: =SUMIF('On Orders'!$B:$B,$B38,'On Orders'!H:H) -> 0 | S38: 0 | T38: 0 | U38: 0 | V38: =(N38+O38+P38)-H38 -> 0 | W38: =(V38+Q38)-I38 -> 0 | X38: =(W38+R38)-J38 -> 0 | Y38: =(X38+S38)-K38 -> 0 | Z38: =(Y38+T38)-L38 -> 0 | AA38: =(Z38+U38)-M38 -> 0 | AB38: =IF(COUNTIF('Master iP17 iP18'!$B:$B,$B38)>0,"18",IF(COUNTIF('Master iP17 iP18'!$E:$E,$B38)>0,"17","NORMAL")) -> 17 | AC38: =IF($AB38="18",_xlfn.XLOOKUP($B38,'Master iP17 iP18'!$B:$B,'Master iP17 iP18'!$E:$E),"") | AD38: =IF($AB38="18",V38+IFERROR(_xlfn.XLOOKUP($AC38,$B:$B,V:V),0),V38) -> 0 | AE38: =IF($AB38="18",W38+IFERROR(_xlfn.XLOOKUP($AC38,$B:$B,W:W),0),W38) -> 0 | AF38: =IF($AB38="18",X38+IFERROR(_xlfn.XLOOKUP($AC38,$B:$B,X:X),0),X38) -> 0 | AG38: =IF($AB38="18",Y38+IFERROR(_xlfn.XLOOKUP($AC38,$B:$B,Y:Y),0),Y38) -> 0 | AH38: =IF($AB38="18",Z38+IFERROR(_xlfn.XLOOKUP($AC38,$B:$B,Z:Z),0),Z38) -> 0 | AI38: =IF($AB38="18",AA38+IFERROR(_xlfn.XLOOKUP($AC38,$B:$B,AA:AA),0),AA38) -> 0 | AJ38: =IF($AB38="17",0,MAX(0,-AD38)) -> 0 | AK38: =IF($AB38="17",0,MAX(0,MAX(0,-AE38)-MAX(0,-AD38))) -> 0 | AL38: =IF($AB38="17",0,MAX(0,MAX(0,-AF38)-MAX(0,-AE38))) -> 0 | AM38: =IF($AB38="17",0,MAX(0,MAX(0,-AG38)-MAX(0,-AF38))) -> 0 | AN38: =IF($AB38="17",0,MAX(0,MAX(0,-AH38)-MAX(0,-AG38))) -> 0 | AO38: =IF($AB38="17",0,MAX(0,MAX(0,-AI38)-MAX(0,-AH38))) -> 0 | AR38: =IFERROR(_xlfn.XLOOKUP(B38,#REF!,#REF!),"") | AS38: =IF($AR38="A",AJ38*1.2,IF($AR38="B",AJ38*1.1,AJ38)) -> 0 | AT38: =IF($AR38="A",AK38*1.2,IF($AR38="B",AK38*1.1,AK38)) -> 0 | AU38: =IF($AR38="A",AL38*1.2,IF($AR38="B",AL38*1.1,AL38)) -> 0 | AV38: =IF($AR38="A",AM38*1.2,IF($AR38="B",AM38*1.1,AM38)) -> 0 | AW38: =IF($AR38="A",AN38*1.2,IF($AR38="B",AN38*1.1,AN38)) -> 0 | AX38: =IF($AR38="A",AO38*1.2,IF($AR38="B",AO38*1.1,AO38)) -> 0 | BA38: =SUMIF(Consenso!$C:$C,$B38,Consenso!AZ:AZ) -> 49761 | BB38: =SUMIF(Consenso!$C:$C,$B38,Consenso!BA:BA) -> 69112.5 | BC38: =SUMIF(Consenso!$C:$C,$B38,Consenso!BB:BB) -> 92150 | BD38: =SUMIF(Consenso!$C:$C,$B38,Consenso!BC:BC) -> 92150 | BE38: =SUMIF(Consenso!$C:$C,$B38,Consenso!BD:BD) -> 0 | BF38: =SUMIF(Consenso!$C:$C,$B38,Consenso!BE:BE) -> 0
A39: Speck | B39: 151117-D143 | C39: Speck iPad Mini 2026 AP 2038 | D39: iPad mini 6 | E39: New | F39: #N/A | G39: 270 | H39: =SUMIF(Consenso!$C:$C,$B39,Consenso!AM:AM) -> 0 | I39: =G39 -> 270 | J39: =SUMIF(Consenso!$C:$C,$B39,Consenso!AO:AO) -> 340 | K39: =SUMIF(Consenso!$C:$C,$B39,Consenso!AP:AP) -> 100 | L39: =SUMIF(Consenso!$C:$C,$B39,Consenso!AQ:AQ) -> 100 | M39: =SUMIF(Consenso!$C:$C,$B39,Consenso!AR:AR) -> 100 | N39: =IFERROR(VLOOKUP(B:B,Consenso!C:P,14,0),0) -> 0 | O39: =SUMIF('On Orders'!$B:$B,$B39,'On Orders'!E:E) -> 0 | P39: =SUMIF('On Orders'!$B:$B,$B39,'On Orders'!F:F) -> 0 | Q39: =SUMIF('On Orders'!$B:$B,$B39,'On Orders'!G:G) -> 0 | R39: =SUMIF('On Orders'!$B:$B,$B39,'On Orders'!H:H) -> 0 | S39: 0 | T39: 0 | U39: 0 | V39: =(N39+O39+P39)-H39 -> 0 | W39: =(V39+Q39)-I39 -> -270 | X39: =(W39+R39)-J39 -> -610 | Y39: =(X39+S39)-K39 -> -710 | Z39: =(Y39+T39)-L39 -> -810 | AA39: =(Z39+U39)-M39 -> -910 | AB39: =IF(COUNTIF('Master iP17 iP18'!$B:$B,$B39)>0,"18",IF(COUNTIF('Master iP17 iP18'!$E:$E,$B39)>0,"17","NORMAL")) -> NORMAL | AC39: =IF($AB39="18",_xlfn.XLOOKUP($B39,'Master iP17 iP18'!$B:$B,'Master iP17 iP18'!$E:$E),"") | AD39: =IF($AB39="18",V39+IFERROR(_xlfn.XLOOKUP($AC39,$B:$B,V:V),0),V39) -> 0 | AE39: =IF($AB39="18",W39+IFERROR(_xlfn.XLOOKUP($AC39,$B:$B,W:W),0),W39) -> -270 | AF39: =IF($AB39="18",X39+IFERROR(_xlfn.XLOOKUP($AC39,$B:$B,X:X),0),X39) -> -610 | AG39: =IF($AB39="18",Y39+IFERROR(_xlfn.XLOOKUP($AC39,$B:$B,Y:Y),0),Y39) -> -710 | AH39: =IF($AB39="18",Z39+IFERROR(_xlfn.XLOOKUP($AC39,$B:$B,Z:Z),0),Z39) -> -810 | AI39: =IF($AB39="18",AA39+IFERROR(_xlfn.XLOOKUP($AC39,$B:$B,AA:AA),0),AA39) -> -910 | AJ39: =IF($AB39="17",0,MAX(0,-AD39)) -> 0 | AK39: =IF($AB39="17",0,MAX(0,MAX(0,-AE39)-MAX(0,-AD39))) -> 270 | AL39: =IF($AB39="17",0,MAX(0,MAX(0,-AF39)-MAX(0,-AE39))) -> 340 | AM39: =IF($AB39="17",0,MAX(0,MAX(0,-AG39)-MAX(0,-AF39))) -> 100 | AN39: =IF($AB39="17",0,MAX(0,MAX(0,-AH39)-MAX(0,-AG39))) -> 100 | AO39: =IF($AB39="17",0,MAX(0,MAX(0,-AI39)-MAX(0,-AH39))) -> 100 | AP39: PO 450 Med Aug | AR39: =IFERROR(_xlfn.XLOOKUP(B39,#REF!,#REF!),"") | AS39: =IF($AR39="A",AJ39*1.2,IF($AR39="B",AJ39*1.1,AJ39)) -> 0 | AT39: =IF($AR39="A",AK39*1.2,IF($AR39="B",AK39*1.1,AK39)) -> 270 | AU39: =IF($AR39="A",AL39*1.2,IF($AR39="B",AL39*1.1,AL39)) -> 340 | AV39: =IF($AR39="A",AM39*1.2,IF($AR39="B",AM39*1.1,AM39)) -> 100 | AW39: =IF($AR39="A",AN39*1.2,IF($AR39="B",AN39*1.1,AN39)) -> 100 | AX39: =IF($AR39="A",AO39*1.2,IF($AR39="B",AO39*1.1,AO39)) -> 100 | AY39: PO FCST / 500 resto del año (una vez que se confrime disponiblidad volamos 240air, resto Nps? | AZ39: ETD Aug 22 | BA39: =SUMIF(Consenso!$C:$C,$B39,Consenso!AZ:AZ) -> 0 | BB39: =SUMIF(Consenso!$C:$C,$B39,Consenso!BA:BA) -> 0 | BC39: =SUMIF(Consenso!$C:$C,$B39,Consenso!BB:BB) -> 146404 | BD39: =SUMIF(Consenso!$C:$C,$B39,Consenso!BC:BC) -> 43060 | BE39: =SUMIF(Consenso!$C:$C,$B39,Consenso!BD:BD) -> 43060 | BF39: =SUMIF(Consenso!$C:$C,$B39,Consenso!BE:BE) -> 43060
